{
  "extracted_at": "2025-03-02T19:10:35.864084+00:00",
  "status": "processed",
  "context_type": "files",
  "context_name": "Knesset Bylaws (תקנון הכנסת) and related laws",
  "source_content": "**חוק חסינות חברי הכנסת, זכויותיהם וחובותיהם: **\n\n[מקור: סעיף 2א. ](https://he.wikisource.org/wiki/%D7%97%D7%95%D7%A7-%D7%99%D7%A1%D7%95%D7%93:_%D7%94%D7%9B%D7%A0%D7%A1%D7%AA#%D7%A1%D7%A2%D7%99%D7%A3_2א)\nחסינות בפני האזנת סתר[תיקון: תשס״ה, תשע״ט]\n\n(א)חבר הכנסת יהיה חסין בפני האזנת סתר.(ב)על אף האמור בסעיף קטן (א), רשאי שופט של בית המשפט העליון להתיר בצו האזנת סתר, אם שוכנע שיש יסוד לחשד שחבר הכנסת חשוד בעבירה ונתקיימו התנאים שבאחד מאלה:(1)נתבקש לכך בכתב מאת ראש רשות ביטחון, כשהעבירה היא מסוג פשע שיש בה סכנה לפגיעה בביטחון המדינה, והאזנת הסתר הכרחית מטעמי ביטחון המדינה;(2)נתבקש לכך בכתב מאת קצין משטרה מוסמך, כשהעבירה היא עבירה לפיסעיפים 300 עד 301ג לחוק העונשין, התשל״ז–1977, עבירה שיש בה סכנה לפגיעה בביטחון המדינה או עבירה של עסקת סמים כהגדרתהבפקודת הסמים המסוכנים [נוסח חדש], התשל״ג–1973, או קשר לעבור אחת העבירות האמורות, והאזנת הסתר הכרחית למניעתה או לחקירתה של העבירה.(ג)בקשה להיתר להאזנת סתר לפי סעיף קטן (ב) תוגש באישור היועץ המשפטי לממשלה.(ד)הבקשה תידון במעמד צד אחד בלבד, ומטעם המבקש יתייצב קצין בדרגת ניצב משנה ומעלה או ראש מחלקה בשירות הביטחון הכללי ומעלה שיקבע ראש השירות, לפי הענין.(ה)בהיתר יתוארו שמו ופרטי זהותו של חבר הכנסת אשר האזנה לשיחותיו הותרה, וכן זהות הקו או המיתקן המשמשים או המיועדים לשמש לקליטה, להעברה או לשידור של בזק, ואשר האזנה אליהם הותרה, ומקום השיחות או סוגן, הכל אם הם ידועים מראש; כן יפורטו דרכי ההאזנה שהותרו.(ו)בהיתר תפורש תקופת תוקפו; התקופה לא תעלה על שלושה חודשים מיום נתינת ההיתר; ההיתר ניתן לחידוש מפעם לפעם, לפי בקשה שהוגשה באישור היועץ המשפטי לממשלה.(ז)התיר שופט האזנת סתר, רשאי הוא להתיר גם כניסה למקום לצורך התקנת אמצעים הנדרשים להאזנה, פירוקם או סילוקם; פרטי המקום שאליו הותרה הכניסה יפורטו בהיתר; אין בהוראות סעיף קטן זה כדי לפגוע בהוראותסעיף 6 לחוק משכן הכנסת, רחבתו ומשמר הכנסת, התשכ״ח–1968.(ח)ניתן היתר להאזנת סתר לפי סעיף קטן (ב)(2), תהיה ההאזנה על דרך של הקלטה בלבד, אלא אם כן הורה השופט, מטעמים מיוחדים שיירשמו, על דרך אחרת, שתפורט בצו; חומר ההקלטה יועבר לעיונו של השופט שנתן את ההיתר, באופן שייקבע לענין זה לפיסעיף 9א(ג) לחוק האזנת סתר, התשל״ט–1979(בחוק זה – חוק האזנת סתר).(ט)השופט שנתן את ההיתר לפי סעיף קטן (ב)(2), ובהעדרו שופט אחר של בית המשפט העליון, רשאי להאזין להקלטה או להורות על עריכת תמליל ולעיין בו במעמד מבקש ההיתר.(י)מצא השופט כי חומר הקלטה שההאזנה אליו הותרה בסעיף קטן (ב)(2) כולל חומר הנוגע לעבירה שבשלה ניתן ההיתר, לעבירה אחרת מסוג פשע, או חומר העשוי להביא למניעתה של עבירה כאמור, יורה על העברתו של חומר זה בלבד למבקש ההיתר, בדרך שתיקבע לענין זה לפיסעיף 9א(ה) לחוק האזנת סתר; מצא השופט כי חומר ההקלטה אינו כולל חומר חקירה כאמור – יורה על הגבלת הגישה לחומר.(יא)לכל מונח בסעיף זה תהא המשמעות שיש לובחוק האזנת סתר.(יב)תקנות לפי סעיף זה יותקנו כאמורבסעיף 15 לחוק האזנת סתר, ואולם הן יותקנו באישור ועדת הכנסת במקום באישור ועדות הכנסת המנויות בו.",
  "document_type": "חוק חסינות חברי הכנסת, זכויותיהם וחובותיהם",
  "extracted_data": {
    "DocumentMetadata": {
      "DocumentTitle": "חוק חסינות חברי הכנסת, זכויותיהם וחובותיהם",
      "PublicationDate": "",
      "OfficialSource": "סעיף 2א.",
      "ReferenceLinks": [
        "https://he.wikisource.org/wiki/%D7%97%D7%95%D7%A7-%D7%99%D7%A1%D7%95%D7%93:_%D7%94%D7%9B%D7%A0%D7%A1%D7%AA#%D7%A1%D7%A2%D7%99%D7%A3_2א"
      ],
      "Language": "עברית",
      "Version": "",
      "ClauseRepresentation": "main clause",
      "OfficialRoles": [
        {
          "Role": "שופט",
          "ClauseLocation": "(ב)",
          "Quote": "שופט של בית המשפט העליון"
        },
        {
          "Role": "ראש רשות ביטחון",
          "ClauseLocation": "(ב)(1)",
          "Quote": "ראש רשות ביטחון"
        },
        {
          "Role": "קצין משטרה מוסמך",
          "ClauseLocation": "(ב)(2)",
          "Quote": "קצין משטרה מוסמך"
        },
        {
          "Role": "יועץ משפטי לממשלה",
          "ClauseLocation": "(ג)",
          "Quote": "באישור היועץ המשפטי לממשלה"
        },
        {
          "Role": "קצין בדרגת ניצב משנה ומעלה",
          "ClauseLocation": "(ד)",
          "Quote": "קצין בדרגת ניצב משנה ומעלה"
        },
        {
          "Role": "ראש מחלקה בשירות הביטחון הכללי",
          "ClauseLocation": "(ד)",
          "Quote": "ראש מחלקה בשירות הביטחון הכללי"
        }
      ],
      "OfficialOrganizations": [
        {
          "Organization": "בית המשפט העליון",
          "ClauseLocation": "(ב)",
          "Quote": "בית המשפט העליון"
        },
        {
          "Organization": "שירות הביטחון הכללי",
          "ClauseLocation": "(ד)",
          "Quote": "שירות הביטחון הכללי"
        }
      ],
      "Placenames": [],
      "Description": "החוק עוסק בחסינות חברי הכנסת בפני האזנת סתר ובתנאים להיתר האזנה."
    },
    "LegalReferences": [
      {
        "ReferenceTitle": "חוק העונשין",
        "ReferenceText": "חוק העונשין, התשל״ז–1977",
        "ReferenceQuote": "עבירה לפיסעיפים 300 עד 301ג לחוק העונשין"
      },
      {
        "ReferenceTitle": "פקודת הסמים המסוכנים",
        "ReferenceText": "פקודת הסמים המסוכנים [נוסח חדש], התשל״ג–1973",
        "ReferenceQuote": "עבירה של עסקת סמים כהגדרתהבפקודת הסמים המסוכנים"
      },
      {
        "ReferenceTitle": "חוק משכן הכנסת",
        "ReferenceText": "חוק משכן הכנסת, רחבתו ומשמר הכנסת, התשכ״ח–1968",
        "ReferenceQuote": "אין בהוראות סעיף קטן זה כדי לפגוע בהוראותסעיף 6 לחוק משכן הכנסת"
      },
      {
        "ReferenceTitle": "חוק האזנת סתר",
        "ReferenceText": "חוק האזנת סתר, התשל״ט–1979",
        "ReferenceQuote": "לכל מונח בסעיף זה תהא המשמעות שיש לובחוק האזנת סתר"
      }
    ],
    "Amendments": [
      "תיקון: תשס״ה, תשע״ט"
    ],
    "AdditionalKeywords": [
      "חסינות",
      "האזנת סתר",
      "חבר הכנסת",
      "שופט",
      "יועץ משפטי לממשלה"
    ],
    "Topics": [
      "חבר הכנסת יהיה חסין בפני האזנת סתר.",
      "שופט יכול להתיר האזנת סתר בתנאים מסוימים.",
      "בקשה להיתר להאזנת סתר תוגש באישור היועץ המשפטי לממשלה.",
      "הבקשה תידון במעמד צד אחד בלבד.",
      "בהיתר יתוארו פרטי חבר הכנסת והאמצעים המיועדים להאזנה.",
      "ההיתר לא יעלה על שלושה חודשים וניתן לחידוש.",
      "ההאזנה תהיה על דרך של הקלטה בלבד, אלא אם כן הורה השופט אחרת.",
      "חומר ההקלטה יועבר לעיונו של השופט שנתן את ההיתר."
    ]
  },
  "title": "חוק חסינות חברי הכנסת, זכויותיהם וחובותיהם",
  "source_file": "חוק חסינות חברי הכנסת, זכויותיהם וחובותיהם_2א.md"
}