{
  "extracted_at": "2025-03-02T19:21:08.314489+00:00",
  "status": "processed",
  "context_type": "files",
  "context_name": "Knesset Bylaws (תקנון הכנסת) and related laws",
  "source_content": "**חוק משכן הכנסת, רחבתו ומשמר הכנסת: **\n\n[מקור: סעיף 3. ](https://he.wikisource.org/wiki/%D7%97%D7%95%D7%A7-%D7%99%D7%A1%D7%95%D7%93:_%D7%94%D7%9B%D7%A0%D7%A1%D7%AA#%D7%A1%D7%A2%D7%99%D7%A3_3)\nכניסה לכנסת[תיקון: תשמ״ז, תשנ״ו, תשע״ו]\n\n(א)יושב־ראש הכנסת, לאחר התייעצות עם הסגנים, רשאי לקבוע שטחים בתוך משכן הכנסת והרחבה שהכניסה אליהם מותרת ושטחים האסורים בכניסה.פורסמותקנות משכן הכנסת ורחבתו (שטחים מותרים ואסורים בכניסה), התשכ״ח–1968.(ב)אדם רשאי להיכנס לשטח במשכן הכנסת או ברחבה שהכניסה אליו נאסרה לפי סעיף קטן (א) אם יש בידו היתר שניתן מאת יושב־ראש הכנסת או מטעמו, ויושב־ראש הכנסת רשאי לתת היתרים מסוגים שונים, בין כלליים ובין מיוחדים.(ג)יושב ראש הכנסת או מי שהוא הסמיך לענין היתרים לפי סעיף קטן (ב) רשאי להביא בחשבון את עברו הפלילי של מבקש ההיתר לגבי עבירות לפי –(1)פרק ז׳,סימנים א׳,א׳1,ב׳,ז׳ו־ט׳ לפרק ח׳,סימן ג׳ לפרק ט׳וסימנים א׳,ד׳,ה׳,ז׳,ו־ח׳ לפרק י׳ של חוק העונשין, התשל״ז–1977;(2)תקנות ההגנה (שעת חירום), 1945;(3)פקודת מניעת טרור, התש״ח–1948;(4)חוק למניעת הסתננות (עבירות ושיפוט), התשי״ד–1954;(5)חוק המאבק בטרור, התשע״ו–2016, וכן עבירות לפי חיקוק אחר שהן מעשה טרור כהגדרתובחוק האמור.",
  "document_type": "חוק משכן הכנסת, רחבתו ומשמר הכנסת",
  "extracted_data": {
    "DocumentMetadata": {
      "DocumentTitle": "חוק משכן הכנסת, רחבתו ומשמר הכנסת",
      "PublicationDate": "",
      "OfficialSource": "סעיף 3",
      "ReferenceLinks": [
        "https://he.wikisource.org/wiki/%D7%97%D7%95%D7%A7-%D7%99%D7%A1%D7%95%D7%93:_%D7%94%D7%9B%D7%A0%D7%A1%D7%AA#%D7%A1%D7%A2%D7%99%D7%A3_3"
      ],
      "Language": "עברית",
      "Version": "",
      "ClauseRepresentation": "main clause",
      "OfficialRoles": [
        {
          "Role": "יושב־ראש הכנסת",
          "ClauseLocation": "(א)",
          "Quote": "יושב־ראש הכנסת, לאחר התייעצות עם הסגנים, רשאי לקבוע שטחים בתוך משכן הכנסת והרחבה שהכניסה אליהם מותרת ושטחים האסורים בכניסה."
        }
      ],
      "OfficialOrganizations": [],
      "Placenames": [
        {
          "Name": "משכן הכנסת",
          "ClauseLocation": "(א)",
          "Quote": "שטחים בתוך משכן הכנסת והרחבה"
        }
      ],
      "Description": "החוק עוסק בקביעת שטחים מותרים ואסורים בכניסה למשכן הכנסת."
    },
    "LegalReferences": [
      {
        "ReferenceTitle": "חוק העונשין",
        "ReferenceText": "חוק העונשין, התשל״ז–1977",
        "ReferenceQuote": "עבירות לפי –(1)פרק ז׳,סימנים א׳,א׳1,ב׳,ז׳ו־ט׳ לפרק ח׳,סימן ג׳ לפרק ט׳וסימנים א׳,ד׳,ה׳,ז׳,ו׳-ח׳ לפרק י׳ של חוק העונשין, התשל״ז–1977"
      },
      {
        "ReferenceTitle": "תקנות ההגנה",
        "ReferenceText": "תקנות ההגנה (שעת חירום), 1945",
        "ReferenceQuote": "(2)תקנות ההגנה (שעת חירום), 1945"
      },
      {
        "ReferenceTitle": "פקודת מניעת טרור",
        "ReferenceText": "פקודת מניעת טרור, התש״ח–1948",
        "ReferenceQuote": "(3)פקודת מניעת טרור, התש״ח–1948"
      },
      {
        "ReferenceTitle": "חוק למניעת הסתננות",
        "ReferenceText": "חוק למניעת הסתננות (עבירות ושיפוט), התשי״ד–1954",
        "ReferenceQuote": "(4)חוק למניעת הסתננות (עבירות ושיפוט), התשי״ד–1954"
      },
      {
        "ReferenceTitle": "חוק המאבק בטרור",
        "ReferenceText": "חוק המאבק בטרור, התשע״ו–2016",
        "ReferenceQuote": "(5)חוק המאבק בטרור, התשע״ו–2016"
      }
    ],
    "Amendments": [
      "תיקון: תשמ״ז, תשנ״ו, תשע״ו"
    ],
    "AdditionalKeywords": [
      "כניסה",
      "שטחים מותרים",
      "שטחים אסורים",
      "היתרים"
    ],
    "Topics": [
      "יושב־ראש הכנסת רשאי לקבוע שטחים בתוך משכן הכנסת והרחבה שהכניסה אליהם מותרת ושטחים האסורים בכניסה.",
      "אדם רשאי להיכנס לשטח במשכן הכנסת או ברחבה שהכניסה אליו נאסרה אם יש בידו היתר.",
      "יושב ראש הכנסת רשאי להביא בחשבון את עברו הפלילי של מבקש ההיתר."
    ]
  },
  "title": "חוק משכן הכנסת, רחבתו ומשמר הכנסת",
  "source_file": "חוק משכן הכנסת, רחבתו ומשמר הכנסת_3.md"
}