{
  "extracted_at": "2025-03-02T19:17:17.565535+00:00",
  "status": "processed",
  "context_type": "files",
  "context_name": "Knesset Bylaws (תקנון הכנסת) and related laws",
  "source_content": "**חוק חסינות חברי הכנסת, זכויותיהם וחובותיהם: **\n\n[מקור: סעיף 1. ](https://he.wikisource.org/wiki/%D7%97%D7%95%D7%A7-%D7%99%D7%A1%D7%95%D7%93:_%D7%94%D7%9B%D7%A0%D7%A1%D7%AA#%D7%A1%D7%A2%D7%99%D7%A3_1)\nחסינות במילוי התפקיד[תיקון: תשס״ב־2]\n\n(א)חבר הכנסת לא ישא באחריות פלילית או אזרחית, ויהיה חסין בפני כל פעולה משפטית, בשל הצבעה, או בשל הבעת דעה בעל פה או בכתב, או בשל מעשה שעשה – בכנסת או מחוצה לה – אם היו ההצבעה, הבעת הדעה או המעשה במילוי תפקידו, או למען מילוי תפקידו, כחבר הכנסת.(א1)למען הסר ספק, מעשה לרבות התבטאות שאינם אקראיים, של חבר הכנסת שיש בהם אחד מאלה, אין רואים אותם, לענין סעיף זה, כהבעת דעה או כמעשה הנעשים במילוי תפקידו או למען מילוי תפקידו כחבר הכנסת:(1)שלילת קיומה של מדינת ישראל כמדינתו של העם היהודי;(2)שלילת אופיה הדמוקרטי של המדינה;(3)הסתה לגזענות בשל צבע או השתייכות לגזע או למוצא לאומי–אתני;(4)תמיכה במאבק מזוין של מדינת אויב או במעשי טרור נגד מדינת ישראל או נגד יהודים או ערבים בשל היותם יהודים או ערבים, בארץ או בחוץ לארץ.(ב)חבר הכנסת אינו חייב להגיד בעדות דבר שנודע לו עקב מילוי תפקידו כחבר הכנסת.(ג)חסינותו של חבר הכנסת לפי סעיף זה תעמוד לו גם לאחר שחדל מהיות חבר הכנסת.",
  "document_type": "חוק חסינות חברי הכנסת, זכויותיהם וחובותיהם",
  "extracted_data": {
    "DocumentMetadata": {
      "DocumentTitle": "חוק חסינות חברי הכנסת, זכויותיהם וחובותיהם",
      "PublicationDate": "",
      "OfficialSource": "סעיף 1",
      "ReferenceLinks": [
        "https://he.wikisource.org/wiki/%D7%97%D7%95%D7%A7-%D7%99%D7%A1%D7%95%D7%93:_%D7%94%D7%9B%D7%A0%D7%A1%D7%AA#%D7%A1%D7%A2%D7%99%D7%A3_1"
      ],
      "Language": "עברית",
      "Version": "",
      "ClauseRepresentation": "main clause",
      "OfficialRoles": [],
      "OfficialOrganizations": [],
      "Placenames": [
        {
          "Name": "מדינת ישראל",
          "ClauseLocation": "(1)",
          "Quote": "שלילת קיומה של מדינת ישראל כמדינתו של העם היהודי"
        },
        {
          "Name": "ארץ",
          "ClauseLocation": "(4)",
          "Quote": "נגד מדינת ישראל או נגד יהודים או ערבים בשל היותם יהודים או ערבים, בארץ או בחוץ לארץ"
        }
      ],
      "Description": "החוק עוסק בחסינות חברי הכנסת במילוי תפקידם ובזכויותיהם וחובותיהם."
    },
    "LegalReferences": [],
    "Amendments": [
      {
        "AmendmentText": "תיקון: תשס״ב־2",
        "AmendmentQuote": "תיקון: תשס״ב־2"
      }
    ],
    "AdditionalKeywords": [
      "חסינות",
      "חבר הכנסת",
      "אחריות פלילית",
      "אחריות אזרחית",
      "הבעת דעה",
      "מעשה",
      "הסתה לגזענות",
      "מאבק מזוין",
      "מעשי טרור"
    ],
    "Topics": [
      "חסינות חברי הכנסת במילוי תפקידם",
      "אחריות פלילית ואזרחית",
      "הגנה על חופש הביטוי של חברי הכנסת"
    ]
  },
  "title": "חוק חסינות חברי הכנסת, זכויותיהם וחובותיהם",
  "source_file": "חוק חסינות חברי הכנסת, זכויותיהם וחובותיהם_1.md"
}