{
  "extracted_at": "2025-03-02T19:28:40.250550+00:00",
  "status": "processed",
  "context_type": "files",
  "context_name": "Knesset Bylaws (תקנון הכנסת) and related laws",
  "source_content": "**חוק חסינות חברי הכנסת, זכויותיהם וחובותיהם: **\n\n[מקור: סעיף 4. ](https://he.wikisource.org/wiki/%D7%97%D7%95%D7%A7-%D7%99%D7%A1%D7%95%D7%93:_%D7%94%D7%9B%D7%A0%D7%A1%D7%AA#%D7%A1%D7%A2%D7%99%D7%A3_4)\nחסינות בפני דיון פלילי[תיקון: תשנ״ה־2, תשס״ה־2, תשע״ו־3]\n\n(א)(1)כתב אישום נגד חבר הכנסת, בעבירהשסעיף 1אינו חל עליה, שנעברה בזמן היותו חבר הכנסת או לפני שהיה לחבר הכנסת, יוגש באישור היועץ המשפטי לממשלה.(2)אישר היועץ המשפטי לממשלה הגשת כתב אישום נגד חבר הכנסת ימסור עותק ממנו, בטרם הגשתו לבית המשפט, לחבר הכנסת, ליושב ראש הכנסת וליושב ראש ועדת הכנסת.(3)חבר הכנסת רשאי, בתוך 30 ימים מיום שהומצא לו כתב האישום, לבקש שהכנסת תקבע כי תהיה לו חסינות בפני דין פלילי לגבי האשמה שבכתב האישום, בשל אחת או יותר מהעילות האלה:(א)העבירה שבה הוא מואשם נעברה במילוי תפקידו או למען מילוי תפקידו כחבר הכנסת וחלות הוראותסעיף 1;(ב)כתב האישום הוגש שלא בתום לב או תוך הפליה;(ג)התקיימו כל אלה: הכנסת או מי שמוסמך בה לכך קיימו הליכים או נקטו אמצעים לפי הדינים והכללים הנהוגים בכנסת נגד חבר הכנסת בשל המעשה המהווה עבירה לפי כתב האישום, העבירה בוצעה במשכן הכנסת במסגרת פעילות הכנסת או ועדה מוועדותיה, ואי ניהול הליך פלילי, בהתחשב בחומרת העבירה, מהותה או נסיבותיה לא יפגע פגיעה ניכרת באינטרס הציבורי;(ד)ייגרם נזק של ממש בשל ניהול ההליך הפלילי, לתפקוד הכנסת או ועדה מוועדותיה או לייצוג ציבור הבוחרים, ואי ניהול הליך כאמור, בהתחשב בחומרת העבירה, מהותה או נסיבותיה, לא יפגע פגיעה ניכרת באינטרס הציבורי.(א1)הוראות סעיף קטן (א) לא יחולו על העבירות הבאות ודינו של חבר הכנסת לענין עבירות אלה כדין כל אדם:(1)עבירת תעבורה כהגדרתהבסעיף 1 לפקודת התעבורה;(2)עבירה שנקבעה כעבירת קנס לפי כל חיקוק;(3)עבירה מינהלית שדינה קנס מינהלי קצוב.(ב)לא ביקש חבר הכנסת כאמור בסעיף קטן (א)(3) וחלפה התקופה כאמור בו, או שחזר בו מן הבקשה בהודעה בכתב ליושב ראש הכנסת וליושב ראש ועדת הכנסת, או שהודיע להם בכתב לפני חלוף התקופה האמורה שאין בכוונתו לבקש חסינות, או שהכנסת דחתה את בקשתו לפיסעיף 13(א)או שוועדת הכנסת החליטה כאמורבסעיף 13(ג1), רשאי היועץ המשפטי לממשלה להגיש את כתב האישום לבית המשפט, ודינו של חבר הכנסת, לכל הכרוך באותה אשמה, כדין כל אדם.(ג)קבעה הכנסת כי תהיה לחבר הכנסת חסינות כאמור בסעיף זה, לא יאשר היועץ המשפטי לממשלה בתקופת כהונתה של אותה כנסת הגשת כתב אישום נגד חבר הכנסת בשל אותה אשמה אלא אם כן חל שינוי בנסיבות.(ד)סעיף זה לא יחול בענין כתב אישום שהוגש בטרם היה אדם לחבר הכנסת.",
  "document_type": "חוק חסינות חברי הכנסת, זכויותיהם וחובותיהם",
  "extracted_data": {
    "DocumentMetadata": {
      "DocumentTitle": "חוק חסינות חברי הכנסת, זכויותיהם וחובותיהם",
      "PublicationDate": "",
      "OfficialSource": "סעיף 4",
      "ReferenceLinks": [
        "https://he.wikisource.org/wiki/%D7%97%D7%95%D7%A7-%D7%99%D7%A1%D7%95%D7%93:_%D7%94%D7%9B%D7%A0%D7%A1%D7%AA#%D7%A1%D7%A2%D7%99%D7%A3_4"
      ],
      "Language": "עברית",
      "Version": "",
      "ClauseRepresentation": "main clause",
      "OfficialRoles": [
        {
          "Role": "יועץ המשפטי לממשלה",
          "ClauseLocation": "(א)(1)",
          "Quote": "אישור היועץ המשפטי לממשלה"
        },
        {
          "Role": "יושב ראש הכנסת",
          "ClauseLocation": "(א)(2)",
          "Quote": "לחבר הכנסת, ליושב ראש הכנסת"
        },
        {
          "Role": "יושב ראש ועדת הכנסת",
          "ClauseLocation": "(א)(2)",
          "Quote": "לחבר הכנסת, ליושב ראש ועדת הכנסת"
        }
      ],
      "OfficialOrganizations": [
        {
          "Organization": "הכנסת",
          "ClauseLocation": "(א)(3)",
          "Quote": "הכנסת תקבע כי תהיה לו חסינות"
        },
        {
          "Organization": "ועדת הכנסת",
          "ClauseLocation": "(א)(3)",
          "Quote": "ליושב ראש ועדת הכנסת"
        }
      ],
      "Placenames": [
        {
          "Name": "משכן הכנסת",
          "ClauseLocation": "(א)(3)(ג)",
          "Quote": "העבירה בוצעה במשכן הכנסת"
        }
      ],
      "Description": "החוק עוסק בחסינות חברי הכנסת בפני דיון פלילי והליכי משפט."
    },
    "LegalReferences": [],
    "Amendments": [
      "תיקון: תשנ״ה־2, תשס״ה־2, תשע״ו־3"
    ],
    "AdditionalKeywords": [
      "חסינות",
      "חבר הכנסת",
      "דיון פלילי",
      "יועץ משפטי",
      "הכנסת"
    ],
    "Topics": [
      "חסינות בפני דיון פלילי",
      "הגשת כתב אישום",
      "בקשה לחסינות",
      "עבירות שאינן חלות על חבר הכנסת"
    ]
  },
  "title": "חוק חסינות חברי הכנסת, זכויותיהם וחובותיהם",
  "source_file": "חוק חסינות חברי הכנסת, זכויותיהם וחובותיהם_4.md"
}