{
  "extracted_at": "2025-03-02T19:22:59.529569+00:00",
  "status": "processed",
  "context_type": "files",
  "context_name": "Knesset Bylaws (תקנון הכנסת) and related laws",
  "source_content": "**חוק משכן הכנסת, רחבתו ומשמר הכנסת: **\n\n[מקור: סעיף 7. ](https://he.wikisource.org/wiki/%D7%97%D7%95%D7%A7-%D7%99%D7%A1%D7%95%D7%93:_%D7%94%D7%9B%D7%A0%D7%A1%D7%AA#%D7%A1%D7%A2%D7%99%D7%A3_7)\nהסדר במשכן הכנסת וברחבה\n\n(א)לא ינהג אדם במשכן הכנסת או ברחבה בדרך או בצורה שיש בה כדי להפריע לעבודה התקינה בכנסת או להפריע לבאי משכן הכנסת.(ב)במשכן הכנסת וברחבה לא תיערך כל אסיפה וכל תהלוכה אלא בהיתר, בין כללי ובין מיוחד, מאת יושב־ראש הכנסת.(ג)במשכן הכנסת וברחבה לא יעמיד אדם שלט, מודעה או כרזה אלא בהיתר מאת יושב־ראש הכנסת.(ד)בסעיף זה –”אסיפה“ – עשרה אנשים או יותר שנאספו לפעול במשותף;”תהלוכה“ – עשרה אנשים או יותר ההולכים יחד, או מתקהלים לשם הליכה יחד, ממקום למקום לשם מטרה משותפת, בין שהסתדרו בסך ובין שלא הסתדרו כך.",
  "document_type": "חוק משכן הכנסת, רחבתו ומשמר הכנסת",
  "extracted_data": {
    "DocumentMetadata": {
      "DocumentTitle": "חוק משכן הכנסת, רחבתו ומשמר הכנסת",
      "PublicationDate": "",
      "OfficialSource": "סעיף 7",
      "ReferenceLinks": [
        "https://he.wikisource.org/wiki/%D7%97%D7%95%D7%A7-%D7%99%D7%A1%D7%95%D7%93:_%D7%94%D7%9B%D7%A0%D7%A1%D7%AA#%D7%A1%D7%A2%D7%99%D7%A3_7"
      ],
      "Language": "עברית",
      "Version": "",
      "ClauseRepresentation": "main clause",
      "OfficialRoles": [
        {
          "Role": "יושב־ראש הכנסת",
          "ClauseLocation": "(ב)",
          "Quote": "בהיתר, בין כללי ובין מיוחד, מאת יושב־ראש הכנסת"
        },
        {
          "Role": "יושב־ראש הכנסת",
          "ClauseLocation": "(ג)",
          "Quote": "בהיתר מאת יושב־ראש הכנסת"
        }
      ],
      "OfficialOrganizations": [],
      "Placenames": [
        {
          "Name": "משכן הכנסת",
          "ClauseLocation": "(א)",
          "Quote": "במשכן הכנסת או ברחבה"
        },
        {
          "Name": "רחבה",
          "ClauseLocation": "(א)",
          "Quote": "במשכן הכנסת או ברחבה"
        }
      ],
      "Description": "הסדר במשכן הכנסת וברחבה"
    },
    "LegalReferences": [],
    "Amendments": [],
    "AdditionalKeywords": [
      "אסיפה",
      "תהלוכה"
    ],
    "Topics": [
      "לא ינהג אדם במשכן הכנסת או ברחבה בדרך או בצורה שיש בה כדי להפריע לעבודה התקינה בכנסת",
      "במשכן הכנסת וברחבה לא תיערך כל אסיפה וכל תהלוכה אלא בהיתר",
      "במשכן הכנסת וברחבה לא יעמיד אדם שלט, מודעה או כרזה אלא בהיתר"
    ]
  },
  "title": "חוק משכן הכנסת, רחבתו ומשמר הכנסת",
  "source_file": "חוק משכן הכנסת, רחבתו ומשמר הכנסת_7.md"
}