{
  "extracted_at": "2025-03-02T19:13:41.760747+00:00",
  "status": "processed",
  "context_type": "files",
  "context_name": "Knesset Bylaws (תקנון הכנסת) and related laws",
  "source_content": "**חוק חסינות חברי הכנסת, זכויותיהם וחובותיהם: **\n\n[מקור: סעיף 14. ](https://he.wikisource.org/wiki/%D7%97%D7%95%D7%A7-%D7%99%D7%A1%D7%95%D7%93:_%D7%94%D7%9B%D7%A0%D7%A1%D7%AA#%D7%A1%D7%A2%D7%99%D7%A3_14)\nאיסורים[תיקון: תשנ״ז־3, תשע״ד־2]\n\n(א)חבר הכנסת, שר וסגן שר, אסור לו להשתמש בתואר תפקידו בכל פעולה הכרוכה בעסקו או במקצועו.(ב)(בוטל).(ג)מי שהיה ראש הממשלה או שר, אסור לו, שלוש שנים לאחר תום כהונתו כראש הממשלה או כשר, להיות חבר בהנהלת חברה או איגוד אחר שקיבלו בזמן כהונתו זכיון מהמדינה.(ד)מי שהיה סגן שר, אסור לו, שלוש שנים לאחר תום כהונתו כסגן שר, להיות חבר בהנהלת חברה או איגוד אחר שקיבלו בזמן כהונתו זכיון מהמדינה באמצעות המשרד שבו הוא כיהן כסגן שר.(ה)העובר על הוראה מהוראות סעיף זה, דינו – מאסר עד שתי שנים או קנס עד שלושת אלפים לירות או שני הענשים כאחד.ראו גםכללים למניעת ניגוד ענינים של שרים וסגני שרים(י״פ תשס״ג, 1136).",
  "document_type": "חוק חסינות חברי הכנסת, זכויותיהם וחובותיהם",
  "extracted_data": {
    "DocumentMetadata": {
      "DocumentTitle": "חוק חסינות חברי הכנסת, זכויותיהם וחובותיהם",
      "PublicationDate": "",
      "OfficialSource": "סעיף 14",
      "ReferenceLinks": [
        "https://he.wikisource.org/wiki/%D7%97%D7%95%D7%A7-%D7%99%D7%A1%D7%95%D7%93:_%D7%94%D7%9B%D7%A0%D7%A1%D7%AA#%D7%A1%D7%A2%D7%99%D7%A3_14"
      ],
      "Language": "עברית",
      "Version": "",
      "ClauseRepresentation": "main clause",
      "OfficialRoles": [
        {
          "Role": "חבר הכנסת",
          "ClauseLocation": "(א)",
          "Quote": "חבר הכנסת, שר וסגן שר, אסור לו להשתמש בתואר תפקידו בכל פעולה הכרוכה בעסקו או במקצועו."
        },
        {
          "Role": "ראש הממשלה",
          "ClauseLocation": "(ג)",
          "Quote": "מי שהיה ראש הממשלה או שר, אסור לו, שלוש שנים לאחר תום כהונתו כראש הממשלה או כשר, להיות חבר בהנהלת חברה או איגוד אחר שקיבלו בזמן כהונתו זכיון מהמדינה."
        },
        {
          "Role": "סגן שר",
          "ClauseLocation": "(ד)",
          "Quote": "מי שהיה סגן שר, אסור לו, שלוש שנים לאחר תום כהונתו כסגן שר, להיות חבר בהנהלת חברה או איגוד אחר שקיבלו בזמן כהונתו זכיון מהמדינה באמצעות המשרד שבו הוא כיהן כסגן שר."
        }
      ],
      "OfficialOrganizations": [],
      "Placenames": [],
      "Description": "החוק עוסק באיסורים על חברי הכנסת, שרים וסגני שרים בנוגע לשימוש בתואר תפקידם ובחברות לאחר תום כהונתם."
    },
    "LegalReferences": [
      {
        "ReferenceTitle": "כללים למניעת ניגוד ענינים של שרים וסגני שרים",
        "ReferenceText": "(י״פ תשס״ג, 1136)",
        "ReferenceQuote": "ראו גם כללים למניעת ניגוד ענינים של שרים וסגני שרים (י״פ תשס״ג, 1136)."
      }
    ],
    "Amendments": [
      "תיקון: תשנ״ז־3, תשע״ד־2"
    ],
    "AdditionalKeywords": [
      "חסינות",
      "זכויות",
      "חובות",
      "איסורים",
      "מאסר",
      "קנס"
    ],
    "Topics": []
  },
  "title": "חוק חסינות חברי הכנסת, זכויותיהם וחובותיהם",
  "source_file": "חוק חסינות חברי הכנסת, זכויותיהם וחובותיהם_14.md"
}