{
  "extracted_at": "2025-03-02T19:31:00.613037+00:00",
  "status": "processed",
  "context_type": "files",
  "context_name": "Knesset Bylaws (תקנון הכנסת) and related laws",
  "source_content": "**חוק-יסוד: הכנסת: **\n\n[מקור: סעיף 7א. ](https://he.wikisource.org/wiki/%D7%97%D7%95%D7%A7-%D7%99%D7%A1%D7%95%D7%93:_%D7%94%D7%9B%D7%A0%D7%A1%D7%AA#%D7%A1%D7%A2%D7%99%D7%A3_7א)\nמניעת השתתפות בבחירות[תיקון: תשמ״ה, תשס״ב־2, תשס״ח, תשע״ז]\n\n(א)רשימת מועמדים לא תשתתף בבחירות לכנסת ולא יהיה אדם מועמד בבחירות לכנסת, אם יש במטרותיה או במעשיה של הרשימה או במעשיו של האדם, לרבות בהתבטאויותיו, לפי הענין, במפורש או במשתמע, אחד מאלה:(1)שלילת קיומה של מדינת ישראל כמדינה יהודית ודמוקרטית;(2)הסתה לגזענות;(3)תמיכה במאבק מזוין, של מדינת אויב או של ארגון טרור, נגד מדינת ישראל.(א1)לעניין סעיף זה, יראו מועמד ששהה במדינת אויב שלא כדין בשבע השנים שקדמו למועד הגשת רשימת המועמדים כמי שיש במעשיו משום תמיכה במאבק מזוין נגד מדינת ישראל, כל עוד לא הוכיח אחרת.(ב)החלטת ועדת הבחירות המרכזית כי מועמד מנוע מלהשתתף בבחירות טעונה אישור בית המשפט העליון.(ג)מועמד יצהיר הצהרה לענין סעיף זה.ראוסעיף 57(ט1) לחוק הבחירות לכנסת [נוסח משולב], תשכ״ט–1969.(ד)פרטים לענין הדיון בועדת הבחירות המרכזית ובבית המשפט העליון ולענין הצהרה לפי סעיף קטן (ג), ייקבעו בחוק.ראוסעיפים 63או־64 לחוק הבחירות לכנסת [נוסח משולב], תשכ״ט–1969.פורסםנוהל הטיפול בבקשות לפסילת רשימת מועמדים או מועמד לכנסת, התשע״ט–2019.",
  "document_type": "חוק-יסוד: הכנסת",
  "extracted_data": {
    "DocumentMetadata": {
      "DocumentTitle": "חוק-יסוד: הכנסת",
      "PublicationDate": "",
      "OfficialSource": "סעיף 7א.",
      "ReferenceLinks": [
        "https://he.wikisource.org/wiki/%D7%97%D7%95%D7%A7-%D7%99%D7%A1%D7%95%D7%93:_%D7%94%D7%9B%D7%A0%D7%A1%D7%AA#%D7%A1%D7%A2%D7%99%D7%A3_7א"
      ],
      "Language": "עברית",
      "Version": "",
      "ClauseRepresentation": "main clause",
      "OfficialRoles": [],
      "OfficialOrganizations": [
        {
          "Organization": "ועדת הבחירות המרכזית",
          "ClauseLocation": "(ב)",
          "Quote": "החלטת ועדת הבחירות המרכזית כי מועמד מנוע מלהשתתף בבחירות טעונה אישור בית המשפט העליון."
        },
        {
          "Organization": "בית המשפט העליון",
          "ClauseLocation": "(ב)",
          "Quote": "החלטת ועדת הבחירות המרכזית כי מועמד מנוע מלהשתתף בבחירות טעונה אישור בית המשפט העליון."
        }
      ],
      "Placenames": [
        {
          "Name": "מדינת ישראל",
          "ClauseLocation": "(א)(1)",
          "Quote": "שלילת קיומה של מדינת ישראל כמדינה יהודית ודמוקרטית"
        },
        {
          "Name": "מדינת אויב",
          "ClauseLocation": "(א1)",
          "Quote": "מועמד ששהה במדינת אויב שלא כדין"
        }
      ],
      "Description": "מניעת השתתפות בבחירות לכנסת למועמדים עם מטרות או מעשים מסוימים."
    },
    "LegalReferences": [
      {
        "ReferenceTitle": "חוק הבחירות לכנסת [נוסח משולב], תשכ״ט–1969",
        "ReferenceText": "ראוסעיף 57(ט1) לחוק הבחירות לכנסת [נוסח משולב], תשכ״ט–1969.",
        "ReferenceQuote": "ראוסעיף 57(ט1) לחוק הבחירות לכנסת [נוסח משולב], תשכ״ט–1969."
      },
      {
        "ReferenceTitle": "חוק הבחירות לכנסת [נוסח משולב], תשכ״ט–1969",
        "ReferenceText": "ראוסעיפים 63או־64 לחוק הבחירות לכנסת [נוסח משולב], תשכ״ט–1969.",
        "ReferenceQuote": "ראוסעיפים 63או־64 לחוק הבחירות לכנסת [נוסח משולב], תשכ״ט–1969."
      }
    ],
    "Amendments": [
      "תיקון: תשמ״ה, תשס״ב־2, תשס״ח, תשע״ז"
    ],
    "AdditionalKeywords": [
      "מניעת השתתפות",
      "בחירות",
      "מועמדים",
      "הסתה לגזענות",
      "תמיכה במאבק מזוין"
    ],
    "Topics": [
      "מניעת השתתפות בבחירות לכנסת למועמדים עם מטרות או מעשים מסוימים."
    ]
  },
  "title": "חוק-יסוד: הכנסת",
  "source_file": "חוק-יסוד: הכנסת_7א.md"
}