{
  "extracted_at": "2025-03-02T19:40:02.650467+00:00",
  "status": "processed",
  "context_type": "files",
  "context_name": "Knesset Bylaws (תקנון הכנסת) and related laws",
  "source_content": "**חוק-יסוד: הכנסת: **\n\n[מקור: סעיף 6א. ](https://he.wikisource.org/wiki/%D7%97%D7%95%D7%A7-%D7%99%D7%A1%D7%95%D7%93:_%D7%94%D7%9B%D7%A0%D7%A1%D7%AA#%D7%A1%D7%A2%D7%99%D7%A3_6א)\nסייג למועמדות חבר הכנסת שפרש מסיעתו[תיקון: תשנ״א, תשנ״ו־3, תשס״ד]\n\n(א)חבר הכנסת שפרש מסיעתו ולא התפטר מכהונתו סמוך לפרישתו, לא ייכלל, בבחירות לכנסת שלאחריה, ברשימת מועמדים שהגישה מפלגה שהיתה מיוצגת על ידי סיעה של הכנסת היוצאת; הוראה זו לא תחול על התפלגות סיעה בתנאים שנקבעו בחוק.ראוסעיף 25 לחוק הבחירות לכנסת [נוסח משולב], תשכ״ט–1969.ראוסעיף 61 לחוק הכנסת, התשנ״ד–1994.(ב)לענין סעיף זה –”פרישה מסיעה“ – לרבות הצבעה במליאת הכנסת שלא בהתאם לעמדת הסיעה בענין הבעת אמון לממשלה או אי־אמון בה; ואולם הצבעה כאמור לא תיחשב כפרישה אם חבר הכנסת לא קיבל כל תמורה בעד הצבעתו;”תמורה“ – במישרין או בעקיפין, בהבטחה או בהתחייבות לעתיד, ולרבות הבטחת מקום ברשימת מועמדים לכנסת, או מינוי חבר הכנסת עצמו או אדם אחר לתפקיד כלשהו.",
  "document_type": "חוק-יסוד: הכנסת",
  "extracted_data": {
    "DocumentMetadata": {
      "DocumentTitle": "חוק-יסוד: הכנסת",
      "PublicationDate": "",
      "OfficialSource": "סעיף 6א.",
      "ReferenceLinks": [
        "https://he.wikisource.org/wiki/%D7%97%D7%95%D7%A7-%D7%99%D7%A1%D7%95%D7%93:_%D7%94%D7%9B%D7%A0%D7%A1%D7%AA#%D7%A1%D7%A2%D7%99%D7%A3_6א"
      ],
      "Language": "עברית",
      "Version": "",
      "ClauseRepresentation": "main clause",
      "OfficialRoles": [],
      "OfficialOrganizations": [],
      "Placenames": [],
      "Description": "סייג למועמדות חבר הכנסת שפרש מסיעתו"
    },
    "LegalReferences": [
      {
        "ReferenceTitle": "חוק הבחירות לכנסת [נוסח משולב]",
        "ReferenceText": "תשכ״ט–1969",
        "ReferenceQuote": "ראוסעיף 25 לחוק הבחירות לכנסת [נוסח משולב], תשכ״ט–1969."
      },
      {
        "ReferenceTitle": "חוק הכנסת",
        "ReferenceText": "התשנ״ד–1994",
        "ReferenceQuote": "ראוסעיף 61 לחוק הכנסת, התשנ״ד–1994."
      }
    ],
    "Amendments": [
      "תיקון: תשנ״א, תשנ״ו־3, תשס״ד"
    ],
    "AdditionalKeywords": [
      "מועמדות",
      "חבר הכנסת",
      "פרישה",
      "סיעה",
      "הבעת אמון",
      "אי־אמון",
      "תמורה"
    ],
    "Topics": [
      "סייג למועמדות חבר הכנסת שפרש מסיעתו"
    ]
  },
  "title": "חוק-יסוד: הכנסת",
  "source_file": "חוק-יסוד: הכנסת_6א.md"
}