{
  "extracted_at": "2025-03-02T19:16:57.000155+00:00",
  "status": "processed",
  "context_type": "files",
  "context_name": "Knesset Bylaws (תקנון הכנסת) and related laws",
  "source_content": "**חוק-יסוד: הכנסת: **\n\n[מקור: סעיף 36א. ](https://he.wikisource.org/wiki/%D7%97%D7%95%D7%A7-%D7%99%D7%A1%D7%95%D7%93:_%D7%94%D7%9B%D7%A0%D7%A1%D7%AA#%D7%A1%D7%A2%D7%99%D7%A3_36א)\nהתפזרות בשל אי קבלת חוק תקציב[תיקון: תשס״א־3, תשע״ד, תש״ף, תש״ף־3, תשפ״א]\n\n(א)לא נתקבל חוק התקציב בתוך שלושה חודשים מיום תחילתה של שנת הכספים, יראו ביום שאחרי סיום התקופה האמורה (להלן – היום הקובע) כאילו החליטה הכנסת על התפזרותה לפני גמר תקופת כהונתה, וייערכו בחירות מוקדמות ביום ג׳ האחרון שלפני תום 90 הימים מהיום הקובע, אלא אם כן החליטה הכנסת ברוב חבריה, בתוך חמישה ימים מהיום הקובע, בשל סמיכות מועד הבחירות ליום חג, מועד או זיכרון, על קיום הבחירות במועד מאוחר יותר, אך לא יאוחר מ־100 ימים מהיום הקובע.(ב)על אף הוראות סעיף קטן (א), פתח נשיא המדינה בהליכים להרכבת ממשלה חדשה לפיסעיף 30 לחוק־יסוד: הממשלה, הביעה הכנסת אמון בממשלה חדשה לפיסעיף 28 לחוק־יסוד: הממשלה, או התקבל חוק על התפזרות הכנסת, או התקיימו בחירות לכנסת, אחרי המועד להגשת הצעת התקציב לפיסעיף 3 לחוק־יסוד: משק המדינה, ולפני תום שלושת החודשים שמיום תחילת שנת הכספים, יהיה היום הקובע כאמור בסעיף קטן (א), היום שאחרי תום שלושה חודשים מיום תחילת שנת הכספים או היום שאחרי תום 145 ימים מיום כינון הממשלה, לפי המאוחר; קבעה ועדת הכספים של הכנסת לפיסעיף 3(ב)(1) לחוק־יסוד: משק המדינהכי הצעת חוק התקציב תונח על שולחן הכנסת לפני היום ה־85 מיום כינון הממשלה, יהיה היום הקובע היום שאחרי תום 60 ימים מהיום שבו הניחה הממשלה את ההצעה; במניין התקופות של 145 ימים, 85 ימים ו־60 ימים כאמור, לא יובאו בחשבון מועדי ישראל וערביהם כפי שייקבע בחוק.(ג)(פקע).",
  "document_type": "חוק-יסוד: הכנסת",
  "extracted_data": {
    "DocumentMetadata": {
      "DocumentTitle": "חוק-יסוד: הכנסת",
      "PublicationDate": "",
      "OfficialSource": "סעיף 36א.",
      "ReferenceLinks": [
        "https://he.wikisource.org/wiki/%D7%97%D7%95%D7%A7-%D7%99%D7%A1%D7%95%D7%93:_%D7%94%D7%9B%D7%A0%D7%A1%D7%AA#%D7%A1%D7%A2%D7%99%D7%A3_36א"
      ],
      "Language": "עברית",
      "Version": "",
      "ClauseRepresentation": "main clause",
      "OfficialRoles": [],
      "OfficialOrganizations": [
        {
          "Organization": "הכנסת",
          "ClauseLocation": "(א)",
          "Quote": "כאילו החליטה הכנסת על התפזרותה"
        },
        {
          "Organization": "ועדת הכספים של הכנסת",
          "ClauseLocation": "(ב)",
          "Quote": "קבעה ועדת הכספים של הכנסת לפיסעיף 3(ב)(1) לחוק־יסוד: משק המדינה"
        }
      ],
      "Placenames": [],
      "Description": "החוק עוסק בהתפזרות הכנסת בשל אי קבלת חוק תקציב."
    },
    "LegalReferences": [
      {
        "ReferenceTitle": "חוק־יסוד: הממשלה",
        "ReferenceText": "פיסעיף 30 לחוק־יסוד: הממשלה",
        "ReferenceQuote": "פתח נשיא המדינה בהליכים להרכבת ממשלה חדשה לפיסעיף 30 לחוק־יסוד: הממשלה"
      },
      {
        "ReferenceTitle": "חוק־יסוד: הממשלה",
        "ReferenceText": "פיסעיף 28 לחוק־יסוד: הממשלה",
        "ReferenceQuote": "הביעה הכנסת אמון בממשלה חדשה לפיסעיף 28 לחוק־יסוד: הממשלה"
      },
      {
        "ReferenceTitle": "חוק־יסוד: משק המדינה",
        "ReferenceText": "פיסעיף 3 לחוק־יסוד: משק המדינה",
        "ReferenceQuote": "לפיסעיף 3 לחוק־יסוד: משק המדינה"
      },
      {
        "ReferenceTitle": "חוק־יסוד: משק המדינה",
        "ReferenceText": "פיסעיף 3(ב)(1) לחוק־יסוד: משק המדינה",
        "ReferenceQuote": "לפיסעיף 3(ב)(1) לחוק־יסוד: משק המדינה"
      }
    ],
    "Amendments": [
      "תיקון: תשס״א־3, תשע״ד, תש״ף, תש״ף־3, תשפ״א"
    ],
    "AdditionalKeywords": [
      "התפזרות",
      "חוק תקציב",
      "בחירות מוקדמות"
    ],
    "Topics": [
      "לא נתקבל חוק התקציב בתוך שלושה חודשים מיום תחילתה של שנת הכספים.",
      "היום הקובע כאילו החליטה הכנסת על התפזרותה.",
      "הוראות לגבי מועד הבחירות המוקדמות."
    ]
  },
  "title": "חוק-יסוד: הכנסת",
  "source_file": "חוק-יסוד: הכנסת_36א.md"
}