{
  "extracted_at": "2025-03-02T19:33:32.170869+00:00",
  "status": "processed",
  "context_type": "files",
  "context_name": "Knesset Bylaws (תקנון הכנסת) and related laws",
  "source_content": "**חוק חסינות חברי הכנסת, זכויותיהם וחובותיהם: **\n\n[מקור: סעיף 10א. ](https://he.wikisource.org/wiki/%D7%97%D7%95%D7%A7-%D7%99%D7%A1%D7%95%D7%93:_%D7%94%D7%9B%D7%A0%D7%A1%D7%AA#%D7%A1%D7%A2%D7%99%D7%A3_10א)\nהשתתפות בהוצאות משפטיות[תיקון: תשס״ג]\n\n(א)חבר הכנסת או מי שהיה חבר הכנסת (בסעיף זה – חבר הכנסת), זכאי להשתתפות בהוצאות משפטיות בשל הליך משפטי בקשר למעשה שעשה במסגרת מילוי תפקידו כחבר הכנסת, הכל בהתאם לכללים שתקבע ועדת הכנסת (בסעיף זה – הכללים); הכללים יפורסמו ברשומות.(ב)החלטת בדבר השתתפות בהוצאות משפטיות של חבר הכנסת על פי הכללים, תתקבל על ידי ועדה ציבורית, על יסוד בקשה בכתב של חבר הכנסת.(ג)הועדה הציבורית תהיה בת שלושה חברים שימנה יושב ראש הכנסת, ואלה הם:(1)שופט בדימוס של בית המשפט העליון או בית המשפט המחוזי, והוא יהיה יושב הראש;(2)אדם שכיהן בתפקיד בכיר בכנסת;(3)אדם בעל מעמד ציבורי וכישורים הולמים, שאינו קשור לאחת הסיעות בכנסת.(ד)הועדה הציבורית תקבע את סדרי עבודתה ונוהלי דיוניה, ככל שלא נקבעו בכללים.(ה)הכללים יחולו על חבר הכנסת גם לגבי הליך משפטי שהחל לפני תחילתו של חוק זה, ובלבד שההליך לא הסתיים לפני תחילת כהונתה של הכנסת החמש עשרה.פורסמוכללי חסינות חברי הכנסת, זכויותיהם וחובותיהם (השתתפות בהוצאות משפטיות), התשס״ג–2003.",
  "document_type": "חוק חסינות חברי הכנסת, זכויותיהם וחובותיהם",
  "extracted_data": {
    "DocumentMetadata": {
      "DocumentTitle": "חוק חסינות חברי הכנסת, זכויותיהם וחובותיהם",
      "PublicationDate": "",
      "OfficialSource": "סעיף 10א.",
      "ReferenceLinks": [
        "https://he.wikisource.org/wiki/%D7%97%D7%95%D7%A7-%D7%99%D7%A1%D7%95%D7%93:_%D7%94%D7%9B%D7%A0%D7%A1%D7%AA#%D7%A1%D7%A2%D7%99%D7%A3_10א"
      ],
      "Language": "עברית",
      "Version": "",
      "ClauseRepresentation": "main clause",
      "OfficialRoles": [
        {
          "Role": "יושב ראש הכנסת",
          "ClauseLocation": "(ג)",
          "Quote": "שימנה יושב ראש הכנסת"
        },
        {
          "Role": "שופט בדימוס של בית המשפט העליון או בית המשפט המחוזי",
          "ClauseLocation": "(ג)(1)",
          "Quote": "שופט בדימוס של בית המשפט העליון או בית המשפט המחוזי, והוא יהיה יושב הראש"
        },
        {
          "Role": "אדם שכיהן בתפקיד בכיר בכנסת",
          "ClauseLocation": "(ג)(2)",
          "Quote": "אדם שכיהן בתפקיד בכיר בכנסת"
        },
        {
          "Role": "אדם בעל מעמד ציבורי וכישורים הולמים",
          "ClauseLocation": "(ג)(3)",
          "Quote": "אדם בעל מעמד ציבורי וכישורים הולמים, שאינו קשור לאחת הסיעות בכנסת"
        }
      ],
      "OfficialOrganizations": [
        {
          "Organization": "ועדת הכנסת",
          "ClauseLocation": "(א)",
          "Quote": "כל בהתאם לכללים שתקבע ועדת הכנסת"
        },
        {
          "Organization": "הכנסת",
          "ClauseLocation": "(ה)",
          "Quote": "תחילת כהונתה של הכנסת החמש עשרה"
        }
      ],
      "Placenames": [],
      "Description": "החוק עוסק בזכאות חברי הכנסת להשתתפות בהוצאות משפטיות הקשורות למילוי תפקידם."
    },
    "LegalReferences": [
      {
        "ReferenceTitle": "חוק חסינות חברי הכנסת, זכויותיהם וחובותיהם",
        "ReferenceText": "פורסמוכללי חסינות חברי הכנסת, זכויותיהם וחובותיהם (השתתפות בהוצאות משפטיות), התשס״ג–2003",
        "ReferenceQuote": "פורסמוכללי חסינות חברי הכנסת, זכויותיהם וחובותיהם (השתתפות בהוצאות משפטיות), התשס״ג–2003"
      }
    ],
    "Amendments": [
      "תיקון: תשס״ג"
    ],
    "AdditionalKeywords": [
      "חסינות",
      "חבר הכנסת",
      "הוצאות משפטיות",
      "הליך משפטי"
    ],
    "Topics": [
      "חבר הכנסת זכאי להשתתפות בהוצאות משפטיות בשל הליך משפטי בקשר למעשה שעשה במסגרת מילוי תפקידו.",
      "החלטת בדבר השתתפות בהוצאות משפטיות תתקבל על ידי ועדה ציבורית.",
      "הועדה הציבורית תהיה בת שלושה חברים שימנה יושב ראש הכנסת.",
      "הכללים יחולו גם לגבי הליך משפטי שהחל לפני תחילת החוק."
    ]
  },
  "title": "חוק חסינות חברי הכנסת, זכויותיהם וחובותיהם",
  "source_file": "חוק חסינות חברי הכנסת, זכויותיהם וחובותיהם_10א.md"
}