{
  "extracted_at": "2025-03-02T19:09:40.446861+00:00",
  "status": "processed",
  "context_type": "files",
  "context_name": "Knesset Bylaws (תקנון הכנסת) and related laws",
  "source_content": "**חוק משכן הכנסת, רחבתו ומשמר הכנסת: **\n\n[מקור: סעיף 19. ](https://he.wikisource.org/wiki/%D7%97%D7%95%D7%A7-%D7%99%D7%A1%D7%95%D7%93:_%D7%94%D7%9B%D7%A0%D7%A1%D7%AA#%D7%A1%D7%A2%D7%99%D7%A3_19)\nשיפוט משמעתי[תיקון: תשנ״ה, תשס״ד, תשס״ו, תשע״א, תשע״ב]\nלענין חובת משמעת ושיפוט משמעתי דין איש משמר הכנסת כדין שוטר לפיחוק המשטרה, התשס״ו–2005(בסעיף זה – חוק המשטרה)ובפקודת המשטרה [נוסח חדש], התשל״א–1971(בסעיף זה – פקודת המשטרה), אולם סמכויות שר המשטרה יהיו נתונות ליושב־ראש הכנסת וסמכויות המפקח הכללי – לקצין הכנסת, והכל בשינויים המחוייבים לפי הענין ובתיאומים שיקבע יושב ראש הכנסת וכן בשינויים אלהבחוק המשטרהולעניין פסקה (10) –בפקודת המשטרה:(1)בסעיף 1, בהגדרה ”קצין שיפוט בכיר“, במקום ”ניצב משנה“ יבוא ”סגן גונן“;(2)בסעיף 27, במקום ”קצין משטרה שדרגתו תיקבע בפקודות משטרת ישראל,“ יבוא ”קצין שיפוט בכיר או עורך דין אחר שאינו עובד הלשכה המשפטית של הכנסת,“;(3)בסעיף 42, במקום ”המפקח הכללי“ יבוא ”יושב ראש הכנסת“;(4)במקום האמורבסעיף 43יבוא ”יושב ראש הכנסת ימנה נשיא לבית הדין למשמעת שהוא עורך דין עובד הלשכה המשפטית של הכנסת.“;(5)בסעיף 44–(א)בסעיף קטן (א), במקום ”שהם קציני משטרה בכירים, מהם שניים לפחות משפטנים“ יבוא ”שהם עורך דין שהוא עובד הלשכה המשפטית של הכנסת ושני קציני שיפוט בכירים“;(ב)בסעיף קטן (ב) –(1)במקום האמור בפסקה (1) יבוא ”עורך דין שהוא עובד הלשכה המשפטית של הכנסת וקצין שיפוט בכיר“;(2)בפסקה (2), המילים ”בהסכמת שר המשפטים“ – יימחקו;(6)לעניןסעיף 55, היועץ המשפטי לכנסת יהיה נשיא בית הדין לערעורים;(7)לעניןסעיף 56, הרכב מותב בית הדין לערעורים יהיה נשיא בית הדין, קצין הכנסת ועורך דין שהוא עובד הכנסת או גמלאי הכנסת;(8)בסעיף 67(א), ברישה, במקום ”שקבע המפקח הכללי“ יבוא ”שקבע קצין הכנסת, בהסכמת המפקח הכללי“;(9)בסעיף 71(ב), במקום ”לקרן הכללית של משטרת ישראל“ יבוא ”לקרן התרבות של משמר הכנסת“;(10)בסעיף 77י לפקודת המשטרה, במקום ”קצין משטרה בכיר“ יבוא ”סגן גונן ומעלה“.",
  "document_type": "חוק משכן הכנסת, רחבתו ומשמר הכנסת",
  "extracted_data": {
    "DocumentMetadata": {
      "DocumentTitle": "חוק משכן הכנסת, רחבתו ומשמר הכנסת",
      "PublicationDate": "",
      "OfficialSource": "סעיף 19",
      "ReferenceLinks": [
        "https://he.wikisource.org/wiki/%D7%97%D7%95%D7%A7-%D7%99%D7%A1%D7%95%D7%93:_%D7%94%D7%9B%D7%A0%D7%A1%D7%AA#%D7%A1%D7%A2%D7%99%D7%A3_19"
      ],
      "Language": "עברית",
      "Version": "",
      "ClauseRepresentation": "main clause",
      "OfficialRoles": [
        {
          "Role": "יושב ראש הכנסת",
          "ClauseLocation": "סעיף 19",
          "Quote": "סמכויות שר המשטרה יהיו נתונות ליושב־ראש הכנסת"
        },
        {
          "Role": "נשיא בית הדין למשמעת",
          "ClauseLocation": "סעיף 19",
          "Quote": "יושב ראש הכנסת ימנה נשיא לבית הדין למשמעת שהוא עורך דין עובד הלשכה המשפטית של הכנסת"
        },
        {
          "Role": "יועץ משפטי לכנסת",
          "ClauseLocation": "סעיף 19",
          "Quote": "היועץ המשפטי לכנסת יהיה נשיא בית הדין לערעורים"
        }
      ],
      "OfficialOrganizations": [
        {
          "Organization": "הלשכה המשפטית של הכנסת",
          "ClauseLocation": "סעיף 19",
          "Quote": "עורך דין שהוא עובד הלשכה המשפטית של הכנסת"
        },
        {
          "Organization": "משמר הכנסת",
          "ClauseLocation": "סעיף 19",
          "Quote": "קרן התרבות של משמר הכנסת"
        },
        {
          "Organization": "משטרת ישראל",
          "ClauseLocation": "סעיף 19",
          "Quote": "קצין משטרה בכיר"
        }
      ],
      "Placenames": [],
      "Description": "החוק עוסק בחובת משמעת ושיפוט משמעתי של אנשי משמר הכנסת."
    },
    "LegalReferences": [
      {
        "ReferenceTitle": "חוק המשטרה",
        "ReferenceText": "התשס״ו–2005",
        "ReferenceQuote": "דין איש משמר הכנסת כדין שוטר לפיחוק המשטרה, התשס״ו–2005"
      },
      {
        "ReferenceTitle": "פקודת המשטרה",
        "ReferenceText": "התשל״א–1971",
        "ReferenceQuote": "ובפקודת המשטרה [נוסח חדש], התשל״א–1971"
      }
    ],
    "Amendments": [
      "תיקון: תשנ״ה, תשס״ד, תשס״ו, תשע״א, תשע״ב"
    ],
    "AdditionalKeywords": [
      "שיפוט משמעתי",
      "חובת משמעת",
      "סמכויות",
      "קצין שיפוט בכיר"
    ],
    "Topics": [
      "החוק עוסק בחובת משמעת ושיפוט משמעתי של אנשי משמר הכנסת."
    ]
  },
  "title": "חוק משכן הכנסת, רחבתו ומשמר הכנסת",
  "source_file": "חוק משכן הכנסת, רחבתו ומשמר הכנסת_19.md"
}