{
  "extracted_at": "2025-03-02T19:19:33.907136+00:00",
  "status": "processed",
  "context_type": "files",
  "context_name": "Knesset Bylaws (תקנון הכנסת) and related laws",
  "source_content": "**חוק משכן הכנסת, רחבתו ומשמר הכנסת: **\n\n[מקור: סעיף 16ד. ](https://he.wikisource.org/wiki/%D7%97%D7%95%D7%A7-%D7%99%D7%A1%D7%95%D7%93:_%D7%94%D7%9B%D7%A0%D7%A1%D7%AA#%D7%A1%D7%A2%D7%99%D7%A3_16ד)\nסמכות למסור הודעות תשלום קנס[תיקון: תשנ״ט]\n\n(א)קצין הכנסת, או איש משמר הכנסת שקצין הכנסת הסמיכו לפיסעיף 16ג, שיש לו יסוד להניח כי אדם פלוני עבר ברחבת הכנסת עבירת תעבורה ברכב מנועי שהיא עבירה של ברירת משפט, רשאי למסור לו הודעת תשלום קנס.(ב)דין הודעת תשלום קנס שנמסרה בהתאם להוראות סעיף קטן (א), כדין הודעת תשלום קנס שנמסרה על ידי שוטר והוראות לפיסעיפים 228 עד 230 לחוק סדר הדין הפלילייחולו לעניין זה, בשינויים המחויבים.",
  "document_type": "חוק משכן הכנסת, רחבתו ומשמר הכנסת",
  "extracted_data": {
    "DocumentMetadata": {
      "DocumentTitle": "חוק משכן הכנסת, רחבתו ומשמר הכנסת",
      "PublicationDate": "",
      "OfficialSource": "סעיף 16ד.",
      "ReferenceLinks": [
        "https://he.wikisource.org/wiki/%D7%97%D7%95%D7%A7-%D7%99%D7%A1%D7%95%D7%93:_%D7%94%D7%9B%D7%A0%D7%A1%D7%AA#%D7%A1%D7%A2%D7%99%D7%A3_16%D7%93"
      ],
      "Language": "עברית",
      "Version": "",
      "ClauseRepresentation": "main clause",
      "OfficialRoles": [
        {
          "Role": "קצין הכנסת",
          "ClauseLocation": "(א)",
          "Quote": "קצין הכנסת, או איש משמר הכנסת שקצין הכנסת הסמיכו לפיסעיף 16ג"
        },
        {
          "Role": "איש משמר הכנסת",
          "ClauseLocation": "(א)",
          "Quote": "איש משמר הכנסת שקצין הכנסת הסמיכו לפיסעיף 16ג"
        }
      ],
      "OfficialOrganizations": [],
      "Placenames": [
        {
          "Name": "רחבת הכנסת",
          "ClauseLocation": "(א)",
          "Quote": "עבר ברחבת הכנסת"
        }
      ],
      "Description": "סמכות למסור הודעות תשלום קנס על עבירות תעבורה ברחבת הכנסת."
    },
    "LegalReferences": [
      {
        "ReferenceTitle": "חוק סדר הדין הפלילי",
        "ReferenceText": "סעיפים 228 עד 230",
        "ReferenceQuote": "הוראות לפיסעיפים 228 עד 230 לחוק סדר הדין הפלילי"
      }
    ],
    "Amendments": [
      "תיקון: תשנ״ט"
    ],
    "AdditionalKeywords": [
      "הודעת תשלום קנס",
      "עבירת תעבורה",
      "ברירת משפט"
    ],
    "Topics": []
  },
  "title": "חוק משכן הכנסת, רחבתו ומשמר הכנסת",
  "source_file": "חוק משכן הכנסת, רחבתו ומשמר הכנסת_16ד.md"
}