{
  "extracted_at": "2025-03-02T19:15:13.026311+00:00",
  "status": "processed",
  "context_type": "files",
  "context_name": "Knesset Bylaws (תקנון הכנסת) and related laws",
  "source_content": "**חוק משכן הכנסת, רחבתו ומשמר הכנסת: **\n\n[מקור: סעיף 16ה. ](https://he.wikisource.org/wiki/%D7%97%D7%95%D7%A7-%D7%99%D7%A1%D7%95%D7%93:_%D7%94%D7%9B%D7%A0%D7%A1%D7%AA#%D7%A1%D7%A2%D7%99%D7%A3_16ה)\nאחריות לחניה[תיקון: תשנ״ט]\n\n(א)קצין הכנסת רשאי להורות על גרירתו או על העברתו של רכב מנועי, העומד ברחבת הכנסת במקום שהעמדתו אסורה, או בנסיבות שיש בהן כדי הפרת סדרי התנועה או בטיחותה, או שההרחקה דרושה לשם הסדרת התנועה או לבטיחותה או לבטיחות הציבור ברחבת הכנסת.(ב)גרירת הרכב או העברתו תיעשה על ידי איש משמר הכנסת או על ידי גורר מורשה, למקום אחר, בין בתחום רחבת הכנסת ובין מחוצה לה; הגרירה או ההעברה תיעשה תוך נקיטת אמצעי זהירות סבירים הדרושים כדי להבטיח את בטיחות הרכב.(ג)הוראותסעיף 70א(ד), (ו) ו־(ז) לפקודת התעבורהיחולו, בשינויים המחויבים, על גרירת רכב או על העברתו לפי סעיף זה.",
  "document_type": "חוק משכן הכנסת, רחבתו ומשמר הכנסת",
  "extracted_data": {
    "DocumentMetadata": {
      "DocumentTitle": "חוק משכן הכנסת, רחבתו ומשמר הכנסת",
      "PublicationDate": "",
      "OfficialSource": "סעיף 16ה",
      "ReferenceLinks": [
        "https://he.wikisource.org/wiki/%D7%97%D7%95%D7%A7-%D7%99%D7%A1%D7%95%D7%93:_%D7%94%D7%9B%D7%A0%D7%A1%D7%AA#%D7%A1%D7%A2%D7%99%D7%A3_16ה"
      ],
      "Language": "עברית",
      "Version": "",
      "ClauseRepresentation": "main clause",
      "OfficialRoles": [
        {
          "Role": "קצין הכנסת",
          "ClauseLocation": "(א)",
          "Quote": "קצין הכנסת רשאי להורות על גרירתו או על העברתו של רכב מנועי"
        },
        {
          "Role": "איש משמר הכנסת",
          "ClauseLocation": "(ב)",
          "Quote": "גרירת הרכב או העברתו תיעשה על ידי איש משמר הכנסת"
        }
      ],
      "OfficialOrganizations": [
        {
          "Organization": "משמר הכנסת",
          "ClauseLocation": "(ב)",
          "Quote": "איש משמר הכנסת"
        }
      ],
      "Placenames": [
        {
          "Name": "רחבת הכנסת",
          "ClauseLocation": "(א)",
          "Quote": "העמדתו אסורה, או בנסיבות שיש בהן כדי הפרת סדרי התנועה או בטיחותה"
        }
      ],
      "Description": "החוק עוסק באחריות לחניה ברחבת הכנסת וגרירת רכבים המפרים את הסדר."
    },
    "LegalReferences": [
      {
        "ReferenceTitle": "פקודת התעבורה",
        "ReferenceText": "סעיף 70א(ד), (ו) ו־(ז)",
        "ReferenceQuote": "הוראות סעיף 70א(ד), (ו) ו־(ז) לפקודת התעבורה יחולו"
      }
    ],
    "Amendments": [
      "תיקון: תשנ״ט"
    ],
    "AdditionalKeywords": [
      "גרירת רכב",
      "בטיחות הציבור",
      "סדרי התנועה"
    ],
    "Topics": []
  },
  "title": "חוק משכן הכנסת, רחבתו ומשמר הכנסת",
  "source_file": "חוק משכן הכנסת, רחבתו ומשמר הכנסת_16ה.md"
}