{
  "extracted_at": "2025-03-02T19:39:51.803639+00:00",
  "status": "processed",
  "context_type": "files",
  "context_name": "Knesset Bylaws (תקנון הכנסת) and related laws",
  "source_content": "**חוק-יסוד: הכנסת: **\n\n[מקור: סעיף 7. ](https://he.wikisource.org/wiki/%D7%97%D7%95%D7%A7-%D7%99%D7%A1%D7%95%D7%93:_%D7%94%D7%9B%D7%A0%D7%A1%D7%AA#%D7%A1%D7%A2%D7%99%D7%A3_7)\nמי לא יהיה מועמד[תיקון: תשי״ט־2, תשנ״ו־3, תשס״א־6]\nאלה לא יהיו מועמדים לכנסת:(1)נשיא המדינה;(2)שני הרבנים הראשיים;(3)שופט;(4)דיין של בית דין דתי;(5)מבקר המדינה;(6)ראש המטה הכללי, צבא־הגנה לישראל;(7)רבנים וכהני דתות אחרות, כשהם משמשים בכהונתם בשכר;(8)עובדי מדינה בכירים וקציני צבא בדרגות או בתפקידים שייקבעו בחוק;(9)שוטרים וסוהרים בדרגות או בתפקידים שייקבעו בחוק;(10)עובדי תאגידים שהוקמו בחוק, בדרגות או בתפקידים שייקבעו בחוק;זולת אם חדלו לכהן במשרה או בתפקיד כאמור לפני המועד להגשת רשימות המועמדים לכנסת, ואם נקבע בחוק מועד מוקדם מזה, לפני המועד האמור.ראוסעיף 56 לחוק הבחירות לכנסת [נוסח משולב], תשכ״ט–1969.",
  "document_type": "חוק-יסוד: הכנסת",
  "extracted_data": {
    "DocumentMetadata": {
      "DocumentTitle": "חוק-יסוד: הכנסת",
      "PublicationDate": "",
      "OfficialSource": "סעיף 7",
      "ReferenceLinks": [
        "https://he.wikisource.org/wiki/%D7%97%D7%95%D7%A7-%D7%99%D7%A1%D7%95%D7%93:_%D7%94%D7%9B%D7%A0%D7%A1%D7%AA#%D7%A1%D7%A2%D7%99%D7%A3_7"
      ],
      "Language": "עברית",
      "Version": "",
      "ClauseRepresentation": "main clause",
      "OfficialRoles": [
        {
          "Role": "נשיא המדינה",
          "ClauseLocation": "סעיף 7",
          "Quote": "אלה לא יהיו מועמדים לכנסת:(1)נשיא המדינה;"
        },
        {
          "Role": "שני הרבנים הראשיים",
          "ClauseLocation": "סעיף 7",
          "Quote": "(2)שני הרבנים הראשיים;"
        },
        {
          "Role": "שופט",
          "ClauseLocation": "סעיף 7",
          "Quote": "(3)שופט;"
        },
        {
          "Role": "דיין של בית דין דתי",
          "ClauseLocation": "סעיף 7",
          "Quote": "(4)דיין של בית דין דתי;"
        },
        {
          "Role": "מבקר המדינה",
          "ClauseLocation": "סעיף 7",
          "Quote": "(5)מבקר המדינה;"
        },
        {
          "Role": "ראש המטה הכללי, צבא־הגנה לישראל",
          "ClauseLocation": "סעיף 7",
          "Quote": "(6)ראש המטה הכללי, צבא־הגנה לישראל;"
        },
        {
          "Role": "רבנים וכהני דתות אחרות",
          "ClauseLocation": "סעיף 7",
          "Quote": "(7)רבנים וכהני דתות אחרות, כשהם משמשים בכהונתם בשכר;"
        },
        {
          "Role": "עובדי מדינה בכירים וקציני צבא",
          "ClauseLocation": "סעיף 7",
          "Quote": "(8)עובדי מדינה בכירים וקציני צבא בדרגות או בתפקידים שייקבעו בחוק;"
        },
        {
          "Role": "שוטרים וסוהרים",
          "ClauseLocation": "סעיף 7",
          "Quote": "(9)שוטרים וסוהרים בדרגות או בתפקידים שייקבעו בחוק;"
        },
        {
          "Role": "עובדי תאגידים שהוקמו בחוק",
          "ClauseLocation": "סעיף 7",
          "Quote": "(10)עובדי תאגידים שהוקמו בחוק, בדרגות או בתפקידים שייקבעו בחוק;"
        }
      ],
      "OfficialOrganizations": [],
      "Placenames": [],
      "Description": "החוק קובע מי לא יהיה מועמד לכנסת."
    },
    "LegalReferences": [
      {
        "ReferenceTitle": "חוק הבחירות לכנסת [נוסח משולב]",
        "ReferenceText": "סעיף 56 לחוק הבחירות לכנסת [נוסח משולב], תשכ״ט–1969.",
        "ReferenceQuote": "ראוסעיף 56 לחוק הבחירות לכנסת [נוסח משולב], תשכ״ט–1969."
      }
    ],
    "Amendments": [
      "תיקון: תשי״ט־2, תשנ״ו־3, תשס״א־6"
    ],
    "AdditionalKeywords": [],
    "Topics": []
  },
  "title": "חוק-יסוד: הכנסת",
  "source_file": "חוק-יסוד: הכנסת_7.md"
}