{
  "extracted_at": "2025-03-02T19:33:14.514166+00:00",
  "status": "processed",
  "context_type": "files",
  "context_name": "Knesset Bylaws (תקנון הכנסת) and related laws",
  "source_content": "**דיון מהיר והצעה דחופה בנושא דומה**\n\nמקור: חלק ד׳ - כלים פרלמנטריים / פרק חמישי - הצעות לסדר היום ודיונים מהירים / סעיף 61\nקישור: https://he.wikisource.org/wiki/תקנון_הכנסת#סעיף_61\n\n * (א) הוגשו לנשיאות הכנסת הצעה דחופה והצעה לדיון מהיר בנושא דומה, בהתאם לקביעת הנשיאות, תחליט הנשיאות אחת מאלה, והחלטתה תחול על כל ההצעות כאמור:\n   * (1) לאשר דיון בהצעה דחופה;\n   * (2) לאשר דיון מהיר בוועדה;\n   * (3) לא לאשר כלל דיון בהצעות, ורשאי חבר הכנסת שביקש שהצעתו תידון כהצעה דחופה, לערער על ההחלטה כאמורבסעיף 54(ו).\n * (ב) \n   * (1) חבר הכנסת לא יגיש באותו שבוע הצעה דחופה והצעה לדיון מהיר בנושא דומה.\n   * (2) החליטה נשיאות הכנסת כי הצעה לדיון מהיר תאושר לדיון כהצעה דחופה לפי סעיף קטן (א)(1), ובשל כך היו להצעה הדחופה כמה מציעים מאותה סיעה, תאושר לדיון רק הצעתו של חבר הסיעה שהגיש את הצעתו כהצעה דחופה.\n * (3) החליטה נשיאות הכנסת כי הצעה דחופה תאושר לדיון מהיר לפי סעיף קטן (א)(2), ובשל כך היו להצעה לדיון מהיר כמה מציעים מאותה סיעה, תאושר לדיון רק הצעתו של חבר הסיעה שהגיש את הצעתו כהצעה לדיון מהיר.\n * (ג) אישרה נשיאות הכנסת דיון בהצעה דחופה שהגיש חבר הכנסת, וכן אישרה כי הצעה לדיון מהיר בוועדה שהגיש אותו חבר כנסת בנושא אחר תידון כהצעה דחופה, לפי סעיף קטן (א)(1), תידון רק אחת מהן כהצעה דחופה, בהתאם להודעתו למזכיר הכנסת.\n * (ד) חבר הכנסת שהגיש הצעה דחופה והצעתו אושרה לדיון מהיר בוועדה כאמור בסעיף קטן (א)(2), אינו רשאי לערער על ההחלטה לפני ועדת הכנסת כאמורבסעיף 54(ו).\n * (ה) אישרה ועדת הכנסת דיון בהצעה לסדר היום כהצעה דחופה בעקבות ערעור של חבר הכנסת לפיסעיף 54(ו), לא תחול החלטתה על הצעה לדיון מהיר שהוגשה בנושא דומה.",
  "document_type": "תקנון הכנסת",
  "extracted_data": {
    "DocumentMetadata": {
      "DocumentTitle": "דיון מהיר והצעה דחופה בנושא דומה",
      "PublicationDate": "",
      "OfficialSource": "חלק ד׳ - כלים פרלמנטריים / פרק חמישי - הצעות לסדר היום ודיונים מהירים / סעיף 61",
      "ReferenceLinks": [
        "https://he.wikisource.org/wiki/תקנון_הכנסת#סעיף_61"
      ],
      "Language": "עברית",
      "Version": "",
      "ClauseRepresentation": "main clause",
      "OfficialRoles": [
        {
          "Role": "חבר הכנסת",
          "ClauseLocation": "(א)",
          "Quote": "חבר הכנסת לא יגיש באותו שבוע הצעה דחופה והצעה לדיון מהיר בנושא דומה."
        }
      ],
      "OfficialOrganizations": [
        {
          "Organization": "נשיאות הכנסת",
          "ClauseLocation": "(א)",
          "Quote": "החליטה נשיאות הכנסת כי הצעה לדיון מהיר תאושר לדיון כהצעה דחופה"
        },
        {
          "Organization": "ועדת הכנסת",
          "ClauseLocation": "(ה)",
          "Quote": "אישרה ועדת הכנסת דיון בהצעה לסדר היום כהצעה דחופה"
        }
      ],
      "Placenames": [],
      "Description": "המסמך עוסק בהצעות דחופות ודיונים מהירים בכנסת."
    },
    "LegalReferences": [
      {
        "ReferenceTitle": "סעיף 54(ו)",
        "ReferenceText": "סעיף 54(ו)",
        "ReferenceQuote": "ורשאי חבר הכנסת שביקש שהצעתו תידון כהצעה דחופה, לערער על ההחלטה כאמורבסעיף 54(ו)."
      }
    ],
    "Amendments": [],
    "AdditionalKeywords": [
      "דיון מהיר",
      "הצעה דחופה",
      "נשיאות הכנסת",
      "ועדת הכנסת"
    ],
    "Topics": [
      "הצעות דחופות ודיונים מהירים בכנסת"
    ]
  },
  "title": "דיון מהיר והצעה דחופה בנושא דומה",
  "source_file": "תקנון הכנסת_61.md"
}