{
  "extracted_at": "2025-03-02T19:12:14.307964+00:00",
  "status": "processed",
  "context_type": "files",
  "context_name": "Knesset Bylaws (תקנון הכנסת) and related laws",
  "source_content": "**הכרזת מצב חירום לפיסעיף 38 לחוק־יסוד: הממשלה**\n\nמקור: חלק ו׳ - מצב חירום / פרק ראשון - הכרזת מצב חירום / סעיף 69\nקישור: https://he.wikisource.org/wiki/תקנון_הכנסת#סעיף_69\n\n * (א) החלטת הכנסת להכריז על מצב חירום, לא תתקבל אלא לפי המלצה של הוועדה המשותפת.\n * (ב) הציעו הממשלה או שלושים חברי הכנסת שהכנסת תכריז על מצב חירום, לפיסעיף 38(א) לחוק־יסוד: הממשלה, או שהכנסת תחזור ותכריז על מצב חירום, לפיסעיף 38(ב) לחוק היסוד, יעבירו את הצעתם אל יושב ראש הכנסת ואל הוועדה המשותפת; הצעה בעניין הכרזה חוזרת על מצב חירום תועבר לא יאוחר משישים ימים לפני תום מצב החירום.\n * (ג) הוועדה המשותפת תבחן את הצורך להכריז על מצב חירום, ואם הוצע לחזור ולהכריז על מצב חירום, תבחן גם את התקנות לשעת חירום שהותקנו מכוח ההכרזה האחרונה על מצב חירום ואת החקיקה שתוקפה מותנה בקיומו של מצב חירום.\n * (ד) הוועדה המשותפת תביא את המלצתה לאישור הכנסת, ואם ההמלצה היא בעניין הכרזה חוזרת, תביאה לאישור הכנסת לא יאוחר מ־14 ימים לפני תום מצב החירום.\n * (ה) היתה ההצעה להכרזה על מצב חירום יוזמה של שלושים חברי הכנסת, תאפשר הוועדה המשותפת לנציג המציעים לנמק את ההצעה לפניה.\n * (ו) תקופת תוקפה של הכרזה על מצב חירום לפי סעיף זה, לא תעלה על שנה מיום ההכרזה.\n * (ז) כל עוד לא נבחרו חברי ועדות הכנסת לאחר הבחירות, יהיו סמכויות הוועדה המשותפת לפיחלק זהנתונות לוועדה הזמנית לענייני חוץ וביטחון שהקימה הוועדה המסדרת לפיסעיף 2א(ה) לחוק הכנסת; ואולם, על אף הוראות סעיף קטן (ו), תקופת תוקפה של הכרזה על מצב חירום לפי הצעת הוועדה הזמנית לא תעלה על ארבעה חודשים מיום ההכרזה.",
  "document_type": "תקנון הכנסת",
  "extracted_data": {
    "DocumentMetadata": {
      "DocumentTitle": "הכרזת מצב חירום לפיסעיף 38 לחוק־יסוד: הממשלה",
      "PublicationDate": "",
      "OfficialSource": "חלק ו׳ - מצב חירום / פרק ראשון - הכרזת מצב חירום / סעיף 69",
      "ReferenceLinks": [
        "https://he.wikisource.org/wiki/תקנון_הכנסת#סעיף_69"
      ],
      "Language": "עברית",
      "Version": "",
      "ClauseRepresentation": "main clause",
      "OfficialRoles": [],
      "OfficialOrganizations": [
        {
          "Organization": "הכנסת",
          "ClauseLocation": "(א)",
          "Quote": "החלטת הכנסת להכריז על מצב חירום"
        },
        {
          "Organization": "הוועדה המשותפת",
          "ClauseLocation": "(א)",
          "Quote": "לפי המלצה של הוועדה המשותפת"
        },
        {
          "Organization": "הוועדה המשותפת",
          "ClauseLocation": "(ג)",
          "Quote": "הוועדה המשותפת תבחן את הצורך להכריז על מצב חירום"
        },
        {
          "Organization": "הוועדה המשותפת",
          "ClauseLocation": "(ד)",
          "Quote": "הוועדה המשותפת תביא את המלצתה לאישור הכנסת"
        },
        {
          "Organization": "הוועדה הזמנית לענייני חוץ וביטחון",
          "ClauseLocation": "(ז)",
          "Quote": "הוועדה המשותפת לפיחלק זה נתונות לוועדה הזמנית לענייני חוץ וביטחון"
        },
        {
          "Organization": "הוועדה המסדרת",
          "ClauseLocation": "(ז)",
          "Quote": "שהקימה הוועדה המסדרת לפיסעיף 2א(ה) לחוק הכנסת"
        }
      ],
      "Placenames": [],
      "Description": "המסמך עוסק בהליכי הכרזה על מצב חירום בישראל."
    },
    "LegalReferences": [
      {
        "ReferenceTitle": "חוק־יסוד: הממשלה",
        "ReferenceText": "פיסעיף 38(א) לחוק־יסוד: הממשלה",
        "ReferenceQuote": "הכנסת תכריז על מצב חירום, לפיסעיף 38(א) לחוק־יסוד: הממשלה"
      },
      {
        "ReferenceTitle": "חוק־יסוד: הממשלה",
        "ReferenceText": "פיסעיף 38(ב) לחוק היסוד",
        "ReferenceQuote": "הכנסת תחזור ותכריז על מצב חירום, לפיסעיף 38(ב) לחוק היסוד"
      },
      {
        "ReferenceTitle": "חוק הכנסת",
        "ReferenceText": "פיסעיף 2א(ה) לחוק הכנסת",
        "ReferenceQuote": "שהקימה הוועדה המסדרת לפיסעיף 2א(ה) לחוק הכנסת"
      }
    ],
    "Amendments": [],
    "AdditionalKeywords": [
      "מצב חירום",
      "הכנסת",
      "הוועדה המשותפת",
      "חקיקה",
      "הצעה"
    ],
    "Topics": [
      "החלטת הכנסת להכריז על מצב חירום",
      "הצעת הממשלה או חברי הכנסת להכריז על מצב חירום",
      "בחינת הצורך להכריז על מצב חירום",
      "המלצת הוועדה המשותפת לאישור הכנסת",
      "יוזמת חברי הכנסת להכרזה על מצב חירום",
      "תקופת תוקפה של הכרזה על מצב חירום",
      "סמכויות הוועדה המשותפת"
    ]
  },
  "title": "הכרזת מצב חירום לפיסעיף 38 לחוק־יסוד: הממשלה",
  "source_file": "תקנון הכנסת_69.md"
}