{
  "extracted_at": "2025-03-02T19:08:18.821357+00:00",
  "status": "processed",
  "context_type": "files",
  "context_name": "Knesset Bylaws (תקנון הכנסת) and related laws",
  "source_content": "**חזרה מהצעת חוק ממשלתית**\n\nמקור: חלק ז׳ - הליך החקיקה / פרק שביעי - הליך החקיקה – הוראות שונות (סימן ג׳: חזרה מהצעת חוק) / סעיף 95\nקישור: https://he.wikisource.org/wiki/תקנון_הכנסת#סעיף_95\n\n * (א) הממשלה רשאית לחזור בה מהצעת חוק ממשלתית כולה, כל עוד לא התקבל החוק בקריאה השלישית, בהודעה לכנסת; הודעת הממשלה על חזרה מהצעת חוק תימסר במליאת הכנסת על ידי שר, או סגן שר בענייני המשרד שבו הוא מכהן, או בהודעה בכתב של מזכיר הממשלה למזכיר הכנסת, ומזכיר הכנסת יודיע על כך לכנסת וליושב ראש הוועדה שאליה הועברה הצעת החוק.\n * (ב) עם מסירת הודעה כאמור בסעיף קטן (א) לכנסת או למזכיר הכנסת, לפי העניין, תוסר הצעת החוק מסדר יומה של הכנסת; מוזגה הצעת החוק הממשלתית עם הצעת חוק אחרת, יחולו הוראותסעיף 84(ה).\n * (ג) \n   * (1) על אף האמור בסעיף קטן (ב), החלה הקריאה השנייה והודיעה הממשלה כי היא חוזרת בה מהצעת החוק, תופסק הקריאה; הוראה זו תחול אף אם מוזגה הצעת החוק הממשלתית עם הצעת חוק אחרת.\n   * (2) הממשלה רשאית לחזור בה מהודעתה כאמור בפסקה (1) בחלוף שבוע ולא יאוחר משלושה שבועות מיום שנמסרה, בדרך האמורה בסעיף קטן (א); הודיעה הממשלה שהיא חוזרת בה מהודעתה – תימשך הקריאה השנייה מהמקום שבו הופסקה.\n   * (3) לא הודיעה הממשלה שהיא חוזרת בה מהודעתה כאמור בפסקה (1), תוסר הצעת החוק מסדר יומה של הכנסת; מוזגה הצעת החוק הממשלתית עם הצעת חוק אחרת שאושרה בקריאה הראשונה, תימשך הקריאה השנייה מהמקום שבו הופסקה.\n   * (4) במניין התקופה האמורה בפסקה (2) יובא בחשבון יום מסירת ההודעה, וימי הפגרה לא יבואו במניין.\n * (ד) חזרה בה הממשלה מהצעת חוק ממשלתית, אין היא רשאית להביא באותו מושב הצעת חוק אחרת באותו נושא, אלא אם כן החליטה ועדת הכנסת להתיר זאת; ואולם, הממשלה רשאית לחזור בה מחזרתה בהודעה כאמור בסעיף קטן (א), והליכי החקיקה יימשכו מהמקום שבו הופסקו.",
  "document_type": "תקנון הכנסת",
  "extracted_data": {
    "DocumentMetadata": {
      "DocumentTitle": "חזרה מהצעת חוק ממשלתית",
      "PublicationDate": "",
      "OfficialSource": "חלק ז׳ - הליך החקיקה / פרק שביעי - הליך החקיקה – הוראות שונות (סימן ג׳: חזרה מהצעת חוק) / סעיף 95",
      "ReferenceLinks": [
        "https://he.wikisource.org/wiki/תקנון_הכנסת#סעיף_95"
      ],
      "Language": "עברית",
      "Version": "",
      "ClauseRepresentation": "main clause",
      "OfficialRoles": [
        {
          "Role": "שר",
          "ClauseLocation": "(א)",
          "Quote": "הודעת הממשלה על חזרה מהצעת חוק תימסר במליאת הכנסת על ידי שר"
        },
        {
          "Role": "סגן שר",
          "ClauseLocation": "(א)",
          "Quote": "הודעת הממשלה על חזרה מהצעת חוק תימסר במליאת הכנסת על ידי סגן שר בענייני המשרד שבו הוא מכהן"
        },
        {
          "Role": "מזכיר הממשלה",
          "ClauseLocation": "(א)",
          "Quote": "בהודעה בכתב של מזכיר הממשלה למזכיר הכנסת"
        },
        {
          "Role": "מזכיר הכנסת",
          "ClauseLocation": "(א)",
          "Quote": "ומזכיר הכנסת יודיע על כך לכנסת וליושב ראש הוועדה"
        }
      ],
      "OfficialOrganizations": [
        {
          "Organization": "כנסת",
          "ClauseLocation": "(א)",
          "Quote": "הודעת הממשלה על חזרה מהצעת חוק תימסר במליאת הכנסת"
        },
        {
          "Organization": "ועדת הכנסת",
          "ClauseLocation": "(ד)",
          "Quote": "אלא אם כן החליטה ועדת הכנסת להתיר זאת"
        }
      ],
      "Placenames": [],
      "Description": "המסמך עוסק בהליכי חזרה מהצעת חוק ממשלתית."
    },
    "LegalReferences": [
      {
        "ReferenceTitle": "סעיף 84(ה)",
        "ReferenceText": "",
        "ReferenceQuote": "מוזגה הצעת החוק הממשלתית עם הצעת חוק אחרת, יחולו הוראות סעיף 84(ה)"
      }
    ],
    "Amendments": [],
    "AdditionalKeywords": [
      "חוק",
      "הצעת חוק",
      "ממשלה",
      "כנסת",
      "חוק ממשלתי"
    ],
    "Topics": [
      "הממשלה רשאית לחזור בה מהצעת חוק ממשלתית כולה",
      "הצעת החוק תוסר מסדר יומה של הכנסת",
      "החלה הקריאה השנייה והודיעה הממשלה כי היא חוזרת בה מהצעת החוק",
      "חזרה בה הממשלה מהצעת חוק ממשלתית"
    ]
  },
  "title": "חזרה מהצעת חוק ממשלתית",
  "source_file": "תקנון הכנסת_95.md"
}