{
  "extracted_at": "2025-03-02T19:17:11.437665+00:00",
  "status": "processed",
  "context_type": "files",
  "context_name": "Knesset Bylaws (תקנון הכנסת) and related laws",
  "source_content": "**מועד הדיון המוקדם והצמדה**\n\nמקור: חלק ז׳ - הליך החקיקה / פרק שני - הצעות חוק פרטיות (סימן ב׳: הדיון המוקדם) / סעיף 76\nקישור: https://he.wikisource.org/wiki/תקנון_הכנסת#סעיף_76\n\n * (א) בישיבת הכנסת שנועדה לכך כאמורבסעיף 25(ד), יתקיים דיון מוקדם בהצעות חוק פרטיות, במסגרת מכסה סיעתית שתקבע ועדת הכנסת לפיסעיף 99.\n * (ב) יושב ראש הכנסת רשאי לקבוע כי נוסף על הדיון המוקדם בהצעות חוק פרטיות כאמור בסעיף קטן (א), יתקיים דיון מוקדם בהצעות חוק פרטיות בישיבה לציון נושא מיוחד, ובלבד שהממשלה הודיעה, בהודעה בכתב של מזכיר הממשלה למזכיר הכנסת, שהיא תומכת בהן או שהיא מסכימה שיידונו באותה ישיבה; יושב ראש הכנסת רשאי לקבוע כי הצעות חוק לפי סעיף קטן זה לא יבואו במניין ההצעות לפיסעיף 99.\n * (ג) הדיון המוקדם לא יתקיים לפני שעברו 45 ימים מיום שהונחה הצעת החוק על שולחן הכנסת; לעניין זה יובאו במניין יום הנחתה של הצעת החוק על שולחן הכנסת ויום ההצבעה עליה.\n * (ד) על אף האמור בסעיף קטן (ג), הדיון המוקדם יכול שיתקיים לפני שעברו 45 ימים מיום שהצעת החוק הונחה על שולחן הכנסת באחת מאלה:\n   * (1) הממשלה הודיעה, בהודעה בכתב של מזכיר הממשלה למזכיר הכנסת, שהיא תומכת בהצעת החוק או שאין בדעתה לנקוט עמדה ביחס אליה, או שהיא מסכימה שתידון במועד מוקדם יותר;\n   * (2) ועדת הכנסת החליטה על קיצור תקופת ההנחה כאמור ברישה, לפי בקשת יוזם הצעת החוק, שאליה יצורף נוסח הצעת החוק, אם השתכנעה כי להצעת החוק יש חשיבות או דחיפות, ובעת ההצבעה נכחו בוועדת הכנסת לפחות שליש מחבריה הקבועים;\n   * (3) הדיון המוקדם בהצעת החוק הוצמד לדיון בהצעת חוק אחרת לפי הוראות סעיף קטן (ה).\n * (ה) לבקשת יוזם הצעת החוק, יצמיד מזכיר הכנסת את הדיון המוקדם של הצעת החוק (בחלק זה– הצעת החוק המוצמדת) לדיון המוקדם או לקריאה הראשונה של הצעת חוק אחרת (בחלק זה– הצעת החוק המקורית), אף אם יש בכך משום חריגה מהמכסה השבועית כאמורבסעיף 99, בהתקיים כל אלה:\n   * (1) הצעת החוק המוצמדת זהה או דומה בעיקרה להצעת החוק המקורית;\n   * (2) הצעת החוק המוצמדת היתה מונחת על שולחן הכנסת שבועיים לפחות לפני מועד הדיון או לכל הפחות כפרק הזמן שבו היתה מונחת הצעת החוק המקורית.\n * (ו) בקשת הצמדה תוגש למזכיר הכנסת עד סיום דיוני המליאה ביום שבו פורסם סדר היום לאותו שבוע או ביום שבו נוספה הצעת החוק המקורית לסדר היום.\n * (ז) יוזם הצעת חוק מוצמדת רשאי לחזור בו מבקשת ההצמדה, ובלבד שטרם נימק את הצעת החוק לפיסעיף 77(א).\n * (ח) לא יתקיים דיון מוקדם בהצעת חוק זהה או דומה בעיקרה להצעת חוק אחרת לפני שעברו שישה חודשים מיום החלטת הכנסת כמפורט להלן לגבי הצעת החוק האחרת, אלא אם כן החליט יושב ראש הכנסת, לבקשת יוזם הצעת החוק, על קיצור התקופה האמורה אם מצא שחל שינוי של ממש בנסיבות:\n   * (1) הצעת החוק הוסרה מסדר היום בדיון המוקדם או בקריאה הראשונה;\n   * (2) הצעת החוק הוסרה מסדר היום לפי הצעת ועדה, לפיסעיף 94;\n   * (3) הוחלט שנושא הצעת החוק יידון בוועדה כהצעה לסדר היום.",
  "document_type": "תקנון הכנסת",
  "extracted_data": {
    "DocumentMetadata": {
      "DocumentTitle": "מועד הדיון המוקדם והצמדה",
      "PublicationDate": "",
      "OfficialSource": "חלק ז׳ - הליך החקיקה / פרק שני - הצעות חוק פרטיות (סימן ב׳: הדיון המוקדם) / סעיף 76",
      "ReferenceLinks": [
        "https://he.wikisource.org/wiki/תקנון_הכנסת#סעיף_76"
      ],
      "Language": "עברית",
      "Version": "",
      "ClauseRepresentation": "main clause",
      "OfficialRoles": [
        {
          "Role": "יושב ראש הכנסת",
          "ClauseLocation": "(ב)",
          "Quote": "יושב ראש הכנסת רשאי לקבוע כי נוסף על הדיון המוקדם בהצעות חוק פרטיות כאמור בסעיף קטן (א)"
        },
        {
          "Role": "מזכיר הממשלה",
          "ClauseLocation": "(ב)",
          "Quote": "הממשלה הודיעה, בהודעה בכתב של מזכיר הממשלה למזכיר הכנסת"
        },
        {
          "Role": "מזכיר הכנסת",
          "ClauseLocation": "(ה)",
          "Quote": "מזכיר הכנסת את הדיון המוקדם של הצעת החוק"
        }
      ],
      "OfficialOrganizations": [
        {
          "Organization": "ועדת הכנסת",
          "ClauseLocation": "(א)",
          "Quote": "שקבעה ועדת הכנסת לפיסעיף 99"
        }
      ],
      "Placenames": [
        {
          "Name": "כנסת",
          "ClauseLocation": "(א)",
          "Quote": "בישיבת הכנסת שנועדה לכך"
        }
      ],
      "Description": "המסמך עוסק בהליכי הדיון המוקדם והצמדה של הצעות חוק פרטיות בכנסת."
    },
    "LegalReferences": [
      {
        "ReferenceTitle": "סעיף 25(ד)",
        "ReferenceText": "",
        "ReferenceQuote": "כאמורבסעיף 25(ד)"
      },
      {
        "ReferenceTitle": "סעיף 99",
        "ReferenceText": "",
        "ReferenceQuote": "מכסה סיעתית שתקבע ועדת הכנסת לפיסעיף 99"
      },
      {
        "ReferenceTitle": "סעיף 77(א)",
        "ReferenceText": "",
        "ReferenceQuote": "טרם נימק את הצעת החוק לפיסעיף 77(א)"
      },
      {
        "ReferenceTitle": "סעיף 94",
        "ReferenceText": "",
        "ReferenceQuote": "הוסרה מסדר היום לפי הצעת ועדה, לפיסעיף 94"
      }
    ],
    "Amendments": [],
    "AdditionalKeywords": [
      "דיון מוקדם",
      "הצעות חוק פרטיות",
      "הצמדה",
      "כנסת"
    ],
    "Topics": [
      "דיון מוקדם בהצעות חוק פרטיות",
      "קביעת דיון מוקדם בישיבה לציון נושא מיוחד",
      "מגבלות על מועד הדיון המוקדם",
      "אפשרויות לקיום דיון מוקדם לפני 45 ימים",
      "בקשת הצמדה של הצעות חוק"
    ]
  },
  "title": "מועד הדיון המוקדם והצמדה",
  "source_file": "תקנון הכנסת_76.md"
}