{
  "extracted_at": "2025-03-02T19:27:15.613116+00:00",
  "status": "processed",
  "context_type": "files",
  "context_name": "Knesset Bylaws (תקנון הכנסת) and related laws",
  "source_content": "**סדרי הדיון וההצבעה בהצעה לסדר היום**\n\nמקור: חלק ד׳ - כלים פרלמנטריים / פרק חמישי - הצעות לסדר היום ודיונים מהירים / סעיף 53\nקישור: https://he.wikisource.org/wiki/תקנון_הכנסת#סעיף_53\n\n * (א) בישיבת הכנסת שנועדה לכך כאמורבסעיף 25(ד), ינמק חבר הכנסת שהציע הצעה לסדר היום, או חבר אחר מסיעתו שהוא הסמיכו לכך, את ההצעה, במסגרת זמן שלא תעלה על עשר דקות; מזכיר הכנסת יקבע את סדר ההנמקה של הצעות לסדר היום, בהתחשב בסדר הגשתן.\n * (ב) יושב ראש הכנסת רשאי לקבוע כי נוסף על דיון בהצעות לסדר היום בישיבה כאמור בסעיף קטן (א), תדון הכנסת בהצעות לסדר היום בישיבה לציון נושא מיוחד; יושב ראש הכנסת רשאי לקבוע כי הצעות לסדר היום לפי סעיף קטן זה לא יבואו במניין ההצעות לפיסעיף 99.\n * (ג) נעדר חבר הכנסת מאולם המליאה בעת שנדרש לנמק את הצעתו לסדר היום, ולא הסמיך חבר אחר לנמקה, לא תישמר זכותו לנמק את ההצעה במועד אחר, אלא אם כן מצא יושב ראש הכנסת כי ההיעדרות מוצדקת.\n * (ד) \n   * (1) אחרי ההנמקה לפי סעיף קטן (א), רשאית הממשלה להביע את עמדתה ביחס להצעה ולהודיע על הסכמתה או על התנגדותה לכלול את הנושא המוצע בסדר היום של הכנסת, או להציע שהנושא יידון בוועדה מוועדות הכנסת; הממשלה רשאית להביע את עמדתה במרוכז על כמה הצעות בנושא דומה.\n   * (2) עמדת הממשלה כאמור בפסקה (1) תוצג על ידי אחד מאלה, בסדר זה: ראש הממשלה, השר שהנושא המוצע נמצא בסמכותו, או סגנו, ואם הנושא נמצא בסמכות ראש הממשלה – גם השר המקשר בין הממשלה לבין הכנסת, ואולם בנסיבות מיוחדות ואם יושב ראש הכנסת אישר זאת מראש, רשאית הממשלה להציג את עמדתה על ידי שר אחר.\n * (ה) \n   * (1) נגעה ההצעה לסדר היום לפעולתו של יושב ראש הכנסת, רשאים יושב ראש ועדת הכנסת ואחריו יושב ראש הכנסת להביע את עמדתם ביחס להצעה, לאחר הנמקת ההצעה ולפני שנשמעה עמדת הממשלה.\n   * (2) נגעה ההצעה לסדר היום לפעולתה של סיעה שאינה סיעתו של המציע או לפעולתו של חבר הכנסת הנמנה עם סיעה שאינה סיעתו של המציע, תהיה לאחד מחברי הסיעה האחרת, המדבר בשמה, או לחבר הכנסת האמור, הזכות להביע עמדה ביחס להצעה, במסגרת זמן שלא תעלה על עשר דקות; התשובה תינתן לאחר הנמקת ההצעה ולפני שנשמעה עמדת הממשלה.\n * (ו) אחרי שנשמעה עמדת הממשלה, ואם לא נשמעה – אחרי ההנמקה, רשאים שניים מחברי הכנסת להביע את עמדתם ביחס להצעה, והם רשאים להציע שהנושא המוצע לא ייכלל בסדר היום או שיידון בוועדה, והכל מהמקום המיועד לכך באולם המליאה ובמסגרת זמן שלא תעלה על דקה אחת לכל אחד מהם.\n * (ז) נשמעה עמדת הממשלה, והודיע המציע כי הוא מסתפק בדברי הממשלה – אין מצביעים; לעניין זה, אם היו כמה הצעות לסדר היום בנושא דומה, בהתאם לקביעת נשיאות הכנסת, תידרש הסכמת כל המציעים.\n * (ח) וזה סדר ההצבעה, ואם היו כמה הצעות לסדר היום בנושא דומה, בהתאם לקביעת נשיאות הכנסת – יצביעו על כולן כאחת:\n   * (1) לא התנגדה הממשלה לכלול את הנושא בסדר היום, ולא נשמעה הצעה כי הנושא יידון בוועדה – תתקיים הצבעה בעד או נגד הכללת הנושא בסדר היום;\n   * (2) נשמעה הצעה כי הנושא יידון בוועדה, וחבר הכנסת המציע הסכים לכך – תתקיים הצבעה בעד או נגד קיום דיון בוועדה; לעניין זה, אם היו כמה הצעות בנושא דומה, תתקיים הצבעה לפי פסקה זו רק אם הסכימו כל המציעים;\n   * (3) נשמעה הצעה כי הנושא יידון בוועדה, וחבר הכנסת המציע התנגד לכך – תתקיים הצבעה בעד או נגד הכללת הנושא בסדר היום; לא התקבלה ההצעה לכלול את הנושא בסדר היום – תתקיים הצבעה בעד או נגד קיום דיון בוועדה; לעניין זה, אם היו כמה הצעות בנושא דומה, תתקיים הצבעה לפי פסקה זו אם התנגדות כאמור נשמעה על ידי אחד המציעים לפחות.",
  "document_type": "תקנון הכנסת",
  "extracted_data": {
    "DocumentMetadata": {
      "DocumentTitle": "סדרי הדיון וההצבעה בהצעה לסדר היום",
      "PublicationDate": "",
      "OfficialSource": "חלק ד׳ - כלים פרלמנטריים / פרק חמישי - הצעות לסדר היום ודיונים מהירים / סעיף 53",
      "ReferenceLinks": [
        "https://he.wikisource.org/wiki/תקנון_הכנסת#סעיף_53"
      ],
      "Language": "עברית",
      "Version": "",
      "ClauseRepresentation": "main clause",
      "OfficialRoles": [
        {
          "Role": "יושב ראש הכנסת",
          "ClauseLocation": "(ב)",
          "Quote": "יושב ראש הכנסת רשאי לקבוע כי נוסף על דיון בהצעות לסדר היום"
        },
        {
          "Role": "מזכיר הכנסת",
          "ClauseLocation": "(א)",
          "Quote": "מזכיר הכנסת יקבע את סדר ההנמקה של הצעות לסדר היום"
        },
        {
          "Role": "ראש הממשלה",
          "ClauseLocation": "(ד)(2)",
          "Quote": "עמדת הממשלה כאמור בפסקה (1) תוצג על ידי אחד מאלה, בסדר זה: ראש הממשלה"
        },
        {
          "Role": "יושב ראש ועדת הכנסת",
          "ClauseLocation": "(ה)(1)",
          "Quote": "יושב ראש ועדת הכנסת ואחריו יושב ראש הכנסת להביע את עמדתם"
        }
      ],
      "OfficialOrganizations": [
        {
          "Organization": "הממשלה",
          "ClauseLocation": "(ד)(1)",
          "Quote": "רשאית הממשלה להביע את עמדתה ביחס להצעה"
        },
        {
          "Organization": "הכנסת",
          "ClauseLocation": "(ב)",
          "Quote": "תדון הכנסת בהצעות לסדר היום"
        }
      ],
      "Placenames": [],
      "Description": "המסמך מפרט את סדרי הדיון וההצבעה בהצעות לסדר היום בכנסת."
    },
    "LegalReferences": [],
    "Amendments": [],
    "AdditionalKeywords": [
      "סדר יום",
      "הצבעה",
      "דיון",
      "הצעות לסדר היום"
    ],
    "Topics": [
      "בישיבת הכנסת שנועדה לכך כאמור בסעיף 25(ד), ינמק חבר הכנסת שהציע הצעה לסדר היום",
      "יושב ראש הכנסת רשאי לקבוע כי נוסף על דיון בהצעות לסדר היום",
      "נעדר חבר הכנסת מאולם המליאה בעת שנדרש לנמק את הצעתו",
      "אחרי ההנמקה לפי סעיף קטן (א), רשאית הממשלה להביע את עמדתה",
      "נגעה ההצעה לסדר היום לפעולתו של יושב ראש הכנסת",
      "אחרי שנשמעה עמדת הממשלה, רשאים שניים מחברי הכנסת להביע את עמדתם",
      "נשמעה עמדת הממשלה, והודיע המציע כי הוא מסתפק בדברי הממשלה",
      "וזה סדר ההצבעה, ואם היו כמה הצעות לסדר היום בנושא דומה"
    ]
  },
  "title": "סדרי הדיון וההצבעה בהצעה לסדר היום",
  "source_file": "תקנון הכנסת_53.md"
}