{
  "extracted_at": "2025-03-02T19:44:55.785184+00:00",
  "status": "processed",
  "context_type": "files",
  "context_name": "Knesset Bylaws (תקנון הכנסת) and related laws",
  "source_content": "**חילופי חבר ועדת חקירה פרלמנטרית ומילוי מקום**\n\nמקור: חלק ח׳ - ועדות הכנסת / פרק שמיני - ועדת חקירה פרלמנטרית / סעיף 134\nקישור: https://he.wikisource.org/wiki/תקנון_הכנסת#סעיף_134\n\n * (א) נתפנה מקומו של חבר ועדת חקירה פרלמנטרית שאת חבריה בחרה ועדת הכנסת או החליטה סיעה על חילופי חבר מטעמה בוועדת חקירה כאמור, תבחר ועדת הכנסת חבר אחר במקומו; הוראות אלה יחולו גם לעניין יושב ראש ועדת החקירה.\n * (ב) יושב ראש ועדת הכנסת יודיע לכנסת מיהו חבר הוועדה החדש, וחברותו תהיה בתוקף מעת מסירת ההודעה לכנסת.\n * (ג) לחבר ועדת חקירה פרלמנטרית לא ימונה ממלא מקום קבוע לפיסעיף 103, ולעניין מילוי מקומו באופן ארעי יחולו הוראותסעיף 104.",
  "document_type": "תקנון הכנסת",
  "extracted_data": {
    "DocumentMetadata": {
      "DocumentTitle": "חילופי חבר ועדת חקירה פרלמנטרית ומילוי מקום",
      "PublicationDate": "",
      "OfficialSource": "חלק ח׳ - ועדות הכנסת / פרק שמיני - ועדת חקירה פרלמנטרית / סעיף 134",
      "ReferenceLinks": [
        "https://he.wikisource.org/wiki/תקנון_הכנסת#סעיף_134"
      ],
      "Language": "עברית",
      "Version": "",
      "ClauseRepresentation": "main clause",
      "OfficialRoles": [
        {
          "Role": "יושב ראש ועדת הכנסת",
          "ClauseLocation": "(ב)",
          "Quote": "יושב ראש ועדת הכנסת יודיע לכנסת מיהו חבר הוועדה החדש"
        }
      ],
      "OfficialOrganizations": [
        {
          "Organization": "ועדת הכנסת",
          "ClauseLocation": "(א)",
          "Quote": "חבר ועדת חקירה פרלמנטרית שאת חבריה בחרה ועדת הכנסת"
        }
      ],
      "Placenames": [],
      "Description": "המסמך עוסק בחילופי חברי ועדת חקירה פרלמנטרית ומילוי מקום."
    },
    "LegalReferences": [
      {
        "ReferenceTitle": "סעיף 103",
        "ReferenceText": "",
        "ReferenceQuote": "לחבר ועדת חקירה פרלמנטרית לא ימונה ממלא מקום קבוע לפיסעיף 103"
      },
      {
        "ReferenceTitle": "סעיף 104",
        "ReferenceText": "",
        "ReferenceQuote": "ולעניין מילוי מקומו באופן ארעי יחולו הוראותסעיף 104"
      }
    ],
    "Amendments": [],
    "AdditionalKeywords": [],
    "Topics": [
      "נתפנה מקומו של חבר ועדת חקירה פרלמנטרית",
      "יושב ראש ועדת הכנסת יודיע לכנסת מיהו חבר הוועדה החדש",
      "לחבר ועדת חקירה פרלמנטרית לא ימונה ממלא מקום קבוע"
    ]
  },
  "title": "חילופי חבר ועדת חקירה פרלמנטרית ומילוי מקום",
  "source_file": "תקנון הכנסת_134.md"
}