{
  "extracted_at": "2025-03-02T19:32:15.010745+00:00",
  "status": "processed",
  "context_type": "files",
  "context_name": "Knesset Bylaws (תקנון הכנסת) and related laws",
  "source_content": "**רציפות הדיון בהצעות חוק לפיחוק הרציפות**\n\nמקור: חלק ז׳ - הליך החקיקה / פרק שביעי - הליך החקיקה – הוראות שונות (סימן ד׳: רציפות הדיון בהצעות חוק לפיחוק הרציפות) / סעיף 97\nקישור: https://he.wikisource.org/wiki/תקנון_הכנסת#סעיף_97\n\n * (א) חבר הכנסת שמכהן בכנסת נכנסת ואינו שר או סגן שר רשאי לתת את הסכמתו להחלת דין רציפות על הצעת חוק שהציע בכנסת היוצאת, כאמורבסעיף 3 לחוק הרציפותבין כיוזם, אף אם אינו היוזם הראשון, ובין כמצטרף; לא מכהנים בכנסת הנכנסת מי שהיו יוזמים של הצעת החוק, יראו את כל המצטרפים כיוזמים.\n * (ב) \n   * (1) ועדה שאליה הועברה הצעת חוק פרטית או הצעת חוק מטעם ועדה בכנסת היוצאת, רשאית להציע להחיל עליה דין רציפות.\n   * (2) החליטה הכנסת להחיל רציפות על הצעת חוק שהועברה לוועדה בכנסת היוצאת, לפי הצעת ועדה או לפי הצעת הממשלה, יימשך הדיון באותה ועדה.\n   * (3) לא הועברה הצעת חוק בקריאה הראשונה לדיון בוועדה מסוימת בכנסת היוצאת או שהוועדה שאליה הועברה אינה קיימת או שאין היא מוסמכת עוד לאותו עניין, תקבע ועדת הכנסת את הוועדה שהצעת החוק היא בתחום ענייניה, ותודיע על כך לכנסת; נקבעה ועדה כאמור, היא רשאית להציע להחיל דין רציפות על הצעת חוק פרטית או על הצעת חוק מטעם ועדה, ולהמשיך לדון בהצעת החוק אם יוחל דין רציפות.\n   * (4) הועברה הצעת חוק לוועדה בכנסת היוצאת או קבעה ועדת הכנסת ועדה כאמור בפסקה (3), יחולו הוראותסעיף 83(ג)(1) ו־(3), לעניין העברת הצעת החוק לוועדה אחרת.\n * (ג) הודעת הממשלה על רצונה להחיל דין רציפות לפיסעיף 1 לחוק הרציפות, תוצג על ידי שר, סגן שר בענייני המשרד שבו הוא מכהן או סגן שר המקשר בין הממשלה לבין הכנסת.\n * (ד) הודעת ועדה על רצונה להחיל דין רציפות לפיסעיף 2 לחוק הרציפותעל הצעת חוק פרטית או על הצעת חוק מטעם ועדה, תוצג על ידי יושב ראש הוועדה.\n * (ה) הגישה סיעה או הממשלה התנגדות להחלת דין רציפות כאמורבסעיף 5 לחוק הרציפות, תנומק ההצעה על ידי אחד מחברי הסיעה או על ידי שר או סגן שר כאמור בסעיף קטן (ג), לפי העניין, במסגרת זמן שלא תעלה על חמש דקות; שר או סגן שר כאמור או יושב ראש הוועדה, לפי העניין, וכן אחד מחברי הכנסת שהציעו את הצעת החוק, ישיבו להתנגדויות, במסגרת זמן שלא תעלה על חמש דקות.\n * (ו) הכנסת תחליט אם להחיל דין רציפות או לקבל התנגדויות, ככל שהוגשו, והכל בהצבעה אחת.\n * (ז) החליטה הכנסת שלא להחיל רציפות על הצעת חוק, לא תימסר בכנסת הודעה נוספת על רצון להחיל דין רציפות על אותה הצעה.\n * (ח) החליטה כנסת נכנסת להחיל רציפות על הצעת חוק, תמשיך לדון בהצעת החוק, והיא רשאית לנהוג בדיונים שנתקיימו בכנסת היוצאת כאילו היו אלה דיונים שלה, כאמורבסעיף 6(ב) לחוק הרציפות, והחלטות פיצול שאושרו במליאת הכנסת היוצאת לפיסעיף 84(ב)יהיו בתוקף גם בכנסת הנכנסת.",
  "document_type": "תקנון הכנסת",
  "extracted_data": {
    "DocumentMetadata": {
      "DocumentTitle": "רציפות הדיון בהצעות חוק לפיחוק הרציפות",
      "PublicationDate": "",
      "OfficialSource": "חלק ז׳ - הליך החקיקה / פרק שביעי - הליך החקיקה – הוראות שונות (סימן ד׳: רציפות הדיון בהצעות חוק לפיחוק הרציפות) / סעיף 97",
      "ReferenceLinks": [
        "https://he.wikisource.org/wiki/תקנון_הכנסת#סעיף_97"
      ],
      "Language": "עברית",
      "Version": "",
      "ClauseRepresentation": "main clause",
      "OfficialRoles": [
        {
          "Role": "חבר הכנסת",
          "ClauseLocation": "(א)",
          "Quote": "חבר הכנסת שמכהן בכנסת נכנסת ואינו שר או סגן שר רשאי לתת את הסכמתו להחלת דין רציפות"
        },
        {
          "Role": "שר",
          "ClauseLocation": "(ג)",
          "Quote": "תוצג על ידי שר, סגן שר בענייני המשרד שבו הוא מכהן"
        },
        {
          "Role": "יושב ראש הוועדה",
          "ClauseLocation": "(ד)",
          "Quote": "תוצג על ידי יושב ראש הוועדה"
        }
      ],
      "OfficialOrganizations": [],
      "Placenames": [],
      "Description": "המסמך עוסק בהליך החקיקה של החלת דין רציפות על הצעות חוק בכנסת."
    },
    "LegalReferences": [
      {
        "ReferenceTitle": "חוק הרציפות",
        "ReferenceText": "סעיף 3 לחוק הרציפות",
        "ReferenceQuote": "כאמור בסעיף 3 לחוק הרציפות"
      },
      {
        "ReferenceTitle": "חוק הרציפות",
        "ReferenceText": "סעיף 1 לחוק הרציפות",
        "ReferenceQuote": "לפיסעיף 1 לחוק הרציפות"
      },
      {
        "ReferenceTitle": "חוק הרציפות",
        "ReferenceText": "סעיף 2 לחוק הרציפות",
        "ReferenceQuote": "לפיסעיף 2 לחוק הרציפות"
      },
      {
        "ReferenceTitle": "חוק הרציפות",
        "ReferenceText": "סעיף 5 לחוק הרציפות",
        "ReferenceQuote": "כאמורבסעיף 5 לחוק הרציפות"
      },
      {
        "ReferenceTitle": "חוק הרציפות",
        "ReferenceText": "סעיף 6(ב) לחוק הרציפות",
        "ReferenceQuote": "כאילו היו אלה דיונים שלה, כאמורבסעיף 6(ב) לחוק הרציפות"
      },
      {
        "ReferenceTitle": "חוק הרציפות",
        "ReferenceText": "סעיף 84(b)",
        "ReferenceQuote": "החלטות פיצול שאושרו במליאת הכנסת היוצאת לפיסעיף 84(ב) יהיו בתוקף גם בכנסת הנכנסת"
      },
      {
        "ReferenceTitle": "חוק הרציפות",
        "ReferenceText": "סעיף 83(ג)(1) ו־(3)",
        "ReferenceQuote": "יחולו הוראותסעיף 83(ג)(1) ו־(3)"
      }
    ],
    "Amendments": [],
    "AdditionalKeywords": [
      "דיון",
      "הצעת חוק",
      "רציפות",
      "כנסת",
      "ועדה"
    ],
    "Topics": [
      "חבר הכנסת יכול להחיל דין רציפות על הצעת חוק.",
      "ועדה יכולה להציע להחיל דין רציפות.",
      "הכנסת תחליט אם להחיל דין רציפות או לקבל התנגדויות.",
      "אם הכנסת לא מחליטה על רציפות, לא תימסר הודעה נוספת."
    ]
  },
  "title": "רציפות הדיון בהצעות חוק לפיחוק הרציפות",
  "source_file": "תקנון הכנסת_97.md"
}