{
  "extracted_at": "2025-03-02T19:11:00.349696+00:00",
  "status": "processed",
  "context_type": "files",
  "context_name": "Knesset Bylaws (תקנון הכנסת) and related laws",
  "source_content": "**נציגים לוועדות מינויים לנושאי משרה שיפוטית**\n\nמקור: חלק ה׳ - בחירה ומינוי של נושאי משרה / פרק ראשון - בחירת נציגים לוועדות מינויים בידי הכנסת / סעיף 62\nקישור: https://he.wikisource.org/wiki/תקנון_הכנסת#סעיף_62\n\n * (א) (הוראת שעה בתקופת כהונתה של הכנסת ה־25):בתוך שבעה חודשים מתחילת כהונתה, וכן בתוך שישים ימים מיום שהתפנה מקומו של נציג במהלך כהונתה של הכנסת, תבחר הכנסת את נציגיה לכל ועדה מוועדות המינויים והבחירה המנויות להלן (בפרק זה– ועדת מינויים):\n   * (1) הוועדה לבחירת דיינים שלפיסעיף 6 לחוק הדיינים, התשט״ו–1955;\n   * (2) הוועדה לבחירת קאדים שלפיסעיף 4 לחוק הקאדים;\n   * (3) ועדת המינויים שלפיסעיף 11 לחוק בתי הדין הדתיים הדרוזיים, התשכ״ג–1962(בסעיף זה – ועדת המינויים לקאדים–מד׳הב);\n   * (4) הוועדה לבחירת שופטים שלפיסעיף 4 לחוק־יסוד: השפיטה, ולפיסעיף 6 לחוק בתי המשפט.\n * (ב) \n   * (1) מזכיר הכנסת יודיע לכל חברי הכנסת על מועד הבחירה לוועדת מינויים שקבע יושב ראש הכנסת, לא יאוחר משבועיים לפני אותו מועד.\n   * (2) הצעת מועמדות תוגש ליושב ראש הכנסת בכתב עד נעילת ישיבת הכנסת ביום האחרון בשבוע שלפני יום הבחירה, ואם חל אותו שבוע בפגרה – לא יאוחר משבוע לפני מועד הבחירה.\n   * (3) כל אחד מחברי הכנסת, שאינו שר או סגן שר, רשאי להציע את מועמדותו לוועדת מינויים, למעט ועדת המינויים לקאדים–מד׳הב; ואולם לעניין הוועדה לבחירת קאדים, רשאי להציע את מועמדותו רק מי שחבר במפלגה אחרת מהמפלגה שבה חבר נציג הממשלה או נציג הכנסת בוועדה.\n   * (4) כל חבר כנסת דרוזי, שאינו שר או סגן שר, רשאי להציע את מועמדותו לוועדת המינויים לקאדים–מד׳הב, וכן רשאים כל עשרה מחברי הכנסת להציע את מועמדותו של דרוזי שאינו חבר הכנסת לוועדה האמורה; לא ישתף עצמו חבר הכנסת ביותר מהצעת מועמד אחד; להצעה תצורף הסכמתו של המועמד והצהרתו בדבר עמידתו בתנאים לבחירה לפיפרק זה.\n * (ג) מזכיר הכנסת יודיע לכל חברי הכנסת על שמות המועמדים לפחות 48 שעות לפני שעת פתיחת ישיבת הכנסת שבה יתקיימו הבחירות לוועדת המינויים.\n * (ד) בחירת נציגי הכנסת לוועדת מינויים תהיה בהצבעה חשאית, כמפורט להלן:\n   * (1) לפני תחילת ההצבעה, יודיע יושב ראש הכנסת לכנסת על הרכב ועדת קלפי שמינה לשם כך, ובה ארבעה חברי הכנסת שאינם מועמדים באותן בחירות, שניים מסיעות הקואליציה ושניים מסיעות האופוזיציה;\n   * (2) מזכיר הכנסת יקרא בשמות חברי הכנסת לפי סדר שמות משפחתם וכל אחד מחברי הכנסת, בזה אחר זה, ייגש להצביע במקום שיועד לכך באולם המליאה ומוסתר מעיני הזולת; הוראותסעיף 36(ב)יחולו לעניין זה, בשינויים המחויבים;\n   * (3) חבר הכנסת יקבל טופס ובו שמות המועמדים, בציון מספר נציגי הכנסת בוועדת המינויים שיש לבחרם; היה מספר המועמדים כמספר נציגי הכנסת שיש לבחרם, יתאפשר גם סימון של התנגדות לבחירת מי מהם;\n   * (4) הבחירה תיעשה בסימון שמות המועמדים על גבי הטופס, עד למספר נציגי הכנסת בוועדת המינויים שיש לבחרם או בסימון התנגדות לבחירתם, כאמור בפסקה (3); טופס שסומנו בו יותר מועמדים מהמספר האמור – פסול, ואם כלל הטופס מועמדים לכמה ועדות מינויים – יהיה פסול לעניין הוועדה שלגביה סומנו יותר מועמדים כאמור;\n   * (5) חבר הכנסת יניח את הטופס בתיבת הצבעה;\n   * (6) עם גמר ההצבעה תימסר תיבת ההצבעה לוועדת הקלפי, והיא תספור מיד את הקולות;\n   * (7) תוצאות ההצבעה ייקבעו לפי הוראות אלה:\n   * (8) ועדת הקלפי תודיע ליושב ראש הכנסת על תוצאות ההצבעה; יושב ראש הכנסת יודיע לכנסת באותה ישיבה שבה התקיימו הבחירות על תוצאותיהן.\n * (ה) מונה נציג הכנסת בוועדת מינויים לשר או לסגן שר, יחדל לכהן כנציג כאמור עם מינויו, ויתקיימו בחירות לנציג במקומו בהתאם להוראות סעיף זה.",
  "document_type": "תקנון הכנסת",
  "extracted_data": {
    "DocumentMetadata": {
      "DocumentTitle": "נציגים לוועדות מינויים לנושאי משרה שיפוטית",
      "PublicationDate": "",
      "OfficialSource": "חלק ה׳ - בחירה ומינוי של נושאי משרה / פרק ראשון - בחירת נציגים לוועדות מינויים בידי הכנסת / סעיף 62",
      "ReferenceLinks": [
        "https://he.wikisource.org/wiki/תקנון_הכנסת#סעיף_62"
      ],
      "Language": "עברית",
      "Version": "",
      "ClauseRepresentation": "main clause",
      "OfficialRoles": [
        {
          "Role": "מזכיר הכנסת",
          "ClauseLocation": "(ב)(1)",
          "Quote": "מזכיר הכנסת יודיע לכל חברי הכנסת על מועד הבחירה לוועדת מינויים שקבע יושב ראש הכנסת, לא יאוחר משבועיים לפני אותו מועד."
        },
        {
          "Role": "יושב ראש הכנסת",
          "ClauseLocation": "(ב)(1)",
          "Quote": "יושב ראש הכנסת, לא יאוחר משבועיים לפני אותו מועד."
        }
      ],
      "OfficialOrganizations": [],
      "Placenames": [],
      "Description": "המסמך עוסק בבחירה ומינוי נציגים לוועדות מינויים לנושאי משרה שיפוטית."
    },
    "LegalReferences": [
      {
        "ReferenceTitle": "חוק הדיינים",
        "ReferenceText": "חוק הדיינים, התשט״ו–1955",
        "ReferenceQuote": "הוועדה לבחירת דיינים שלפיסעיף 6 לחוק הדיינים, התשט״ו–1955;"
      },
      {
        "ReferenceTitle": "חוק הקאדים",
        "ReferenceText": "חוק הקאדים",
        "ReferenceQuote": "הוועדה לבחירת קאדים שלפיסעיף 4 לחוק הקאדים;"
      },
      {
        "ReferenceTitle": "חוק בתי הדין הדתיים הדרוזיים",
        "ReferenceText": "חוק בתי הדין הדתיים הדרוזיים, התשכ״ג–1962",
        "ReferenceQuote": "ועדת המינויים שלפיסעיף 11 לחוק בתי הדין הדתיים הדרוזיים, התשכ״ג–1962(בסעיף זה – ועדת המינויים לקאדים–מד׳הב);"
      },
      {
        "ReferenceTitle": "חוק יסוד: השפיטה",
        "ReferenceText": "חוק־יסוד: השפיטה",
        "ReferenceQuote": "הוועדה לבחירת שופטים שלפיסעיף 4 לחוק־יסוד: השפיטה, ולפיסעיף 6 לחוק בתי המשפט."
      }
    ],
    "Amendments": [],
    "AdditionalKeywords": [
      "וועדות מינויים",
      "נושאי משרה שיפוטית",
      "בחירה",
      "מינוי"
    ],
    "Topics": [
      "הוראת שעה בתקופת כהונתה של הכנסת ה־25",
      "מועד הבחירה לוועדת מינויים",
      "הצעת מועמדות לוועדת מינויים",
      "הצבעה חשאית לבחירת נציגי הכנסת"
    ]
  },
  "title": "נציגים לוועדות מינויים לנושאי משרה שיפוטית",
  "source_file": "תקנון הכנסת_62.md"
}