{
  "extracted_at": "2025-03-02T19:22:06.993082+00:00",
  "status": "processed",
  "context_type": "files",
  "context_name": "Knesset Bylaws (תקנון הכנסת) and related laws",
  "source_content": "**הכנת הצעת חוק פרטית לקריאה הראשונה, פיצול ומיזוג ופרסום ברשומות**\n\nמקור: חלק ז׳ - הליך החקיקה / פרק שלישי - הכנה לקריאה הראשונה (סימן א׳: הכנת הצעת חוק פרטית לקריאה הראשונה) / סעיף 79\nקישור: https://he.wikisource.org/wiki/תקנון_הכנסת#סעיף_79\n\n * (א) אושרה הצעת חוק בדיון המוקדם, תכין אותה הוועדה שאליה הועברה לקריאה הראשונה או תציע לכנסת להסירה מסדר היום; היו הקולות בוועדה שקולים, תציע הוועדה לכנסת להסיר את הצעת החוק מסדר היום.\n * (ב) ועדה רשאית, באישור הכנסת, לפצל הצעת חוק שהועברה אליה אחרי הדיון המוקדם לשתי הצעות חוק או יותר, כך שיובאו כהצעות חוק נפרדות לקריאה הראשונה; הצעת הפיצול תונח על שולחן הכנסת עם דברי הסבר, ויפורטו בהם החלקים מנוסח הצעת החוק שאושר בדיון המוקדם שייכללו בכל אחת מהצעות החוק הנפרדות, לפי סעיפים, נושאים או תקופות.\n * (ג) ועדה רשאית למזג שתי הצעות חוק או יותר באותו נושא שהועברו אליה אחרי הדיון המוקדם, ולהביאן כהצעת חוק אחת לקריאה הראשונה.\n * (ד) ועדה לא תכין לקריאה הראשונה הצעת חוק שיושב ראש הוועדה הוא אחד מיוזמיה, כל עוד מצויה על סדר יומה הצעת חוק פרטית אחרת שאושרה בדיון המוקדם ועברו שישה חודשים מהיום שהצעת החוק האחרת הועברה אליה או מהיום שבו נדונה לאחרונה בוועדה, אלא אם כן ביקש יוזם אותה הצעת חוק לדחות את הדיון בהצעתו; הוראה זו לא תחול בתום שישה חודשים מהיום שבו הועברה לוועדה הצעת החוק שיושב ראש הוועדה הוא אחד מיוזמיה.\n * (ה) הכינה ועדה הצעת חוק לקריאה הראשונה, יורה מזכיר הכנסת על פרסומה ברשומות – הצעות חוק הכנסת, בצירוף דברי הסבר.\n * (ו) \n   * (1) סדר השמות של חברי הכנסת על גבי הצעת החוק ברשומות יהיה כסדר שמותיהם על גבי הצעת החוק לדיון המוקדם, למעט מי מהם שחזר בו מהצעת החוק או שאינו רשאי עוד להגיש הצעת חוק פרטית ובהתאם להוראותסעיף 75(ג)(2)לעניין היוזם הראשון; שמות חברי הכנסת המצטרפים להצעת החוק יופיעו בנפרד לפי הסדר כאמור.\n   * (2) היתה הצעת החוק מיזוג של כמה הצעות חוק כאמור בסעיף קטן (ג), יצוינו על גבי הצעת החוק ברשומות שמותיהם של היוזמים הראשונים של כל הצעת חוק לדיון המוקדם תחילה, אחריהם שמותיהם של שאר היוזמים כסדרם על גבי כל הצעת חוק לדיון המוקדם, ובנפרד – שמותיהם של המצטרפים לכל הצעת חוק, והכל לפי סדר מועדי הדיון המוקדם בהן, ובהצעות חוק שהדיון המוקדם בהן התקיים באותו היום – לפי מספרן הסידורי.",
  "document_type": "תקנון הכנסת",
  "extracted_data": {
    "DocumentMetadata": {
      "DocumentTitle": "הכנת הצעת חוק פרטית לקריאה הראשונה, פיצול ומיזוג ופרסום ברשומות",
      "PublicationDate": "",
      "OfficialSource": "חלק ז׳ - הליך החקיקה / פרק שלישי - הכנה לקריאה הראשונה (סימן א׳: הכנת הצעת חוק פרטית לקריאה הראשונה) / סעיף 79",
      "ReferenceLinks": [
        "https://he.wikisource.org/wiki/תקנון_הכנסת#סעיף_79"
      ],
      "Language": "עברית",
      "Version": "",
      "ClauseRepresentation": "main clause",
      "OfficialRoles": [],
      "OfficialOrganizations": [
        {
          "Organization": "הכנסת",
          "ClauseLocation": "(ב)",
          "Quote": "ועדה רשאית, באישור הכנסת, לפצל הצעת חוק"
        }
      ],
      "Placenames": [],
      "Description": "המסמך עוסק בהכנת הצעת חוק פרטית לקריאה הראשונה, כולל פיצול ומיזוג הצעות חוק."
    },
    "LegalReferences": [],
    "Amendments": [],
    "AdditionalKeywords": [
      "הצעת חוק",
      "קריאה ראשונה",
      "פיצול",
      "מיזוג",
      "פרסום ברשומות"
    ],
    "Topics": [
      "אושרה הצעת חוק בדיון המוקדם, תכין אותה הוועדה שאליה הועברה לקריאה הראשונה",
      "ועדה רשאית, באישור הכנסת, לפצל הצעת חוק",
      "ועדה רשאית למזג שתי הצעות חוק",
      "ועדה לא תכין לקריאה הראשונה הצעת חוק שיושב ראש הוועדה הוא אחד מיוזמיה",
      "הכינה ועדה הצעת חוק לקריאה הראשונה, יורה מזכיר הכנסת על פרסומה ברשומות",
      "סדר השמות של חברי הכנסת על גבי הצעת החוק ברשומות"
    ]
  },
  "title": "הכנת הצעת חוק פרטית לקריאה הראשונה, פיצול ומיזוג ופרסום ברשומות",
  "source_file": "תקנון הכנסת_79.md"
}