{
  "extracted_at": "2025-03-02T19:44:45.604226+00:00",
  "status": "processed",
  "context_type": "files",
  "context_name": "Knesset Bylaws (תקנון הכנסת) and related laws",
  "source_content": "**הדיון בנושא שהכנסת החליטה לכלול בסדר היום**\n\nמקור: חלק ד׳ - כלים פרלמנטריים / פרק חמישי - הצעות לסדר היום ודיונים מהירים / סעיף 56\nקישור: https://he.wikisource.org/wiki/תקנון_הכנסת#סעיף_56\n\n * (א) החליטה הכנסת, בעקבות הצעה לסדר היום, לכלול נושא בסדר יומה, יקבע יושב ראש הכנסת את מועד הדיון בתוך שלושה חודשים מיום קבלת ההחלטה; חלפה התקופה האמורה ולא קבע יושב ראש הכנסת את מועד הדיון, יוסר הנושא מסדר היום, אלא אם כן חבר הכנסת המציע ביקש מיושב ראש הכנסת, בתוך שבועיים מתום התקופה האמורה, כי יקבע את מועד הדיון; ביקש חבר הכנסת כאמור, יקבע יושב ראש הכנסת את מועד הדיון בתוך שבועיים מיום הבקשה; ימי הפגרה לא יבואו במניין התקופות לפי סעיף קטן זה.\n * (ב) חבר הכנסת שהציע את ההצעה לסדר היום יפתח את הדיון האישי והוא רשאי לסכמו, ובהעדרו – חבר כנסת שהוא הסמיכו לכך, במסגרת הזמן האמורהבסעיף 29(3); הצביעה הכנסת על כמה הצעות בנושא דומה כאחת, יפתחו המציעים את הדיון בהתאם לסדר הנמקת הצעותיהם, ובדיון לפיסעיף 55– בהתאם לסדר הגשת הצעותיהם או לסדר אחר שעליו הסכימו.\n * (ג) \n   * (1) כל סיעה או כמה סיעות רשאיות להגיש ליושב ראש הכנסת, בכתב, הצעת החלטה לסיכום הדיון; נציג הסיעה או הסיעות יקרא את הצעת הסיכום לפני הכנסת, והיושב ראש יעמיד להצבעה אחת את השאלה אם לקבל את הצעת הסיכום, אף אם כללה כמה סעיפים.\n   * (2) סדר הקראת הצעות הסיכום יהיה לפי סדר גודלן של הסיעות, החל בסיעה הגדולה, וסדר ההצבעה יהיה לפי סדר גודלן, החל בסיעה הקטנה; הגישו כמה סיעות הצעת החלטה אחת, יראו אותן כסיעה אחת.\n * (ד) התקבלה החלטה לסיכום הדיון הקוראת לפעולה מצד הממשלה, יעביר יושב ראש הכנסת את ההחלטה לשר הנוגע בדבר, ואם לא ברור מיהו השר – לראש הממשלה; בתוך שישה חודשים מיום שקיבל את ההחלטה, יודיע השר האמור ליושב ראש הכנסת, בכתב, על כל פעולה שפעל בעקבות ההחלטה; הודעת השר תונח על שולחן הכנסת.",
  "document_type": "תקנון הכנסת",
  "extracted_data": {
    "DocumentMetadata": {
      "DocumentTitle": "הדיון בנושא שהכנסת החליטה לכלול בסדר היום",
      "PublicationDate": "",
      "OfficialSource": "חלק ד׳ - כלים פרלמנטריים / פרק חמישי - הצעות לסדר היום ודיונים מהירים / סעיף 56",
      "ReferenceLinks": [
        "https://he.wikisource.org/wiki/תקנון_הכנסת#סעיף_56"
      ],
      "Language": "עברית",
      "Version": "",
      "ClauseRepresentation": "main clause",
      "OfficialRoles": [
        {
          "Role": "יושב ראש הכנסת",
          "ClauseLocation": "(א)",
          "Quote": "יקבע יושב ראש הכנסת את מועד הדיון"
        },
        {
          "Role": "חבר הכנסת",
          "ClauseLocation": "(ב)",
          "Quote": "חבר הכנסת שהציע את ההצעה לסדר היום"
        },
        {
          "Role": "נציג הסיעה",
          "ClauseLocation": "(ג)(1)",
          "Quote": "נציג הסיעה או הסיעות יקרא את הצעת הסיכום"
        },
        {
          "Role": "שר",
          "ClauseLocation": "(ד)",
          "Quote": "יעביר יושב ראש הכנסת את ההחלטה לשר הנוגע בדבר"
        },
        {
          "Role": "ראש הממשלה",
          "ClauseLocation": "(ד)",
          "Quote": "אם לא ברור מיהו השר – לראש הממשלה"
        }
      ],
      "OfficialOrganizations": [
        {
          "Organization": "הכנסת",
          "ClauseLocation": "(א)",
          "Quote": "החליטה הכנסת"
        }
      ],
      "Placenames": [],
      "Description": "המסמך עוסק בהליך קביעת מועד דיון בכנסת בעקבות הצעה לסדר היום."
    },
    "LegalReferences": [],
    "Amendments": [],
    "AdditionalKeywords": [
      "דיון",
      "סדר היום",
      "הצעה",
      "הצבעה",
      "סיכום"
    ],
    "Topics": [
      "ההליך לקביעת מועד דיון בכנסת",
      "פתיחת הדיון על ידי חבר הכנסת המציע",
      "הגשת הצעות החלטה לסיכום הדיון",
      "העברת החלטות לשר הנוגע בדבר"
    ]
  },
  "title": "הדיון בנושא שהכנסת החליטה לכלול בסדר היום",
  "source_file": "תקנון הכנסת_56.md"
}