{
  "extracted_at": "2025-03-02T19:08:25.504727+00:00",
  "status": "processed",
  "context_type": "files",
  "context_name": "Knesset Bylaws (תקנון הכנסת) and related laws",
  "source_content": "**הנחה על שולחן הכנסת ומועד הקריאה השנייה**\n\nמקור: חלק ז׳ - הליך החקיקה / פרק שישי - הקריאה השנייה והקריאה השלישית / סעיף 88\nקישור: https://he.wikisource.org/wiki/תקנון_הכנסת#סעיף_88\n\n * (א) מזכיר הכנסת יניח על שולחן הכנסת הצעת חוק שוועדה הכינה לקריאה השנייה ולקריאה השלישית; יושב ראש הכנסת יעמיד את הצעת החוק על סדר יומה של הכנסת.\n * (ב) הקריאה השנייה תחל לכל המוקדם למחרת ההנחה על שולחן הכנסת, אלא אם כן החליטה ועדת הכנסת על קיצור תקופת ההנחה כאמור, לפי בקשה בכתב של הוועדה שהכינה את הצעת החוק, ולגבי הצעת חוק ממשלתית – גם לפי בקשה של הממשלה, בהודעה בכתב של מזכיר הממשלה; לבקשה יצורף נוסח הצעת החוק.",
  "document_type": "תקנון הכנסת",
  "extracted_data": {
    "DocumentMetadata": {
      "DocumentTitle": "הנחה על שולחן הכנסת ומועד הקריאה השנייה",
      "PublicationDate": "",
      "OfficialSource": "חלק ז׳ - הליך החקיקה / פרק שישי - הקריאה השנייה והקריאה השלישית / סעיף 88",
      "ReferenceLinks": [
        "https://he.wikisource.org/wiki/תקנון_הכנסת#סעיף_88"
      ],
      "Language": "עברית",
      "Version": "",
      "ClauseRepresentation": "main clause",
      "OfficialRoles": [
        {
          "Role": "מזכיר הכנסת",
          "ClauseLocation": "(א)",
          "Quote": "מזכיר הכנסת יניח על שולחן הכנסת הצעת חוק"
        },
        {
          "Role": "יושב ראש הכנסת",
          "ClauseLocation": "(א)",
          "Quote": "יושב ראש הכנסת יעמיד את הצעת החוק על סדר יומה של הכנסת"
        },
        {
          "Role": "מזכיר הממשלה",
          "ClauseLocation": "(ב)",
          "Quote": "בהודעה בכתב של מזכיר הממשלה"
        }
      ],
      "OfficialOrganizations": [
        {
          "Organization": "ועדת הכנסת",
          "ClauseLocation": "(ב)",
          "Quote": "החליטה ועדת הכנסת על קיצור תקופת ההנחה"
        },
        {
          "Organization": "הממשלה",
          "ClauseLocation": "(ב)",
          "Quote": "גם לפי בקשה של הממשלה"
        }
      ],
      "Placenames": [
        {
          "Name": "כנסת",
          "ClauseLocation": "(א)",
          "Quote": "על שולחן הכנסת"
        }
      ],
      "Description": "המסמך עוסק בהנחה על שולחן הכנסת ובמועד הקריאה השנייה והשלישית של הצעות חוק."
    },
    "LegalReferences": [],
    "Amendments": [],
    "AdditionalKeywords": [
      "הנחה",
      "קריאה שנייה",
      "קריאה שלישית",
      "הצעת חוק"
    ],
    "Topics": [
      "מזכיר הכנסת יניח על שולחן הכנסת הצעת חוק שוועדה הכינה לקריאה השנייה ולקריאה השלישית",
      "הקריאה השנייה תחל לכל המוקדם למחרת ההנחה על שולחן הכנסת"
    ]
  },
  "title": "הנחה על שולחן הכנסת ומועד הקריאה השנייה",
  "source_file": "תקנון הכנסת_88.md"
}