{
  "extracted_at": "2025-03-02T19:27:49.270251+00:00",
  "status": "processed",
  "context_type": "files",
  "context_name": "Knesset Bylaws (תקנון הכנסת) and related laws",
  "source_content": "**מען והודעות**\n\nמקור: חלק ב׳ - ארגון הכנסת / פרק שלישי - חברי הכנסת / סעיף 12\nקישור: https://he.wikisource.org/wiki/תקנון_הכנסת#סעיף_12\n\n * (א) עם היבחרו, יודיע חבר הכנסת למזכיר הכנסת, בכתב, על מספר הטלפון שלו וכן על מען, מספר פקסימילה וכתובת דואר אלקטרוני, לצורך מסירת מסמכים מאת הכנסת, וכן יודיע על כל שינוי בפרטים אלה; יראו מסירת מסמכים או מתן הודעה בטלפון, כאמור, כהודעה מספקת, ואולם בימים שבהם מליאת הכנסת מתכנסת, יראו הנחת מסמך על שולחן הכנסת או מסירתו בחדרו של חבר הכנסת במשכן הכנסת, כהודעה מספקת.\n * (ב) חבר הכנסת הנוסע לחוץ לארץ חייב להודיע על כך ליושב ראש הכנסת, ולציין את זמן שהותו בחוץ לארץ, את מקום הימצאו ואת מספר הטלפון באותו מקום.",
  "document_type": "תקנון הכנסת",
  "extracted_data": {
    "DocumentMetadata": {
      "DocumentTitle": "מען והודעות",
      "PublicationDate": "",
      "OfficialSource": "חלק ב׳ - ארגון הכנסת / פרק שלישי - חברי הכנסת / סעיף 12",
      "ReferenceLinks": [
        "https://he.wikisource.org/wiki/תקנון_הכנסת#סעיף_12"
      ],
      "Language": "עברית",
      "Version": "",
      "ClauseRepresentation": "main clause",
      "OfficialRoles": [
        {
          "Role": "חבר הכנסת",
          "ClauseLocation": "(א)",
          "Quote": "חבר הכנסת הנוסע לחוץ לארץ חייב להודיע על כך ליושב ראש הכנסת"
        },
        {
          "Role": "יושב ראש הכנסת",
          "ClauseLocation": "(ב)",
          "Quote": "חבר הכנסת הנוסע לחוץ לארץ חייב להודיע על כך ליושב ראש הכנסת"
        },
        {
          "Role": "מזכיר הכנסת",
          "ClauseLocation": "(א)",
          "Quote": "יודיע חבר הכנסת למזכיר הכנסת, בכתב, על מספר הטלפון שלו"
        }
      ],
      "OfficialOrganizations": [
        {
          "Organization": "הכנסת",
          "ClauseLocation": "(א)",
          "Quote": "מסירת מסמכים מאת הכנסת"
        }
      ],
      "Placenames": [
        {
          "Name": "חוץ לארץ",
          "ClauseLocation": "(ב)",
          "Quote": "חבר הכנסת הנוסע לחוץ לארץ"
        },
        {
          "Name": "משכן הכנסת",
          "ClauseLocation": "(א)",
          "Quote": "מסירתו בחדרו של חבר הכנסת במשכן הכנסת"
        }
      ],
      "Description": "המסמך עוסק בהודעות חברי הכנסת על פרטי קשר ושינויים בהם."
    },
    "LegalReferences": [],
    "Amendments": [],
    "AdditionalKeywords": [
      "הודעות",
      "חבר הכנסת",
      "יושב ראש הכנסת",
      "מזכיר הכנסת",
      "מסמכים"
    ],
    "Topics": [
      "חבר הכנסת חייב להודיע על פרטי קשר.",
      "חבר הכנסת הנוסע לחוץ לארץ חייב להודיע על כך."
    ]
  },
  "title": "מען והודעות",
  "source_file": "תקנון הכנסת_12.md"
}