{
  "extracted_at": "2025-03-02T19:44:13.697975+00:00",
  "status": "processed",
  "context_type": "files",
  "context_name": "Knesset Bylaws (תקנון הכנסת) and related laws",
  "source_content": "**הנוהל בדיון בהשתתפות ראש הממשלה לפיסעיף 42 לחוק־יסוד: הממשלה**\n\nמקור: חלק ד׳ - כלים פרלמנטריים / פרק שני - דיון בהשתתפות ראש הממשלה / סעיף 45\nקישור: https://he.wikisource.org/wiki/תקנון_הכנסת#סעיף_45\n\n * (א) הוגשה ליושב ראש הכנסת דרישה לקיים דיון בהשתתפות ראש הממשלה לפיסעיף 42(ב) לחוק־יסוד: הממשלה, תקיים הכנסת את הדיון בתוך 21 ימים מקבלת הדרישה, וימי הפגרה לא יבואו במניין.\n * (ב) לא ייקבע דיון כאמור בסעיף קטן (א) ביום שבו נקבע דיון בהצעה להביע אי־אמון בממשלה שהוגשה בדרך של הצעת סעיף לסדר היום; נקבע מועד הדיון כאמור בסעיף קטן (א), ולאחר מכן נקבע לאותו היום דיון בהצעה להביע אי־אמון בממשלה שהוגשה בדרך של הצעת סעיף לסדר היום, יקבע יושב ראש הכנסת מועד אחר לדיון כאמור בסעיף קטן (א), שיהיה בתוך 30 ימים מקבלת הדרישה וימי הפגרה לא יבואו במניין.\n * (ג) פחת מארבעים מספר חברי הכנסת הדורשים את הדיון בהשתתפות ראש הממשלה, בעקבות הודעתו בכתב של חבר הכנסת ליושב ראש הכנסת כי הוא חוזר בו מהדרישה, לא יתקיים הדיון; ואולם אם פחת המספר כאמור בתוך 72 שעות שלפני פתיחת ישיבת הכנסת שבה היה אמור להיערך הדיון – יתקיים הדיון, אלא אם כן חזרו בהם כל חברי הכנסת שהגישו את הדרישה.\n * (ד) וזה סדר הדיון:\n   * (1) אחד מחברי הכנסת שהגישו את הדרישה לקיים את הדיון, לפי קביעתם של מגישי הדרישה, יפתח את הדיון במסגרת זמן שלא תעלה על עשר דקות;\n   * (2) לדיון תוקצב מסגרת זמן של שישים דקות, שתחולק בין הסיעות לפי גודלן, ובלבד שמסגרת הזמן לכל סיעה לא תפחת משלוש דקות; דברי הפתיחה כאמור בפסקה (1) וכן דברי ראש הממשלה וראש האופוזיציה לא יבואו במניין הזמן האמור בפסקה זו;\n   * (3) ראש הממשלה ישתתף בכל מהלך הדיון, ובמהלכו יציג פעם אחת את עמדתו;\n   * (4) ראש האופוזיציה ישתתף בכל מהלך הדיון, והוא רשאי לנאום מיד אחרי ראש הממשלה כאמורבסעיף 14 לחוק הכנסת;\n   * (5) הוראותסעיף 31לא יחולו על דיון לפי סעיף זה;\n   * (6) בתום הדיון תצביע הכנסת על העמדה שהציג ראש הממשלה.",
  "document_type": "תקנון הכנסת",
  "extracted_data": {
    "DocumentMetadata": {
      "DocumentTitle": "הנוהל בדיון בהשתתפות ראש הממשלה לפיסעיף 42 לחוק־יסוד: הממשלה",
      "PublicationDate": "",
      "OfficialSource": "חלק ד׳ - כלים פרלמנטריים / פרק שני - דיון בהשתתפות ראש הממשלה / סעיף 45",
      "ReferenceLinks": [
        "https://he.wikisource.org/wiki/תקנון_הכנסת#סעיף_45"
      ],
      "Language": "עברית",
      "Version": "",
      "ClauseRepresentation": "main clause",
      "OfficialRoles": [
        {
          "Role": "יושב ראש הכנסת",
          "ClauseLocation": "(א)",
          "Quote": "הוגשה ליושב ראש הכנסת דרישה לקיים דיון"
        },
        {
          "Role": "ראש הממשלה",
          "ClauseLocation": "(ג)",
          "Quote": "ראש הממשלה ישתתף בכל מהלך הדיון"
        },
        {
          "Role": "ראש האופוזיציה",
          "ClauseLocation": "(ג)",
          "Quote": "ראש האופוזיציה ישתתף בכל מהלך הדיון"
        }
      ],
      "OfficialOrganizations": [
        {
          "Organization": "הכנסת",
          "ClauseLocation": "(א)",
          "Quote": "תקיים הכנסת את הדיון"
        }
      ],
      "Placenames": [],
      "Description": "הנוהל מתאר את ההליך לקיום דיון בהשתתפות ראש הממשלה בהתאם לחוק־יסוד: הממשלה."
    },
    "LegalReferences": [
      {
        "ReferenceTitle": "חוק־יסוד: הממשלה",
        "ReferenceText": "פיסעיף 42(ב)",
        "ReferenceQuote": "דרישה לקיים דיון בהשתתפות ראש הממשלה לפיסעיף 42(ב) לחוק־יסוד: הממשלה"
      },
      {
        "ReferenceTitle": "חוק הכנסת",
        "ReferenceText": "סעיף 14",
        "ReferenceQuote": "הוא רשאי לנאום מיד אחרי ראש הממשלה כאמורבסעיף 14 לחוק הכנסת"
      },
      {
        "ReferenceTitle": "חוק הכנסת",
        "ReferenceText": "סעיף 31",
        "ReferenceQuote": "הוראותסעיף 31לא יחולו על דיון לפי סעיף זה"
      }
    ],
    "Amendments": [],
    "AdditionalKeywords": [
      "דיון",
      "ראש הממשלה",
      "חוק־יסוד",
      "הכנסת",
      "אי־אמון"
    ],
    "Topics": [
      "הדיון יתקיים בתוך 21 ימים מקבלת הדרישה.",
      "לא ייקבע דיון ביום שבו נקבע דיון בהצעה להביע אי־אמון.",
      "אם פחת מארבעים מספר חברי הכנסת, לא יתקיים הדיון.",
      "סדר הדיון כולל זמן פתיחה, זמן לכל סיעה, והצבעה על העמדה שהציג ראש הממשלה."
    ]
  },
  "title": "הנוהל בדיון בהשתתפות ראש הממשלה לפיסעיף 42 לחוק־יסוד: הממשלה",
  "source_file": "תקנון הכנסת_45.md"
}