{
  "extracted_at": "2025-03-02T19:42:48.313829+00:00",
  "status": "processed",
  "context_type": "files",
  "context_name": "Knesset Bylaws (תקנון הכנסת) and related laws",
  "source_content": "**תפקידי יושב ראש הכנסת וסגן ליושב ראש הכנסת**\n\nמקור: חלק ב׳ - ארגון הכנסת / פרק ראשון - יושב ראש הכנסת וסגניו / סעיף 6\nקישור: https://he.wikisource.org/wiki/תקנון_הכנסת#סעיף_6\n\n * (א) יושב ראש הכנסת ינהל את ענייני הכנסת, ייצג אותה כלפי חוץ, ישמור על כבודה, על הסדר בישיבותיה ועל קיום תקנונה; הוא ישב ראש בישיבות הכנסת וינהלן, ובכלל זה יקבע את תוצאות ההצבעות וכן ימלא כל תפקיד המוטל עליו לפי דין.\n * (ב) יושב ראש הכנסת אחראי על הכנתו וביצועו של תקציב הכנסת; אושרה הצעת התקציב השנתי של הכנסת בקריאה הראשונה במסגרת הצעת חוק התקציב השנתי, תועבר לדיון בוועדה המשותפת של ועדת הכנסת וועדת הכספים האמורהבסעיף 11(ב) לחוק יסודות התקציב; ההצעה תובא לקריאה השניה ולקריאה השלישית במסגרת הצעת חוק התקציב השנתי.\n * (ג) יושב ראש הכנסת אחראי על מינהל הכנסת ועל מזכירות הכנסת.\n * (ד) בכהונתו כנשיא המדינה בפועל כאמורבסעיף 23(א) לחוק־יסוד: נשיא המדינה, לא ינהל יושב ראש הכנסת את ישיבות הכנסת, אלא אם כן החליטה ועדת הכנסת אחרת.\n * (ה) יושב ראש הכנסת לא יהיה חבר בוועדה מוועדות הכנסת, פרט לוועדת הפירושים, ואולם הוא רשאי להשתתף בדיוני כל אחת מוועדות הכנסת ובכלל זה ועדות משותפות וועדות משנה, אף אם הפרוטוקול שלהן חסוי.\n * (ו) יושב ראש הכנסת רשאי למסור, מזמן לזמן, את ניהול ישיבת הכנסת או כל תפקיד מתפקידיו שנקבעו בתקנון זה, לאחד הסגנים, למעט תפקידיו לפי סעיפים קטנים (ב) ו־(ג).\n * (ז) לסגן ליושב ראש הכנסת, הממלא את מקומו של יושב ראש הכנסת כאמורבסעיף 29 לחוק משכן הכנסת, או שיושב ראש הכנסת אצל לו מסמכויותיו כאמורבסעיף 30(א) לחוק האמור, או המנהל את ישיבת הכנסת או הממלא אחד מתפקידי יושב ראש הכנסת, יהיו, באותו מעמד, כל החובות והסמכויות הנתונות ליושב ראש הכנסת.\n * (ח) סגן ליושב ראש הכנסת לא יהיה יושב ראש ועדת הכנסת או ממלא מקומו.",
  "document_type": "תקנון הכנסת",
  "extracted_data": {
    "DocumentMetadata": {
      "DocumentTitle": "תפקידי יושב ראש הכנסת וסגן ליושב ראש הכנסת",
      "PublicationDate": "",
      "OfficialSource": "חלק ב׳ - ארגון הכנסת / פרק ראשון - יושב ראש הכנסת וסגניו / סעיף 6",
      "ReferenceLinks": [
        "https://he.wikisource.org/wiki/תקנון_הכנסת#סעיף_6"
      ],
      "Language": "עברית",
      "Version": "",
      "ClauseRepresentation": "main clause",
      "OfficialRoles": [
        {
          "Role": "יושב ראש הכנסת",
          "ClauseLocation": "(א)",
          "Quote": "יושב ראש הכנסת ינהל את ענייני הכנסת, ייצג אותה כלפי חוץ, ישמור על כבודה, על הסדר בישיבותיה ועל קיום תקנונה"
        },
        {
          "Role": "סגן ליושב ראש הכנסת",
          "ClauseLocation": "(ז)",
          "Quote": "סגן ליושב ראש הכנסת, הממלא את מקומו של יושב ראש הכנסת"
        }
      ],
      "OfficialOrganizations": [
        {
          "Organization": "ועדת הכנסת",
          "ClauseLocation": "(ד)",
          "Quote": "לא ינהל יושב ראש הכנסת את ישיבות הכנסת, אלא אם כן החליטה ועדת הכנסת אחרת"
        },
        {
          "Organization": "ועדת הכספים",
          "ClauseLocation": "(ב)",
          "Quote": "תועבר לדיון בוועדה המשותפת של ועדת הכנסת וועדת הכספים"
        }
      ],
      "Placenames": [],
      "Description": "המסמך מפרט את תפקידי יושב ראש הכנסת וסגן יושב ראש הכנסת."
    },
    "LegalReferences": [
      {
        "ReferenceTitle": "חוק יסודות התקציב",
        "ReferenceText": "סעיף 11(ב)",
        "ReferenceQuote": "אושרה הצעת התקציב השנתי של הכנסת בקריאה הראשונה במסגרת הצעת חוק התקציב השנתי"
      },
      {
        "ReferenceTitle": "חוק־יסוד: נשיא המדינה",
        "ReferenceText": "סעיף 23(א)",
        "ReferenceQuote": "בכהונתו כנשיא המדינה בפועל כאמור"
      },
      {
        "ReferenceTitle": "חוק משכן הכנסת",
        "ReferenceText": "סעיף 29",
        "ReferenceQuote": "הממלא את מקומו של יושב ראש הכנסת כאמור"
      },
      {
        "ReferenceTitle": "חוק משכן הכנסת",
        "ReferenceText": "סעיף 30(א)",
        "ReferenceQuote": "שיושב ראש הכנסת אצל לו מסמכויותיו כאמור"
      }
    ],
    "Amendments": [],
    "AdditionalKeywords": [
      "תפקידים",
      "יושב ראש הכנסת",
      "סגן יושב ראש הכנסת",
      "ועדות הכנסת",
      "תקציב הכנסת"
    ],
    "Topics": [
      "יושב ראש הכנסת אחראי על הכנתו וביצועו של תקציב הכנסת.",
      "יושב ראש הכנסת לא יהיה חבר בוועדה מוועדות הכנסת, פרט לוועדת הפירושים.",
      "סגן ליושב ראש הכנסת לא יהיה יושב ראש ועדת הכנסת או ממלא מקומו."
    ]
  },
  "title": "תפקידי יושב ראש הכנסת וסגן ליושב ראש הכנסת",
  "source_file": "תקנון הכנסת_6.md"
}