{
  "extracted_at": "2025-03-02T19:29:52.631444+00:00",
  "status": "processed",
  "context_type": "files",
  "context_name": "Knesset Bylaws (תקנון הכנסת) and related laws",
  "source_content": "**סייגים לזימון ולמסירת מידע**\n\nמקור: חלק ח׳ - ועדות הכנסת / פרק שביעי - מוזמנים לישיבות הוועדות ומסירת מידע לוועדות / סעיף 124\nקישור: https://he.wikisource.org/wiki/תקנון_הכנסת#סעיף_124\n\n * (א) עובד, נושא משרה או ממלא תפקיד שנדרש למסור מידע לוועדה לפיסעיף 123ימסור אותו במלואו, אלא אם כן חלים על המידע הסייגים הקבועיםבסעיף 21(ב) לחוק־יסוד: הכנסתאובסעיף 42(א) לחוק־יסוד: הממשלה; ואולם חלים סייגים כאמור וניתן להעביר את המידע המבוקש תוך השמטת החלקים שחלים עליהם הסייגים, או להעבירו בתנאים, יועבר המידע בחלקו או בתנאים, ובכלל זה שישיבת הוועדה לא תהיה פומבית, שפרוטוקול הישיבה יהיה חסוי או שהמידע יימסר רק ליושב ראש הוועדה.\n * (ב) הודעה שלפיה לא ניתן למסור לוועדה מידע כמפורט בסעיף קטן (א), או שניתן למסור מידע בחלקו או בתנאים, תימסר, בצירוף נימוקים ובלי לחשוף מידע כאמור, בידי השר או ראש הגוף כאמורבסעיף 123(ה)ליושב ראש הוועדה, ולבקשת מוסר ההודעה היא תהיה חסויה.",
  "document_type": "תקנון הכנסת",
  "extracted_data": {
    "DocumentMetadata": {
      "DocumentTitle": "סייגים לזימון ולמסירת מידע",
      "PublicationDate": "",
      "OfficialSource": "חלק ח׳ - ועדות הכנסת / פרק שביעי - מוזמנים לישיבות הוועדות ומסירת מידע לוועדות / סעיף 124",
      "ReferenceLinks": [
        "https://he.wikisource.org/wiki/תקנון_הכנסת#סעיף_124"
      ],
      "Language": "עברית",
      "Version": "",
      "ClauseRepresentation": "main clause",
      "OfficialRoles": [
        {
          "Role": "יושב ראש הוועדה",
          "ClauseLocation": "(א)",
          "Quote": "יושב ראש הוועדה"
        },
        {
          "Role": "השר או ראש הגוף",
          "ClauseLocation": "(ב)",
          "Quote": "השר או ראש הגוף"
        }
      ],
      "OfficialOrganizations": [],
      "Placenames": [],
      "Description": "המסמך עוסק בסייגים למסירת מידע לוועדות הכנסת."
    },
    "LegalReferences": [
      {
        "ReferenceTitle": "חוק־יסוד: הכנסת",
        "ReferenceText": "סעיף 21(ב)",
        "ReferenceQuote": "סעיף 21(ב) לחוק־יסוד: הכנסת"
      },
      {
        "ReferenceTitle": "חוק־יסוד: הממשלה",
        "ReferenceText": "סעיף 42(א)",
        "ReferenceQuote": "סעיף 42(א) לחוק־יסוד: הממשלה"
      },
      {
        "ReferenceTitle": "חוק־יסוד: הכנסת",
        "ReferenceText": "סעיף 123",
        "ReferenceQuote": "סעיף 123(ה) לחוק־יסוד: הכנסת"
      }
    ],
    "Amendments": [],
    "AdditionalKeywords": [
      "סייגים",
      "מסירת מידע",
      "וועדה",
      "חוק־יסוד"
    ],
    "Topics": [
      "עובד, נושא משרה או ממלא תפקיד שנדרש למסור מידע לוועדה.",
      "הודעה שלפיה לא ניתן למסור לוועדה מידע."
    ]
  },
  "title": "סייגים לזימון ולמסירת מידע",
  "source_file": "תקנון הכנסת_124.md"
}