{
  "extracted_at": "2025-03-02T19:09:16.594524+00:00",
  "status": "processed",
  "context_type": "files",
  "context_name": "Knesset Bylaws (תקנון הכנסת) and related laws",
  "source_content": "**סדרי הקריאה הראשונה**\n\nמקור: חלק ז׳ - הליך החקיקה / פרק רביעי - הקריאה הראשונה / סעיף 82\nקישור: https://he.wikisource.org/wiki/תקנון_הכנסת#סעיף_82\n\n * (א) הדיון האישי בקריאה הראשונה ייפתח בהנמקה של הצעת החוק, במסגרת זמן שלא תעלה על עשר דקות, על ידי אחד מאלה, לפי העניין, והוא רשאי לסכם את הדיון:\n   * (1) בהצעת חוק פרטית – יוזם הצעת החוק או חבר כנסת אחר שהוא הסמיכו לכך; היתה הצעת החוק מיזוג של כמה הצעות חוק כאמורבסעיף 79(ג), ייפתח ויסוכם הדיון על ידי היוזם ששמו מופיע ראשון על גבי הצעת החוק או חבר כנסת אחר שהוא הסמיכו לכך; ואולם לאחר ההנמקה כאמור, רשאי היוזם הראשון של כל אחת מהצעות החוק הנוספות שמוזגו לנמק את הצעת החוק במסגרת זמן שלא תעלה על חמש דקות, לפי סדר השמות על גבי הצעת החוק;\n   * (2) בהצעת חוק מטעם ועדה – יושב ראש הוועדה;\n   * (3) בהצעת חוק ממשלתית – שר, או סגן שר בענייני המשרד שבו הוא מכהן.\n * (ב) היה מוצמד לקריאה הראשונה בהצעת חוק דיון מוקדם בהצעת חוק אחרת, רשאי יוזם הצעת החוק המוצמדת או חבר כנסת אחר שהוא הסמיכו לכך, לנמק את הצעתו מיד לאחר הנמקת הצעת החוק המקורית, במסגרת זמן שלא תעלה על שלוש דקות.\n * (ג) אחרי ההנמקה של הצעת חוק פרטית או של הצעת חוק מטעם ועדה רשאי שר, או סגן שר בענייני המשרד שבו הוא מכהן, להביע את עמדת הממשלה ביחס להצעת החוק.\n * (ד) היו על סדר היום כמה הצעות חוק בנושא דומה בהתאם לקביעת נשיאות הכנסת, רשאי יושב ראש הכנסת לקבוע כי יתקיים דיון משולב בהצעות החוק, והוראות סעיף זה יחולו בשינויים המחויבים.\n * (ה) בתום הדיון תחליט הכנסת אם לאשר את הצעת החוק או להסירה מסדר היום, ולעניין דחיית ההצבעה יחולו הוראותסעיף 35; הוצמד לקריאה הראשונה דיון מוקדם בהצעת חוק אחרת, תחליט הכנסת לגביה כאמור בהצבעה נפרדת שתתקיים מיד.\n * (ו) סיעה שכל חבריה לא השתתפו בדיון ולא השתתפו בהצבעה או נמנעו, רשאי אחד מחבריה למסור בשמה הודעה בקשר לכך מיד לאחר ההצבעה, במסגרת זמן שלא תעלה על חמש דקות.",
  "document_type": "תקנון הכנסת",
  "extracted_data": {
    "DocumentMetadata": {
      "DocumentTitle": "סדרי הקריאה הראשונה",
      "PublicationDate": "",
      "OfficialSource": "חלק ז׳ - הליך החקיקה / פרק רביעי - הקריאה הראשונה / סעיף 82",
      "ReferenceLinks": [
        "https://he.wikisource.org/wiki/תקנון_הכנסת#סעיף_82"
      ],
      "Language": "עברית",
      "Version": "",
      "ClauseRepresentation": "main clause",
      "OfficialRoles": [
        {
          "Role": "יושב ראש הוועדה",
          "ClauseLocation": "(א)(2)",
          "Quote": "בהצעת חוק מטעם ועדה – יושב ראש הוועדה"
        },
        {
          "Role": "שר",
          "ClauseLocation": "(א)(3)",
          "Quote": "בהצעת חוק ממשלתית – שר, או סגן שר בענייני המשרד שבו הוא מכהן"
        },
        {
          "Role": "סגן שר",
          "ClauseLocation": "(א)(3)",
          "Quote": "בהצעת חוק ממשלתית – שר, או סגן שר בענייני המשרד שבו הוא מכהן"
        },
        {
          "Role": "יושב ראש הכנסת",
          "ClauseLocation": "(ד)",
          "Quote": "רשאי יושב ראש הכנסת לקבוע כי יתקיים דיון משולב בהצעות החוק"
        }
      ],
      "OfficialOrganizations": [],
      "Placenames": [],
      "Description": "המסמך מפרט את סדרי הקריאה הראשונה של הצעות חוק בכנסת."
    },
    "LegalReferences": [],
    "Amendments": [],
    "AdditionalKeywords": [
      "הצעת חוק",
      "דיון",
      "כנסת",
      "יושב ראש",
      "שר",
      "סגן שר"
    ],
    "Topics": [
      "הדיון האישי בקריאה הראשונה",
      "הנמקה של הצעת החוק",
      "דיון מוקדם בהצעת חוק אחרת",
      "עמדת הממשלה ביחס להצעת החוק",
      "דיון משולב בהצעות החוק",
      "הצבעה על הצעת החוק"
    ]
  },
  "title": "סדרי הקריאה הראשונה",
  "source_file": "תקנון הכנסת_82.md"
}