{
  "extracted_at": "2025-03-02T19:44:39.301889+00:00",
  "status": "processed",
  "context_type": "files",
  "context_name": "Knesset Bylaws (תקנון הכנסת) and related laws",
  "source_content": "**הנחה על שולחן הכנסת ומועד הקריאה הראשונה**\n\nמקור: חלק ז׳ - הליך החקיקה / פרק רביעי - הקריאה הראשונה / סעיף 81\nקישור: https://he.wikisource.org/wiki/תקנון_הכנסת#סעיף_81\n\n * (א) מזכיר הכנסת יניח על שולחן הכנסת הצעת חוק פרטית, הצעת חוק מטעם ועדה או הצעת חוק ממשלתית שפורסמה ברשומות ונמסרה לכנסת.\n * (ב) יושב ראש הכנסת יעמיד את הצעת החוק על סדר יומה של הכנסת, ואולם הקריאה הראשונה של הצעת חוק מטעם ועדה או של הצעת חוק ממשלתית לא תתקיים אלא לאחר שחלפו יומיים מיום שהונחה; במניין התקופה האמורה יובא בחשבון יום הנחתה של הצעת החוק על שולחן הכנסת.\n * (ג) ועדת הכנסת רשאית להחליט על קיצור תקופת ההנחה כאמור בסעיף קטן (ב), לפי בקשה בכתב של הוועדה שיזמה את הצעת החוק, ולגבי הצעת חוק ממשלתית – בקשה של הממשלה, בהודעה בכתב של מזכיר הממשלה, ויחולו הוראותסעיף 76(ד)(2); לבקשה יצורף נוסח הצעת החוק.",
  "document_type": "תקנון הכנסת",
  "extracted_data": {
    "DocumentMetadata": {
      "DocumentTitle": "הנחה על שולחן הכנסת ומועד הקריאה הראשונה",
      "PublicationDate": "",
      "OfficialSource": "חלק ז׳ - הליך החקיקה / פרק רביעי - הקריאה הראשונה / סעיף 81",
      "ReferenceLinks": [
        "https://he.wikisource.org/wiki/תקנון_הכנסת#סעיף_81"
      ],
      "Language": "עברית",
      "Version": "",
      "ClauseRepresentation": "main clause",
      "OfficialRoles": [
        {
          "Role": "מזכיר הכנסת",
          "ClauseLocation": "(א)",
          "Quote": "מזכיר הכנסת יניח על שולחן הכנסת הצעת חוק פרטית"
        },
        {
          "Role": "יושב ראש הכנסת",
          "ClauseLocation": "(ב)",
          "Quote": "יושב ראש הכנסת יעמיד את הצעת החוק על סדר יומה של הכנסת"
        },
        {
          "Role": "ועדת הכנסת",
          "ClauseLocation": "(ג)",
          "Quote": "ועדת הכנסת רשאית להחליט על קיצור תקופת ההנחה"
        },
        {
          "Role": "הממשלה",
          "ClauseLocation": "(ג)",
          "Quote": "בקשה של הממשלה, בהודעה בכתב של מזכיר הממשלה"
        }
      ],
      "OfficialOrganizations": [],
      "Placenames": [
        {
          "Name": "כנסת",
          "ClauseLocation": "(א)",
          "Quote": "על שולחן הכנסת"
        }
      ],
      "Description": "המסמך עוסק בהנחה על שולחן הכנסת ובמועד הקריאה הראשונה של הצעות חוק."
    },
    "LegalReferences": [
      {
        "ReferenceTitle": "סעיף 76(ד)(2)",
        "ReferenceText": "",
        "ReferenceQuote": "הוראות סעיף 76(ד)(2)"
      }
    ],
    "Amendments": [],
    "AdditionalKeywords": [
      "הצעת חוק",
      "קריאה ראשונה",
      "הנחה"
    ],
    "Topics": [
      "מזכיר הכנסת יניח על שולחן הכנסת הצעת חוק פרטית",
      "יושב ראש הכנסת יעמיד את הצעת החוק על סדר יומה של הכנסת",
      "ועדת הכנסת רשאית להחליט על קיצור תקופת ההנחה"
    ]
  },
  "title": "הנחה על שולחן הכנסת ומועד הקריאה הראשונה",
  "source_file": "תקנון הכנסת_81.md"
}