{
  "extracted_at": "2025-03-02T19:21:21.718252+00:00",
  "status": "processed",
  "context_type": "files",
  "context_name": "Knesset Bylaws (תקנון הכנסת) and related laws",
  "source_content": "**בחירת יושב ראש הכנסת וסגניו**\n\nמקור: חלק ב׳ - ארגון הכנסת / פרק ראשון - יושב ראש הכנסת וסגניו / סעיף 2\nקישור: https://he.wikisource.org/wiki/תקנון_הכנסת#סעיף_2\n\n * (א) הכנסת תבחר, בבחירות גלויות, את יושב ראש הכנסת ואת הסגנים ליושב ראש הכנסת, בהתאם להוראותסעיף 20 לחוק־יסוד: הכנסת,וסעיף 10 לחוק הכנסת; הסגנים ייבחרו בהמלצת ועדת הכנסת, וכל עוד לא נבחרה – בהמלצת הוועדה המסדרת, בהתחשב בהרכב הסיעתי של הכנסת ובגודל הסיעות; בחירתם של כמה סגנים באותו מועד תיעשה בהצבעה אחת בלבד.\n * (ב) יושב ראש הכנסת ייבחר לא יאוחר מהמועד שבו כונסה הכנסת לצורך כינון הממשלה, כאמורבסעיף 13 לחוק־יסוד: הממשלה; נקבעה בחירת יושב ראש הכנסת לאותו מועד שבו נקבעה ישיבה לצורך כינון הממשלה, ייבחר תחילה יושב ראש הכנסת.\n * (ג) יושב ראש הכנסת והסגנים ייבחרו לכל תקופת כהונתה של הכנסת; ואולם רשאית הכנסת לבחור, לפי המלצה כאמור בסעיף קטן (א), סגנים ליושב ראש הכנסת לתקופות כהונה קצרות יותר, ולקבוע את תחילתן ואת סופן.\n * (ד) שר או סגן שר לא יהיה יושב ראש הכנסת או סגן ליושב ראש הכנסת.\n * (ה) \n   * (1) נתפנתה משרתו של יושב ראש הכנסת, תבחר הכנסת, בתוך 21 ימים, יושב ראש חדש, בדרך הקבועה בסעיף קטן (א); נתפנתה משרה של סגן ליושב ראש הכנסת, רשאית הכנסת לבחור חבר כנסת אחר במקומו, בדרך האמורה.\n   * (2) הושעה סגן ליושב ראש הכנסת מכהונתו, רשאית הכנסת לבחור חבר כנסת אחר במקומו בדרך האמורה, ועל אף האמור ברישה של סעיף קטן (ג), הוא יכהן כסגן ליושב ראש בתקופת ההשעיה בלבד.",
  "document_type": "תקנון הכנסת",
  "extracted_data": {
    "DocumentMetadata": {
      "DocumentTitle": "בחירת יושב ראש הכנסת וסגניו",
      "PublicationDate": "",
      "OfficialSource": "חלק ב׳ - ארגון הכנסת / פרק ראשון - יושב ראש הכנסת וסגניו / סעיף 2",
      "ReferenceLinks": [
        "https://he.wikisource.org/wiki/תקנון_הכנסת#סעיף_2"
      ],
      "Language": "עברית",
      "Version": "",
      "ClauseRepresentation": "main clause",
      "OfficialRoles": [
        {
          "Role": "יושב ראש הכנסת",
          "ClauseLocation": "(א)",
          "Quote": "יושב ראש הכנסת ייבחר לא יאוחר מהמועד שבו כונסה הכנסת לצורך כינון הממשלה"
        },
        {
          "Role": "סגן יושב ראש הכנסת",
          "ClauseLocation": "(א)",
          "Quote": "את הסגנים ליושב ראש הכנסת"
        },
        {
          "Role": "שר",
          "ClauseLocation": "(ד)",
          "Quote": "שר או סגן שר לא יהיה יושב ראש הכנסת או סגן ליושב ראש הכנסת"
        },
        {
          "Role": "סגן שר",
          "ClauseLocation": "(ד)",
          "Quote": "שר או סגן שר לא יהיה יושב ראש הכנסת או סגן ליושב ראש הכנסת"
        }
      ],
      "OfficialOrganizations": [
        {
          "Organization": "ועדת הכנסת",
          "ClauseLocation": "(א)",
          "Quote": "בהמלצת ועדת הכנסת"
        },
        {
          "Organization": "הוועדה המסדרת",
          "ClauseLocation": "(א)",
          "Quote": "בהמלצת הוועדה המסדרת"
        }
      ],
      "Placenames": [],
      "Description": "המסמך עוסק בבחירת יושב ראש הכנסת וסגניו, כולל הליך הבחירה ותנאים נלווים."
    },
    "LegalReferences": [
      {
        "ReferenceTitle": "חוק־יסוד: הכנסת",
        "ReferenceText": "סעיף 20 לחוק־יסוד: הכנסת",
        "ReferenceQuote": "בהתאם להוראות סעיף 20 לחוק־יסוד: הכנסת"
      },
      {
        "ReferenceTitle": "חוק הכנסת",
        "ReferenceText": "סעיף 10 לחוק הכנסת",
        "ReferenceQuote": "בהתאם להוראות סעיף 10 לחוק הכנסת"
      },
      {
        "ReferenceTitle": "חוק־יסוד: הממשלה",
        "ReferenceText": "סעיף 13 לחוק־יסוד: הממשלה",
        "ReferenceQuote": "כאמור בסעיף 13 לחוק־יסוד: הממשלה"
      }
    ],
    "Amendments": [],
    "AdditionalKeywords": [
      "בחירות",
      "יושב ראש הכנסת",
      "סגנים",
      "ועדת הכנסת",
      "הוועדה המסדרת"
    ],
    "Topics": [
      "הכנסת תבחר, בבחירות גלויות, את יושב ראש הכנסת ואת הסגנים ליושב ראש הכנסת",
      "יושב ראש הכנסת ייבחר לא יאוחר מהמועד שבו כונסה הכנסת לצורך כינון הממשלה",
      "יושב ראש הכנסת והסגנים ייבחרו לכל תקופת כהונתה של הכנסת",
      "שר או סגן שר לא יהיה יושב ראש הכנסת או סגן ליושב ראש הכנסת",
      "נתפנתה משרתו של יושב ראש הכנסת, תבחר הכנסת, בתוך 21 ימים, יושב ראש חדש"
    ]
  },
  "title": "בחירת יושב ראש הכנסת וסגניו",
  "source_file": "תקנון הכנסת_2.md"
}