{
  "extracted_at": "2025-03-02T19:23:46.457702+00:00",
  "status": "processed",
  "context_type": "files",
  "context_name": "Knesset Bylaws (תקנון הכנסת) and related laws",
  "source_content": "**חקיקה הצריכה תקציב**\n\nמקור: חלק ז׳ - הליך החקיקה / פרק שביעי - הליך החקיקה – הוראות שונות (סימן א׳: עלות תקציבית) / סעיף 93\nקישור: https://he.wikisource.org/wiki/תקנון_הכנסת#סעיף_93\n\n * (א) בהכינה הצעת חוק שאינה הצעת חוק ממשלתית לקריאה הראשונה, וכן לקריאה השנייה ולקריאה השלישית, תזמין ועדה לדיוניה את שר האוצר או את מי שהוא הסמיך לכך (בסעיף זה – השר), כדי לברר את הערכתו בדבר העלות התקציבית של הצעת החוק או של הסתייגות, לפי העניין, לצורך קביעתה בידי הוועדה לפי הוראותסעיף 3ג לחוק־יסוד: משק המדינהולפיסעיף 39א לחוק יסודות התקציב.\n * (ב) חבר הכנסת רשאי להציע לוועדה לקבל הערכה אחרת בדבר העלות התקציבית של הצעת חוק; הערכה אחרת תוגש, אם לא קבעה הוועדה אחרת, על ידי מרכז המחקר והמידע של הכנסת;הוועדה תזמין את מגיש ההערכה האחרת כדי לברר את הערכתו, וכן היא רשאית להזמין את מי שנתן לו נתונים לצורך ההערכה האמורה; הוגשה הערכה אחרת, תאפשר הוועדה לשר להגיב עליה.\n * (ג) הערכת השר והערכה אחרת בדבר העלות התקציבית של הצעת חוק או הסתייגות יוגשו לוועדה לפני הדיון בהכנת הצעת החוק לקריאה הראשונה או לקריאה השנייה ולקריאה השלישית, לפי העניין, ואם לא ניתן למסרן לפני הדיון – בעת הדיון או אחריו, בתוך זמן סביר שקצב לכך יושב ראש הוועדה.\n * (ד) \n   * (1) הממשלה תמסור לוועדה המכינה את הצעת החוק את עמדתה כאמורבסעיף 3ג(ד) לחוק־יסוד: משק המדינה; עמדת הממשלה תימסר בהודעה בכתב של מזכיר הממשלה, ככל האפשר עם מסירת הערכת השר בדבר העלות התקציבית או בתוך זמן סביר שקצב לכך יושב ראש הוועדה, וכל עוד הצעת החוק לא הונחה על שולחן הכנסת.\n   * (2) בדברי ההסבר להצעת חוק המתפרסמת לקריאה הראשונה תצוין עלותה התקציבית; קבעה הוועדה שהעלות התקציבית עולה על הסכום הנקובבסעיף 3ג לחוק־יסוד: משק המדינה, תצוין בדברי ההסבר גם היותה הצעת חוק תקציבית, זולת אם הממשלה נתנה את הסכמתה כאמורבחוק היסודאו אם חל לגביה הסייג האמורבסעיף 3ג(ו) לחוק היסוד.\n   * (3) קבעה ועדה שלהצעת חוק שהכינה לקריאה השנייה ולקריאה השלישית יש עלות תקציבית העולה על הסכום הנקובבסעיף 3ג לחוק־יסוד: משק המדינה, יצוין על גבי הנוסח המונח על שולחן הכנסת כי הצעת החוק היא הצעת חוק תקציבית, זולת אם הממשלה נתנה את הסכמתה כאמור בחוק היסוד או אם חל לגביה הסייג האמורבסעיף 3ג(ו) לחוק היסוד; הוראות פסקה זו יחולו גם על הסתייגות תקציבית.\n * (ה) הונחה הצעת חוק על שולחן הכנסת, רשאית הממשלה להודיע על שינוי עמדתה בעניין הסכמתה לעלות התקציבית של הצעת החוק, בהודעה במליאת הכנסת שתימסר על ידי שר או סגן שר או בהודעה בכתב של מזכיר הממשלה למזכיר הכנסת, ומזכיר הכנסת יודיע על כך לכנסת וליושב ראש הוועדה שהכינה את הצעת החוק; ואולם, אם בשל הודעת הממשלה תהפוך הצעת החוק להצעת חוק תקציבית, תימסר ההודעה לא יאוחר מהיום שלפני הדיון בהצעת החוק, ואם ההצבעה מתקיימת ביום הנחת הצעת החוק – עד לפני תחילת הדיון בה.\n * (ו) הודעה על עדכון הסכומים הנקובים בהגדרות ”הצעת חוק תקציבית“ ו”הסתייגות תקציבית“בסעיף 3ג(ד) לחוק־יסוד: משק המדינה, כאמורבסעיף 3ג(ה) לחוק היסוד, תפורסם ברשומות מטעם הכנסת.",
  "document_type": "תקנון הכנסת",
  "extracted_data": {
    "DocumentMetadata": {
      "DocumentTitle": "חקיקה הצריכה תקציב",
      "PublicationDate": "",
      "OfficialSource": "סעיף 93",
      "ReferenceLinks": [
        "https://he.wikisource.org/wiki/תקנון_הכנסת#סעיף_93"
      ],
      "Language": "עברית",
      "Version": "",
      "ClauseRepresentation": "main clause",
      "OfficialRoles": [
        {
          "Role": "שר האוצר",
          "ClauseLocation": "(א)",
          "Quote": "תזמין ועדה לדיוניה את שר האוצר או את מי שהוא הסמיך לכך"
        },
        {
          "Role": "מזכיר הממשלה",
          "ClauseLocation": "(ד)(1)",
          "Quote": "תימסר בהודעה בכתב של מזכיר הממשלה"
        },
        {
          "Role": "סגן שר",
          "ClauseLocation": "(ה)",
          "Quote": "בהודעה במליאת הכנסת שתימסר על ידי שר או סגן שר"
        }
      ],
      "OfficialOrganizations": [
        {
          "Organization": "הכנסת",
          "ClauseLocation": "(ב)",
          "Quote": "מרכז המחקר והמידע של הכנסת"
        }
      ],
      "Placenames": [],
      "Description": "הוראות שונות לגבי חקיקה הצריכה תקציב והערכות תקציביות."
    },
    "LegalReferences": [
      {
        "ReferenceTitle": "חוק־יסוד: משק המדינה",
        "ReferenceText": "סעיף 3ג",
        "ReferenceQuote": "לפי הוראות סעיף 3ג לחוק־יסוד: משק המדינה"
      },
      {
        "ReferenceTitle": "חוק יסודות התקציב",
        "ReferenceText": "סעיף 39א",
        "ReferenceQuote": "לפי סעיף 39א לחוק יסודות התקציב"
      }
    ],
    "Amendments": [],
    "AdditionalKeywords": [
      "חקיקה",
      "תקציב",
      "הערכה תקציבית"
    ],
    "Topics": [
      "בהכינה הצעת חוק שאינה הצעת חוק ממשלתית לקריאה הראשונה",
      "חבר הכנסת רשאי להציע לוועדה לקבל הערכה אחרת",
      "הערכת השר והערכה אחרת יוגשו לוועדה לפני הדיון",
      "הממשלה תמסור לוועדה את עמדתה",
      "דברי ההסבר להצעת חוק המתפרסמת לקריאה הראשונה תצוין עלותה התקציבית",
      "הונחה הצעת חוק על שולחן הכנסת, רשאית הממשלה להודיע על שינוי עמדתה",
      "הודעה על עדכון הסכומים הנקובים"
    ]
  },
  "title": "חקיקה הצריכה תקציב",
  "source_file": "תקנון הכנסת_93.md"
}