{
  "extracted_at": "2025-03-02T19:08:45.988936+00:00",
  "status": "processed",
  "context_type": "files",
  "context_name": "Knesset Bylaws (תקנון הכנסת) and related laws",
  "source_content": "**ישיבות הכנסת**\n\nמקור: חלק ג׳ - עבודת הכנסת / פרק ראשון - ישיבות / סעיף 19\nקישור: https://he.wikisource.org/wiki/תקנון_הכנסת#סעיף_19\n\n * (א) \n   * (1) הכנסת תקיים ישיבות בימים ב׳ ו־ג׳ החל בשעה 16:00, וביום ד׳ החל בשעה 11:00; יושב ראש הכנסת, באישור ועדת הכנסת, רשאי לשנות את זמניה של ישיבה, לבטל ישיבה ולקבוע ישיבה נוספת ואת זמניה – בין באחד הימים האמורים ובין ביום אחר שאינו מועד ממועדי ישראל המפורטיםבסעיף 18א(א) לפקודת סדרי השלטון והמשפט.\n   * (2) יושב ראש הכנסת רשאי לקבוע הפסקה במהלכה של ישיבת הכנסת.\n * (ב) ראה יושב ראש הכנסת כי התרחש אירוע בעל חשיבות יוצאת דופן המחייב את כינוס הכנסת לישיבה דחופה החורגת מסדר היום השבועי, רשאי הוא, לאחר התייעצות עם יושב ראש ועדת הכנסת, לכנס את הכנסת לדיון באירוע כאמור, והוא יקבע את סדרי הדיון בישיבה.\n * (ג) יושב ראש הכנסת רשאי לקבוע ישיבה לציון מאורע, והוא יקבע את סדרי הדיון בה.\n * (ד) בכל ישיבה של הכנסת ובמשך כל הישיבה, יהיה נוכח לפחות אחד משרי הממשלה.",
  "document_type": "תקנון הכנסת",
  "extracted_data": {
    "DocumentMetadata": {
      "DocumentTitle": "ישיבות הכנסת",
      "PublicationDate": "",
      "OfficialSource": "חלק ג׳ - עבודת הכנסת / פרק ראשון - ישיבות / סעיף 19",
      "ReferenceLinks": [
        "https://he.wikisource.org/wiki/תקנון_הכנסת#סעיף_19"
      ],
      "Language": "עברית",
      "Version": "",
      "ClauseRepresentation": "main clause",
      "OfficialRoles": [
        {
          "Role": "יושב ראש הכנסת",
          "ClauseLocation": "(א)",
          "Quote": "יושב ראש הכנסת, באישור ועדת הכנסת, רשאי לשנות את זמניה של ישיבה, לבטל ישיבה ולקבוע ישיבה נוספת"
        },
        {
          "Role": "יושב ראש הכנסת",
          "ClauseLocation": "(ב)",
          "Quote": "ראה יושב ראש הכנסת כי התרחש אירוע בעל חשיבות יוצאת דופן המחייב את כינוס הכנסת לישיבה דחופה"
        },
        {
          "Role": "יושב ראש הכנסת",
          "ClauseLocation": "(ג)",
          "Quote": "יושב ראש הכנסת רשאי לקבוע ישיבה לציון מאורע"
        },
        {
          "Role": "שרים הממשלה",
          "ClauseLocation": "(ד)",
          "Quote": "יהיה נוכח לפחות אחד משרי הממשלה"
        }
      ],
      "OfficialOrganizations": [
        {
          "Organization": "ועדת הכנסת",
          "ClauseLocation": "(א)",
          "Quote": "באישור ועדת הכנסת"
        }
      ],
      "Placenames": [],
      "Description": "המסמך מתאר את כללי כינוס ישיבות הכנסת וזמני הישיבות."
    },
    "LegalReferences": [
      {
        "ReferenceTitle": "פקודת סדרי השלטון והמשפט",
        "ReferenceText": "סעיף 18א(א)",
        "ReferenceQuote": "המועדים המפורטים בסעיף 18א(א) לפקודת סדרי השלטון והמשפט"
      }
    ],
    "Amendments": [],
    "AdditionalKeywords": [
      "ישיבות",
      "כנסת",
      "יושב ראש",
      "ועדת הכנסת",
      "שרים"
    ],
    "Topics": [
      "הכנסת תקיים ישיבות בימים ב׳ ו־ג׳ החל בשעה 16:00, וביום ד׳ החל בשעה 11:00",
      "יושב ראש הכנסת רשאי לקבוע הפסקה במהלכה של ישיבת הכנסת",
      "יושב ראש הכנסת רשאי לכנס את הכנסת לדיון באירוע בעל חשיבות יוצאת דופן",
      "יושב ראש הכנסת רשאי לקבוע ישיבה לציון מאורע",
      "יהיה נוכח לפחות אחד משרי הממשלה בכל ישיבה"
    ]
  },
  "title": "ישיבות הכנסת",
  "source_file": "תקנון הכנסת_19.md"
}