{
  "extracted_at": "2025-03-02T19:12:01.360985+00:00",
  "status": "processed",
  "context_type": "files",
  "context_name": "Knesset Bylaws (תקנון הכנסת) and related laws",
  "source_content": "**ציון זכרם של נפטרים**\n\nמקור: חלק ג׳ - עבודת הכנסת / פרק ראשון - ישיבות / סעיף 24\nקישור: https://he.wikisource.org/wiki/תקנון_הכנסת#סעיף_24\n\n * (א) נפטר חבר הכנסת לשעבר תכבד הכנסת את זכרו בקימה באחת הישיבות הסמוכות לפטירתו; יושב ראש הכנסת יישא דברים לזכר הנפטר והוא רשאי לאפשר לחברי כנסת נוספים לשאת דברים, במספר ובמסגרת זמן שיקבע.\n * (ב) נפטר נשיא המדינה, חבר הכנסת, שר או סגן שר, בעת כהונתו, או נפטר נשיא המדינה לשעבר, יושב ראש הכנסת לשעבר או ראש הממשלה לשעבר, תקיים הכנסת ישיבה לזכרו ותכבד את זכרו בקימה; יושב ראש הכנסת יפתח את הישיבה בדברים לזכר הנפטר ויאפשר לחברי כנסת נוספים לשאת דברים, במספר ובמסגרת זמן שיקבע.",
  "document_type": "תקנון הכנסת",
  "extracted_data": {
    "DocumentMetadata": {
      "DocumentTitle": "ציון זכרם של נפטרים",
      "PublicationDate": "",
      "OfficialSource": "חלק ג׳ - עבודת הכנסת / פרק ראשון - ישיבות / סעיף 24",
      "ReferenceLinks": [
        "https://he.wikisource.org/wiki/תקנון_הכנסת#סעיף_24"
      ],
      "Language": "עברית",
      "Version": "",
      "ClauseRepresentation": "main clause",
      "OfficialRoles": [
        {
          "Role": "יושב ראש הכנסת",
          "ClauseLocation": "(א)",
          "Quote": "יושב ראש הכנסת יישא דברים לזכר הנפטר"
        },
        {
          "Role": "יושב ראש הכנסת",
          "ClauseLocation": "(ב)",
          "Quote": "יושב ראש הכנסת יפתח את הישיבה בדברים לזכר הנפטר"
        }
      ],
      "OfficialOrganizations": [
        {
          "Organization": "הכנסת",
          "ClauseLocation": "(א)",
          "Quote": "תכבד הכנסת את זכרו"
        },
        {
          "Organization": "הכנסת",
          "ClauseLocation": "(ב)",
          "Quote": "תקיים הכנסת ישיבה לזכרו"
        }
      ],
      "Placenames": [],
      "Description": "המסמך עוסק בכיצד הכנסת מכבדת את זכרם של נפטרים."
    },
    "LegalReferences": [],
    "Amendments": [],
    "AdditionalKeywords": [
      "נפטר",
      "חבר הכנסת",
      "יושב ראש הכנסת",
      "ישיבה"
    ],
    "Topics": [
      "נפטר חבר הכנסת לשעבר תכבד הכנסת את זכרו",
      "נפטר נשיא המדינה, חבר הכנסת, שר או סגן שר"
    ]
  },
  "title": "ציון זכרם של נפטרים",
  "source_file": "תקנון הכנסת_24.md"
}