{
  "extracted_at": "2025-03-02T19:30:11.038888+00:00",
  "status": "processed",
  "context_type": "files",
  "context_name": "Knesset Bylaws (תקנון הכנסת) and related laws",
  "source_content": "**סדרי דיון מיוחדים בוועדת הכנסת**\n\nמקור: חלק ח׳ - ועדות הכנסת / פרק רביעי - ישיבות הוועדות / סעיף 116\nקישור: https://he.wikisource.org/wiki/תקנון_הכנסת#סעיף_116\n\n * (א) סדרי דיון המפורטים בסעיף זה יחולו בעת שוועדת הכנסת דנה באלה:\n   * (1) קביעת חסינות או נטילתה או נטילת זכות מחבר הכנסת או הטלת סייגים על יכולתו למלא תפקידים מסוימים בכנסת או מטעמה, לרבות השעיה מאותם תפקידים או העברתו מכהונה בהם;\n   * (2) קביעה כי חבר הכנסת פרש מסיעתו;\n   * (3) שלילת תשלומים מחבר הכנסת או חבר הכנסת לשעבר;\n   * (4) הפסקת כהונה של חבר הכנסת.\n * (ב) חבר הכנסת שהוא חבר ועדת הכנסת או ממלא מקום בה לא ישתתף כחבר הוועדה בדיונים ובהצבעות בעניינו, ולעניין מילוי מקומו יחולו הוראותסעיפים 103ו־104.\n * (ג) חבר הכנסת שעניינו נדון בוועדה רשאי להיות מיוצג בוועדה על ידי עורך דין או על ידי חבר כנסת אחר.\n * (ד) \n   * (1) רק חבר הכנסת שהשתתף בכל הישיבות שבהן התקיים דיון מהותי בנושא מהנושאים המנויים בסעיף קטן (א) (בסעיף זה – ישיבה מהותית) רשאי להשתתף בהצבעה; לעניין זה יראו נוכחות לפחות במחצית ממשכה של ישיבה כהשתתפות.\n   * (2) על אף האמור בפסקה (1), הודיע חבר הכנסת לפני ישיבה מהותית כי נבצר ממנו להשתתף בה מסיבה רפואית או מסיבה מוצדקת אחרת, רשאית ועדת הכנסת, במועד קיומה של הישיבה האמורה, לקבוע כי היעדרותו כאמור לא תמנע ממנו להשתתף בהצבעה, ובלבד שהשתתף במחצית לפחות ממספר הישיבות המהותיות באותו נושא.\n   * (3) החלה ועדת הכנסת לדון בנושא מהנושאים המנויים בסעיף קטן (א), ונבצר מחבר הכנסת להשתתף בהמשך הדיונים מסיבה רפואית או מסיבה מוצדקת אחרת, שוועדת הכנסת אישרה, רשאי חבר כנסת אחר למלא את מקומו בהמשך הדיונים, לפי הוראותסעיפים 103ו־104, ויחולו על חבר הכנסת האחר הוראות פסקאות (1) ו־(2) לגבי התקופה שממועד החלטת ועדת הכנסת.\n * (ה) יושב ראש ועדת הכנסת יודיע לחברי הוועדה מראש על מועדי הישיבות; התקיימה יותר מישיבה מהותית אחת, יעמיד יושב ראש ועדת הכנסת את כל הפרוטוקולים של הישיבות המהותיות לעיונם של חברי הכנסת הרשאים להשתתף בהצבעה.\n * (ו) לא תהיה התייעצות סיעתית בדיון לפי סעיף זה.",
  "document_type": "תקנון הכנסת",
  "extracted_data": {
    "DocumentMetadata": {
      "DocumentTitle": "סדרי דיון מיוחדים בוועדת הכנסת",
      "PublicationDate": "",
      "OfficialSource": "חלק ח׳ - ועדות הכנסת / פרק רביעי - ישיבות הוועדות / סעיף 116",
      "ReferenceLinks": [
        "https://he.wikisource.org/wiki/תקנון_הכנסת#סעיף_116"
      ],
      "Language": "עברית",
      "Version": "",
      "ClauseRepresentation": "main clause",
      "OfficialRoles": [
        {
          "Role": "יושב ראש ועדת הכנסת",
          "ClauseLocation": "(ה)",
          "Quote": "יושב ראש ועדת הכנסת יודיע לחברי הוועדה מראש על מועדי הישיבות"
        }
      ],
      "OfficialOrganizations": [
        {
          "Organization": "ועדת הכנסת",
          "ClauseLocation": "(א)",
          "Quote": "סדרי דיון המפורטים בסעיף זה יחולו בעת שוועדת הכנסת דנה באלה"
        }
      ],
      "Placenames": [],
      "Description": "המסמך מפרט את סדרי הדיון המיוחדים בוועדת הכנסת בנושאים שונים הקשורים לחברי הכנסת."
    },
    "LegalReferences": [],
    "Amendments": [],
    "AdditionalKeywords": [
      "חסינות",
      "השעיה",
      "שלילת תשלומים",
      "כהונה",
      "ייצוג",
      "הצבעה"
    ],
    "Topics": [
      "סדרי דיון המפורטים בסעיף זה יחולו בעת שוועדת הכנסת דנה באלה",
      "חבר הכנסת שהוא חבר ועדת הכנסת או ממלא מקום בה לא ישתתף כחבר הוועדה בדיונים ובהצבעות בעניינו",
      "חבר הכנסת שעניינו נדון בוועדה רשאי להיות מיוצג בוועדה על ידי עורך דין או על ידי חבר כנסת אחר",
      "רק חבר הכנסת שהשתתף בכל הישיבות שבהן התקיים דיון מהותי בנושא מהנושאים המנויים בסעיף קטן (א) רשאי להשתתף בהצבעה",
      "יושב ראש ועדת הכנסת יודיע לחברי הוועדה מראש על מועדי הישיבות",
      "לא תהיה התייעצות סיעתית בדיון לפי סעיף זה"
    ]
  },
  "title": "סדרי דיון מיוחדים בוועדת הכנסת",
  "source_file": "תקנון הכנסת_116.md"
}