{
  "extracted_at": "2025-03-02T19:35:59.391657+00:00",
  "status": "processed",
  "context_type": "files",
  "context_name": "Knesset Bylaws (תקנון הכנסת) and related laws",
  "source_content": "**השעיה מכהונה מחמת עבירה לפיסעיף 7 לחוק הכנסת**\n\nמקור: חלק ב׳ - ארגון הכנסת / פרק ראשון - יושב ראש הכנסת וסגניו / סעיף 4\nקישור: https://he.wikisource.org/wiki/תקנון_הכנסת#סעיף_4\n\n * (א) הושעה יושב ראש הכנסת או סגן ליושב ראש הכנסת, או שנקבעו סייגים לכהונתו, לפי הוראותסעיף 7 לחוק הכנסת, תסתיים ההשעיה או יבוטלו הסייגים עם מתן פסק דין סופי, המזכה אותו או שאינו קובע שיש עם העבירה קלון, ואם נקבע שתהיה לו חסינות בפני דין פלילי – עם תום תקופת כהונתה של אותה כנסת, והכל אם לא קבעה הכנסת, לפי הצעת ועדת הכנסת, תקופה קצרה יותר להשעיה או לסייגים.\n * (ב) הציעה ועדת הכנסת לכנסת להשעות מכהונתו את יושב ראש הכנסת או סגן ליושב ראש הכנסת או לקבוע סייגים לכהונתו, יציג יושב ראש ועדת הכנסת את הצעת ועדת הכנסת לפני הכנסת, חבר הכנסת שההצעה נוגעת אליו רשאי להשיב, כל אחד מהם במסגרת זמן שלא תעלה על 15 דקות, והכנסת תחליט בלא דיון.",
  "document_type": "תקנון הכנסת",
  "extracted_data": {
    "DocumentMetadata": {
      "DocumentTitle": "השעיה מכהונה מחמת עבירה לפיסעיף 7 לחוק הכנסת",
      "PublicationDate": "",
      "OfficialSource": "חלק ב׳ - ארגון הכנסת / פרק ראשון - יושב ראש הכנסת וסגניו / סעיף 4",
      "ReferenceLinks": [
        "https://he.wikisource.org/wiki/תקנון_הכנסת#סעיף_4"
      ],
      "Language": "עברית",
      "Version": "",
      "ClauseRepresentation": "main clause",
      "OfficialRoles": [
        {
          "Role": "יושב ראש הכנסת",
          "ClauseLocation": "(א)",
          "Quote": "הושעה יושב ראש הכנסת או סגן ליושב ראש הכנסת"
        },
        {
          "Role": "סגן ליושב ראש הכנסת",
          "ClauseLocation": "(א)",
          "Quote": "הושעה יושב ראש הכנסת או סגן ליושב ראש הכנסת"
        },
        {
          "Role": "יושב ראש ועדת הכנסת",
          "ClauseLocation": "(ב)",
          "Quote": "יציג יושב ראש ועדת הכנסת את הצעת ועדת הכנסת"
        }
      ],
      "OfficialOrganizations": [
        {
          "Organization": "ועדת הכנסת",
          "ClauseLocation": "(ב)",
          "Quote": "הציעה ועדת הכנסת לכנסת להשעות מכהונתו"
        },
        {
          "Organization": "הכנסת",
          "ClauseLocation": "(ב)",
          "Quote": "הכנסת תחליט בלא דיון"
        }
      ],
      "Placenames": [],
      "Description": "המסמך עוסק בהשעיה מכהונה של יושב ראש הכנסת או סגן יושב ראש הכנסת בעקבות עבירה."
    },
    "LegalReferences": [
      {
        "ReferenceTitle": "חוק הכנסת",
        "ReferenceText": "סעיף 7 לחוק הכנסת",
        "ReferenceQuote": "לפי הוראות סעיף 7 לחוק הכנסת"
      }
    ],
    "Amendments": [],
    "AdditionalKeywords": [
      "השעיה",
      "כהונה",
      "עבירה",
      "חסינות",
      "פסק דין"
    ],
    "Topics": [
      "הושעה יושב ראש הכנסת או סגן ליושב ראש הכנסת, או שנקבעו סייגים לכהונתו.",
      "הצעת ועדת הכנסת להשעיה או לקביעת סייגים לכהונה."
    ]
  },
  "title": "השעיה מכהונה מחמת עבירה לפיסעיף 7 לחוק הכנסת",
  "source_file": "תקנון הכנסת_4.md"
}